Workbook
Name AntennaGrowth: Assumptions!$B$24
Name BldgSF: Assumptions!$B$5
Name CatchupGP: Assumptions!$B$71
Name CloseDate: Assumptions!$B$12
Name DispCost: Assumptions!$B$17
Name ExitCap: Assumptions!$B$16
Name ExpGrowth: Assumptions!$B$21
Name GPShare: Assumptions!$B$67
Name GPTarget: Assumptions!$B$72
Name HoldMonths: Assumptions!$B$15
Name LeaseTable: Assumptions!$A$56:$J$59
Name LPShare: Assumptions!$B$68
Name MgmtFeePct: Assumptions!$B$41
Name ParkGrowth: Assumptions!$B$23
Name PrefMo: Assumptions!$B$70
Name PurchasePrice: Assumptions!$B$6
Name ReimbPool: Assumptions!$B$40
Name RenewDiscount: Assumptions!$B$62
Name RenoBudget: Assumptions!$B$50
Name RenoDuration: Assumptions!$B$51
Name RentGrowth: Assumptions!$B$20
Name ReservesGrowth: Assumptions!$B$25
Name ReservesPSF: Assumptions!$B$42
Name ResidGP: Assumptions!$B$73
Name ResidLP: Assumptions!$B$74
Name SpecBuildout: Assumptions!$B$64
Name SpecTI: Assumptions!$B$63

Sheet Assumptions
A1: SouthPark Centre
A2: 4800 Sharon Road, Charlotte, NC 2821 | B2: Class B+ Multi-Tenant Office | D2: All inputs blue, formulas black
A4: PROPERTY
A5: Building SF (RSF) | B5: 280000 | C5: Total rentable area
A6: Purchase Price | B6: 50000000 | C6: VP revised down from Broker Guidance of $52.0m
A7: Acquisition Costs (% of gross) | B7: 0.03
A8: Price per SF | B8: =B6/B5 -> 178.57143 | C8: = Price / SF
A9: Stories | B9: 8
A10: Floor Plate (SF) | B10: 35000
A11: Parking Spaces | B11: 1176 | C11: 4.2 per 1,000 SF
A12: Close Date | B12: 46265 | C12: Projection month 0 = this month
A14: HOLD & EXIT
A15: Hold Period (months) | B15: 60 | C15: 5 years
A16: Exit Cap Rate | B16: 0.0775
A17: Disposition Costs (% of gross) | B17: 0.02
A19: GROWTH & ESCALATION
A20: Rent Growth (annual) | B20: 0.027 | C20: 30-yr US CPI avg per Standard Guide
A21: Expense Growth (annual) | B21: 0.027
A22: Stabilised Occupancy | B22: 0.88
A23: Parking Income Growth | B23: 0.025
A24: Antenna Income Growth | B24: 0.02
A25: Building Reserves Growth | B25: 0.025
A27: OPERATING EXPENSES (Annual, Year 1) | C27: Reimbursable?
A28: Real Estate Taxes | B28: 742000 | C28: Yes
A29: Insurance | B29: 210000 | C29: Yes
A30: Utilities | B30: 700000 | C30: Yes
A31: Repairs & Maintenance | B31: 490000 | C31: Yes
A32: Janitorial | B32: 378000 | C32: Yes
A33: Landscaping | B33: 84000 | C33: Yes
A34: Security | B34: 112000 | C34: Yes
A35: Elevator | B35: 50400 | C35: Yes
A36: HVAC | B36: 98000 | C36: Yes
A37: General & Admin | B37: 67200 | C37: Yes
A38: Marketing | B38: 39200 | C38: No
A39: Total OpEx (ex-mgmt fee) | B39: =SUM(B28:B38) -> 2970800
A40: Reimbursable OpEx Pool | B40: =SUMIF(C28:C38,"Yes",B28:B38) -> 2931600 | C40: Excl. marketing & mgmt fee
A41: Management Fee (% of EGI) | B41: 0.035
A42: Building Reserves ($/SF/yr) | B42: 0.5
A44: OTHER INCOME (Annual) | C44: Growth
A45: Parking Income | B45: 230000 | C45: =B23 -> 0.025
A46: Antenna Income (T-Mobile) | B46: 32000 | C46: =B24 -> 0.02
A47: Storage Income | B47: 20000 | C47: Flat
A49: RENOVATION
A50: Renovation Budget (Pinnacle) | B50: =SUM('CapEx Schedule'!B8:B36) -> 7500000
A51: Renovation Sensitivity | B51: 0 | C51: Positive numbers increase renovation budget
A54: LEASING ASSUMPTIONS BY SIZE (Standard Guide) | L54: <-- Sensi input
A55: Min SF | B55: Bucket Label | C55: Mkt Rent $/SF | D55: Renew % | E55: Downtime (mo) | F55: New TI $/SF | G55: Ren TI $/SF | H55: LC % | I55: Free New (mo) | J55: Free Ren (mo) | K55: Downtime (mo) - base reference
A56: 0 | B56: <2,000 | C56: 24 | D56: 0.5 | E56: =K56+$K$54 -> 7 | F56: 28 | G56: 10 | H56: 0.06 | I56: 3 | J56: 1 | K56: 7
A57: 2000 | B57: 2,000-5,000 | C57: 25 | D57: 0.55 | E57: =K57+$K$54 -> 6 | F57: 32 | G57: 12 | H57: 0.06 | I57: 2 | J57: 1 | K57: 6
A58: 5000 | B58: 5,000-15,000 | C58: 25.5 | D58: 0.65 | E58: =K58+$K$54 -> 5 | F58: 36 | G58: 16 | H58: 0.05 | I58: 2 | J58: 1 | K58: 5
A59: 15000 | B59: >15,000 | C59: 25 | D59: 0.75 | E59: =K59+$K$54 -> 4 | F59: 40 | G59: 20 | H59: 0.04 | I59: 2 | J59: 0 | K59: 4
A61: Renewal market rent = 95% of new-lease market rent
A62: Renewal Discount % | B62: 0.95
A63: Spec Suite TI ($/SF) | B63: 40 | C63: VP-revised from $35
A64: Spec Suite Buildout Duration (mo) | B64: 6
A66: JV / EQUITY WATERFALL
A67: GP Equity Share | B67: 0.1 | C67: Contributions called 90/10 LP/GP
A68: LP Equity Share | B68: =1-B67 -> 0.9
A69: Preferred Return (effective annual) | B69: 0.08 | C69: Compounds monthly; accrues on GP and LP capital
A70: Monthly Pref Rate | B70: =(1+B69)^(1/12)-1 -> 0.0064340301 | C70: =(1+annual)^(1/12)-1
A71: Catch-up — GP Share of Catch-up Dists | B71: 0.5 | C71: 50/50 GP/LP during catch-up
A72: Catch-up — GP Target Share of Profits | B72: 0.2 | C72: Catch-up runs until GP has 20% of cumulative profit
A73: Residual Split — GP | B73: 0.2
A74: Residual Split — LP | B74: =1-B73 -> 0.8
A77: SENSITIVITY TABLES - Levered Deal-level Returns (IRR & MoIC)
B79: Purchase Price vs. Exit Cap Rate
C80: Exit Cap Rate
C81: -0.005 | D81: -0.0025 | E81: 0 | F81: 0.0025 | G81: 0.005
B82: =TEXT('Property Cash Flow'!$B$72,"0.00%")&" / "&TEXT('Property Cash Flow'!$B$75,"0.00x") -> 21.21% / 2.11x | C82: =+$E82+C81 -> 0.0725 | D82: =+$E82+D81 -> 0.075 | E82: 0.0775 | F82: =+$E82+F81 -> 0.08 | G82: =+$E82+G81 -> 0.0825
A83: Purchase Price | B83: =B84-10^6 -> 46000000 | C83: 32.84% / 2.79x | D83: 30.28% / 2.64x | E83: 27.82% / 2.49x | F83: 25.45% / 2.35x | G83: 23.17% / 2.22x
B84: =B85-10^6 -> 47000000 | C84: 31.13% / 2.69x | D84: 28.57% / 2.53x | E84: 26.11% / 2.39x | F84: 23.75% / 2.25x | G84: 21.47% / 2.12x
B85: =B86-10^6 -> 48000000 | C85: 29.45% / 2.59x | D85: 26.90% / 2.44x | E85: 24.44% / 2.29x | F85: 22.08% / 2.16x | G85: 19.81% / 2.02x
B86: =B87-10^6 -> 49000000 | C86: 27.81% / 2.49x | D86: 25.26% / 2.34x | E86: 22.81% / 2.20x | F86: 20.46% / 2.07x | G86: 18.19% / 1.89x
B87: 50000000 | C87: 26.20% / 2.40x | D87: 23.65% / 2.25x | E87: 21.21% / 2.11x | F87: 18.86% / 1.96x | G87: 16.61% / 1.77x
B90: Construction Cost Overrun vs. Lease-up Delay
C91: Construction Cost Overrun
B92: =TEXT('Property Cash Flow'!$B$72,"0.00%")&" / "&TEXT('Property Cash Flow'!$B$75,"0.00x") -> 21.21% / 2.11x | C92: 0 | D92: =C92+10% -> 0.1 | E92: =D92+10% -> 0.2 | F92: =E92+10% -> 0.3 | G92: =F92+10% -> 0.4
A93: Lease-up Delay | B93: 0 | C93: 21.21% / 2.11x | D93: 20.15% / 2.05x | E93: 19.11% / 1.99x | F93: 18.07% / 1.91x | G93: 17.04% / 1.82x
B94: 3 | C94: 21.15% / 2.01x | D94: 20.09% / 1.95x | E94: 19.03% / 1.90x | F94: 17.98% / 1.85x | G94: 16.94% / 1.79x
B95: 6 | C95: 21.31% / 1.97x | D95: 20.23% / 1.92x | E95: 19.16% / 1.87x | F95: 18.10% / 1.82x | G95: 17.05% / 1.77x
B96: 9 | C96: 20.31% / 1.99x | D96: 19.26% / 1.90x | E96: 18.22% / 1.83x | F96: 17.19% / 1.75x | G96: 16.18% / 1.69x
B99: Purchase Price vs. Rent Growth
C100: Rent Growth
C101: =D101-0.5% -> -0.02 | D101: =E101-0.5% -> -0.015 | E101: =F101-0.5% -> -0.01 | F101: =G101-0.5% -> -0.005 | G101: 0 | H101: =G101+0.5% -> 0.005 | I101: =H101+0.5% -> 0.01 | J101: =I101+0.5% -> 0.015 | K101: =J101+0.5% -> 0.02
B102: =TEXT('Property Cash Flow'!$B$72,"0.00%")&" / "&TEXT('Property Cash Flow'!$B$75,"0.00x") -> 21.21% / 2.11x | C102: =+$G102+C101 -> 0.007 | D102: =+$G102+D101 -> 0.012 | E102: =+$G102+E101 -> 0.017 | F102: =+$G102+F101 -> 0.022 | G102: 0.027 | H102: =+$G102+H101 -> 0.032 | I102: =+$G102+I101 -> 0.037 | J102: =+$G102+J101 -> 0.042 | K102: =+$G102+K101 -> 0.047
A103: Purchase Price | B103: =B104-10^6 -> 46000000 | C103: 17.81% / 1.85x | D103: 20.33% / 2.05x | E103: 22.84% / 2.19x | F103: 25.33% / 2.34x | G103: 27.82% / 2.49x | H103: 30.28% / 2.64x | I103: 32.74% / 2.80x | J103: 35.18% / 2.96x | K103: 37.61% / 3.12x
B104: =B105-10^6 -> 47000000 | C104: 16.13% / 1.73x | D104: 18.64% / 1.93x | E104: 21.14% / 2.10x | F104: 23.63% / 2.24x | G104: 26.11% / 2.39x | H104: 28.58% / 2.54x | I104: 31.03% / 2.69x | J104: 33.47% / 2.85x | K104: 35.89% / 3.01x
B105: =B106-10^6 -> 48000000 | C105: 14.49% / 1.62x | D105: 16.99% / 1.80x | E105: 19.48% / 2.01x | F105: 21.97% / 2.15x | G105: 24.44% / 2.29x | H105: 26.90% / 2.44x | I105: 29.35% / 2.59x | J105: 31.79% / 2.75x | K105: 34.21% / 2.90x
B106: =B107-10^6 -> 49000000 | C106: 12.88% / 1.52x | D106: 15.38% / 1.68x | E106: 17.86% / 1.87x | F106: 20.34% / 2.06x | G106: 22.81% / 2.20x | H106: 25.27% / 2.35x | I106: 27.71% / 2.49x | J106: 30.14% / 2.65x | K106: 32.56% / 2.80x
B107: 50000000 | C107: 11.32% / 1.44x | D107: 13.80% / 1.58x | E107: 16.28% / 1.75x | F107: 18.75% / 1.96x | G107: 21.21% / 2.11x | H107: 23.66% / 2.25x | I107: 26.10% / 2.40x | J107: 28.53% / 2.55x | K107: 30.95% / 2.70x

Sheet Rent Roll
B1: SouthPark Centre — Rent Roll
O3: Cols N–U: occupied = expiry mo# + size lookups; vacant = lease-up commencement mo# (blue) + size lookups
A4: Size Rank | B4: # | C4: Tenant | D4: Suite | E4: Flr | F4: SF | G4: Rent $/SF | H4: Annual Rent | I4: Esc % | J4: Esc Mo | K4: Start | L4: Expiry | M4: Renewal | N4: Status | O4: Expiry Mo# | P4: Size Key | Q4: Bucket | R4: Mkt Rent $/SF | S4: Downtime | T4: New TI $/SF | U4: LC % | V4: Free New | W4: Renew % | X4: Blend Rent $/SF | Y4: 1st Esc Date >close
A5: =RANK(F5,$F$5:$F$32) -> 1 | B5: 1 | C5: Meridian Financial Group | D5: 600-820 | E5: 6-8 | F5: 76000 | G5: 19.5 | H5: =F5*G5 -> 1482000 | I5: 0.025 | J5: 11 | K5: 42675 | L5: 46326 | M5: None | N5: Departing | O5: =DATEDIF(CloseDate,L5,"m")+1 -> 3 | P5: =LOOKUP(F5,{0,2000,5000,15000}) -> 15000 | Q5: =VLOOKUP(P5,LeaseTable,2,FALSE) -> >15,000 | R5: =VLOOKUP(P5,LeaseTable,3,FALSE) -> 25 | S5: =VLOOKUP(P5,LeaseTable,5,FALSE) -> 4 | T5: =VLOOKUP(P5,LeaseTable,6,FALSE) -> 40 | U5: =VLOOKUP(P5,LeaseTable,8,FALSE) -> 0.04 | V5: =VLOOKUP(P5,LeaseTable,9,FALSE) -> 2 | W5: 0 | X5: =R5*(W5*RenewDiscount+(1-W5)) -> 25 | Y5: =IF(J5="","",EOMONTH(DATE(YEAR(CloseDate)+IF(J5>MONTH(CloseDate),0,1),J5,1),0)) -> 46356
A6: =RANK(F6,$F$5:$F$32) -> 2 | B6: 2 | C6: Southeast Regional Health | D6: 200 | E6: 2 | F6: 24000 | G6: 21.5 | H6: =F6*G6 -> 516000 | I6: 0.03 | J6: 4 | K6: 43556 | L6: 47208 | M6: 1x5yr | N6: Occupied | O6: =DATEDIF(CloseDate,L6,"m")+1 -> 32 | P6: =LOOKUP(F6,{0,2000,5000,15000}) -> 15000 | Q6: =VLOOKUP(P6,LeaseTable,2,FALSE) -> >15,000 | R6: =VLOOKUP(P6,LeaseTable,3,FALSE) -> 25 | S6: =VLOOKUP(P6,LeaseTable,5,FALSE) -> 4 | T6: =VLOOKUP(P6,LeaseTable,6,FALSE) -> 40 | U6: =VLOOKUP(P6,LeaseTable,8,FALSE) -> 0.04 | V6: =VLOOKUP(P6,LeaseTable,9,FALSE) -> 2 | W6: =VLOOKUP(P6,LeaseTable,4,FALSE) -> 0.75 | X6: =R6*(W6*RenewDiscount+(1-W6)) -> 24.0625 | Y6: =IF(J6="","",EOMONTH(DATE(YEAR(CloseDate)+IF(J6>MONTH(CloseDate),0,1),J6,1),0)) -> 46507
A7: =RANK(F7,$F$5:$F$32) -> 3 | B7: 3 | C7: Carter & Associates Law | D7: 310 | E7: 3 | F7: 12000 | G7: 22 | H7: =F7*G7 -> 264000 | I7: 0.025 | J7: 10 | K7: 44835 | L7: 46660 | M7: None | N7: Occupied | O7: =DATEDIF(CloseDate,L7,"m")+1 -> 13 | P7: =LOOKUP(F7,{0,2000,5000,15000}) -> 5000 | Q7: =VLOOKUP(P7,LeaseTable,2,FALSE) -> 5,000-15,000 | R7: =VLOOKUP(P7,LeaseTable,3,FALSE) -> 25.5 | S7: =VLOOKUP(P7,LeaseTable,5,FALSE) -> 5 | T7: =VLOOKUP(P7,LeaseTable,6,FALSE) -> 36 | U7: =VLOOKUP(P7,LeaseTable,8,FALSE) -> 0.05 | V7: =VLOOKUP(P7,LeaseTable,9,FALSE) -> 2 | W7: =VLOOKUP(P7,LeaseTable,4,FALSE) -> 0.65 | X7: =R7*(W7*RenewDiscount+(1-W7)) -> 24.67125 | Y7: =IF(J7="","",EOMONTH(DATE(YEAR(CloseDate)+IF(J7>MONTH(CloseDate),0,1),J7,1),0)) -> 46326
A8: =RANK(F8,$F$5:$F$32) -> 4 | B8: 4 | C8: Pinnacle Wealth Advisors | D8: 320 | E8: 3 | F8: 11000 | G8: 20.25 | H8: =F8*G8 -> 222750 | I8: 0.02 | J8: 1 | K8: 45292 | L8: 47118 | M8: 1x3yr | N8: Occupied | O8: =DATEDIF(CloseDate,L8,"m")+1 -> 29 | P8: =LOOKUP(F8,{0,2000,5000,15000}) -> 5000 | Q8: =VLOOKUP(P8,LeaseTable,2,FALSE) -> 5,000-15,000 | R8: =VLOOKUP(P8,LeaseTable,3,FALSE) -> 25.5 | S8: =VLOOKUP(P8,LeaseTable,5,FALSE) -> 5 | T8: =VLOOKUP(P8,LeaseTable,6,FALSE) -> 36 | U8: =VLOOKUP(P8,LeaseTable,8,FALSE) -> 0.05 | V8: =VLOOKUP(P8,LeaseTable,9,FALSE) -> 2 | W8: =VLOOKUP(P8,LeaseTable,4,FALSE) -> 0.65 | X8: =R8*(W8*RenewDiscount+(1-W8)) -> 24.67125 | Y8: =IF(J8="","",EOMONTH(DATE(YEAR(CloseDate)+IF(J8>MONTH(CloseDate),0,1),J8,1),0)) -> 46418
A9: =RANK(F9,$F$5:$F$32) -> 5 | B9: 5 | C9: TechBridge Solutions | D9: 410 | E9: 4 | F9: 10500 | G9: 21.75 | H9: =F9*G9 -> 228375 | I9: 0.03 | J9: 7 | K9: 45839 | L9: 47664 | M9: None | N9: Occupied | O9: =DATEDIF(CloseDate,L9,"m")+1 -> 46 | P9: =LOOKUP(F9,{0,2000,5000,15000}) -> 5000 | Q9: =VLOOKUP(P9,LeaseTable,2,FALSE) -> 5,000-15,000 | R9: =VLOOKUP(P9,LeaseTable,3,FALSE) -> 25.5 | S9: =VLOOKUP(P9,LeaseTable,5,FALSE) -> 5 | T9: =VLOOKUP(P9,LeaseTable,6,FALSE) -> 36 | U9: =VLOOKUP(P9,LeaseTable,8,FALSE) -> 0.05 | V9: =VLOOKUP(P9,LeaseTable,9,FALSE) -> 2 | W9: =VLOOKUP(P9,LeaseTable,4,FALSE) -> 0.65 | X9: =R9*(W9*RenewDiscount+(1-W9)) -> 24.67125 | Y9: =IF(J9="","",EOMONTH(DATE(YEAR(CloseDate)+IF(J9>MONTH(CloseDate),0,1),J9,1),0)) -> 46599
A10: =RANK(F10,$F$5:$F$32) -> 12 | B10: 6 | C10: Brightpath Insurance | D10: 330 | E10: 3 | F10: 7900 | G10: 20.75 | H10: =F10*G10 -> 163925 | I10: 0.025 | J10: 3 | K10: 43525 | L10: 47177 | M10: 1x5yr | N10: Occupied | O10: =DATEDIF(CloseDate,L10,"m")+1 -> 30 | P10: =LOOKUP(F10,{0,2000,5000,15000}) -> 5000 | Q10: =VLOOKUP(P10,LeaseTable,2,FALSE) -> 5,000-15,000 | R10: =VLOOKUP(P10,LeaseTable,3,FALSE) -> 25.5 | S10: =VLOOKUP(P10,LeaseTable,5,FALSE) -> 5 | T10: =VLOOKUP(P10,LeaseTable,6,FALSE) -> 36 | U10: =VLOOKUP(P10,LeaseTable,8,FALSE) -> 0.05 | V10: =VLOOKUP(P10,LeaseTable,9,FALSE) -> 2 | W10: =VLOOKUP(P10,LeaseTable,4,FALSE) -> 0.65 | X10: =R10*(W10*RenewDiscount+(1-W10)) -> 24.67125 | Y10: =IF(J10="","",EOMONTH(DATE(YEAR(CloseDate)+IF(J10>MONTH(CloseDate),0,1),J10,1),0)) -> 46477
A11: =RANK(F11,$F$5:$F$32) -> 6 | B11: 7 | C11: Caldwell Consulting Group | D11: 420 | E11: 4 | F11: 9500 | G11: 20.5 | H11: =F11*G11 -> 194750 | I11: 0.02 | J11: 9 | K11: 44440 | L11: 48091 | M11: 1x5yr | N11: Occupied | O11: =DATEDIF(CloseDate,L11,"m")+1 -> 61 | P11: =LOOKUP(F11,{0,2000,5000,15000}) -> 5000 | Q11: =VLOOKUP(P11,LeaseTable,2,FALSE) -> 5,000-15,000 | R11: =VLOOKUP(P11,LeaseTable,3,FALSE) -> 25.5 | S11: =VLOOKUP(P11,LeaseTable,5,FALSE) -> 5 | T11: =VLOOKUP(P11,LeaseTable,6,FALSE) -> 36 | U11: =VLOOKUP(P11,LeaseTable,8,FALSE) -> 0.05 | V11: =VLOOKUP(P11,LeaseTable,9,FALSE) -> 2 | W11: =VLOOKUP(P11,LeaseTable,4,FALSE) -> 0.65 | X11: =R11*(W11*RenewDiscount+(1-W11)) -> 24.67125 | Y11: =IF(J11="","",EOMONTH(DATE(YEAR(CloseDate)+IF(J11>MONTH(CloseDate),0,1),J11,1),0)) -> 46295
A12: =RANK(F12,$F$5:$F$32) -> 10 | B12: 8 | C12: Queen City Accounting | D12: 210 | E12: 2 | F12: 8500 | G12: 19.75 | H12: =F12*G12 -> 167875 | I12: 0.025 | J12: 2 | K12: 44958 | L12: 46783 | M12: None | N12: Occupied | O12: =DATEDIF(CloseDate,L12,"m")+1 -> 18 | P12: =LOOKUP(F12,{0,2000,5000,15000}) -> 5000 | Q12: =VLOOKUP(P12,LeaseTable,2,FALSE) -> 5,000-15,000 | R12: =VLOOKUP(P12,LeaseTable,3,FALSE) -> 25.5 | S12: =VLOOKUP(P12,LeaseTable,5,FALSE) -> 5 | T12: =VLOOKUP(P12,LeaseTable,6,FALSE) -> 36 | U12: =VLOOKUP(P12,LeaseTable,8,FALSE) -> 0.05 | V12: =VLOOKUP(P12,LeaseTable,9,FALSE) -> 2 | W12: =VLOOKUP(P12,LeaseTable,4,FALSE) -> 0.65 | X12: =R12*(W12*RenewDiscount+(1-W12)) -> 24.67125 | Y12: =IF(J12="","",EOMONTH(DATE(YEAR(CloseDate)+IF(J12>MONTH(CloseDate),0,1),J12,1),0)) -> 46446
A13: =RANK(F13,$F$5:$F$32) -> 13 | B13: 9 | C13: Monarch Marketing Group | D13: 340 | E13: 3 | F13: 7800 | G13: 21 | H13: =F13*G13 -> 163800 | I13: 0.025 | J13: 5 | K13: 43586 | L13: 47238 | M13: 1x3yr | N13: Occupied | O13: =DATEDIF(CloseDate,L13,"m")+1 -> 32 | P13: =LOOKUP(F13,{0,2000,5000,15000}) -> 5000 | Q13: =VLOOKUP(P13,LeaseTable,2,FALSE) -> 5,000-15,000 | R13: =VLOOKUP(P13,LeaseTable,3,FALSE) -> 25.5 | S13: =VLOOKUP(P13,LeaseTable,5,FALSE) -> 5 | T13: =VLOOKUP(P13,LeaseTable,6,FALSE) -> 36 | U13: =VLOOKUP(P13,LeaseTable,8,FALSE) -> 0.05 | V13: =VLOOKUP(P13,LeaseTable,9,FALSE) -> 2 | W13: =VLOOKUP(P13,LeaseTable,4,FALSE) -> 0.65 | X13: =R13*(W13*RenewDiscount+(1-W13)) -> 24.67125 | Y13: =IF(J13="","",EOMONTH(DATE(YEAR(CloseDate)+IF(J13>MONTH(CloseDate),0,1),J13,1),0)) -> 46538
A14: =RANK(F14,$F$5:$F$32) -> 15 | B14: 10 | C14: Davidson & Reed Architects | D14: 430 | E14: 4 | F14: 7200 | G14: 20.75 | H14: =F14*G14 -> 149400 | I14: 0.02 | J14: 12 | K14: 43435 | L14: 47087 | M14: None | N14: Occupied | O14: =DATEDIF(CloseDate,L14,"m")+1 -> 27 | P14: =LOOKUP(F14,{0,2000,5000,15000}) -> 5000 | Q14: =VLOOKUP(P14,LeaseTable,2,FALSE) -> 5,000-15,000 | R14: =VLOOKUP(P14,LeaseTable,3,FALSE) -> 25.5 | S14: =VLOOKUP(P14,LeaseTable,5,FALSE) -> 5 | T14: =VLOOKUP(P14,LeaseTable,6,FALSE) -> 36 | U14: =VLOOKUP(P14,LeaseTable,8,FALSE) -> 0.05 | V14: =VLOOKUP(P14,LeaseTable,9,FALSE) -> 2 | W14: =VLOOKUP(P14,LeaseTable,4,FALSE) -> 0.65 | X14: =R14*(W14*RenewDiscount+(1-W14)) -> 24.67125 | Y14: =IF(J14="","",EOMONTH(DATE(YEAR(CloseDate)+IF(J14>MONTH(CloseDate),0,1),J14,1),0)) -> 46387
A15: =RANK(F15,$F$5:$F$32) -> 16 | B15: 11 | C15: Greenway Environmental | D15: 220 | E15: 2 | F15: 6800 | G15: 19.5 | H15: =F15*G15 -> 132600 | I15: 0.025 | J15: 8 | K15: 43678 | L15: 47330 | M15: None | N15: Occupied | O15: =DATEDIF(CloseDate,L15,"m")+1 -> 36 | P15: =LOOKUP(F15,{0,2000,5000,15000}) -> 5000 | Q15: =VLOOKUP(P15,LeaseTable,2,FALSE) -> 5,000-15,000 | R15: =VLOOKUP(P15,LeaseTable,3,FALSE) -> 25.5 | S15: =VLOOKUP(P15,LeaseTable,5,FALSE) -> 5 | T15: =VLOOKUP(P15,LeaseTable,6,FALSE) -> 36 | U15: =VLOOKUP(P15,LeaseTable,8,FALSE) -> 0.05 | V15: =VLOOKUP(P15,LeaseTable,9,FALSE) -> 2 | W15: =VLOOKUP(P15,LeaseTable,4,FALSE) -> 0.65 | X15: =R15*(W15*RenewDiscount+(1-W15)) -> 24.67125 | Y15: =IF(J15="","",EOMONTH(DATE(YEAR(CloseDate)+IF(J15>MONTH(CloseDate),0,1),J15,1),0)) -> 46630
A16: =RANK(F16,$F$5:$F$32) -> 18 | B16: 12 | C16: Trellis HR Solutions | D16: 510 | E16: 5 | F16: 6200 | G16: 22.25 | H16: =F16*G16 -> 137950 | I16: 0.025 | J16: 6 | K16: 45078 | L16: 47634 | M16: 1x3yr | N16: Occupied | O16: =DATEDIF(CloseDate,L16,"m")+1 -> 46 | P16: =LOOKUP(F16,{0,2000,5000,15000}) -> 5000 | Q16: =VLOOKUP(P16,LeaseTable,2,FALSE) -> 5,000-15,000 | R16: =VLOOKUP(P16,LeaseTable,3,FALSE) -> 25.5 | S16: =VLOOKUP(P16,LeaseTable,5,FALSE) -> 5 | T16: =VLOOKUP(P16,LeaseTable,6,FALSE) -> 36 | U16: =VLOOKUP(P16,LeaseTable,8,FALSE) -> 0.05 | V16: =VLOOKUP(P16,LeaseTable,9,FALSE) -> 2 | W16: =VLOOKUP(P16,LeaseTable,4,FALSE) -> 0.65 | X16: =R16*(W16*RenewDiscount+(1-W16)) -> 24.67125 | Y16: =IF(J16="","",EOMONTH(DATE(YEAR(CloseDate)+IF(J16>MONTH(CloseDate),0,1),J16,1),0)) -> 46568
A17: =RANK(F17,$F$5:$F$32) -> 21 | B17: 13 | C17: Summit Digital Media | D17: 350 | E17: 3 | F17: 5400 | G17: 21.5 | H17: =F17*G17 -> 116100 | I17: 0.03 | J17: 11 | K17: 45231 | L17: 47057 | M17: None | N17: Occupied | O17: =DATEDIF(CloseDate,L17,"m")+1 -> 27 | P17: =LOOKUP(F17,{0,2000,5000,15000}) -> 5000 | Q17: =VLOOKUP(P17,LeaseTable,2,FALSE) -> 5,000-15,000 | R17: =VLOOKUP(P17,LeaseTable,3,FALSE) -> 25.5 | S17: =VLOOKUP(P17,LeaseTable,5,FALSE) -> 5 | T17: =VLOOKUP(P17,LeaseTable,6,FALSE) -> 36 | U17: =VLOOKUP(P17,LeaseTable,8,FALSE) -> 0.05 | V17: =VLOOKUP(P17,LeaseTable,9,FALSE) -> 2 | W17: =VLOOKUP(P17,LeaseTable,4,FALSE) -> 0.65 | X17: =R17*(W17*RenewDiscount+(1-W17)) -> 24.67125 | Y17: =IF(J17="","",EOMONTH(DATE(YEAR(CloseDate)+IF(J17>MONTH(CloseDate),0,1),J17,1),0)) -> 46356
... A23: =RANK(F23,$F$5:$F$32) -> 27 | B23: 19 | C23: Horizon Physical Therapy | D23: 110 | E23: 1 | F23: 2500 | G23: 18.5 | H23: =F23*G23 -> 46250 | I23: 0.02 | J23: 3 | K23: 44986 | L23: 46811 | M23: None | N23: Occupied | O23: =DATEDIF(CloseDate,L23,"m")+1 -> 18 | P23: =LOOKUP(F23,{0,2000,5000,15000}) -> 2000 | Q23: =VLOOKUP(P23,LeaseTable,2,FALSE) -> 2,000-5,000 | R23: =VLOOKUP(P23,LeaseTable,3,FALSE) -> 25 | S23: =VLOOKUP(P23,LeaseTable,5,FALSE) -> 6 | T23: =VLOOKUP(P23,LeaseTable,6,FALSE) -> 32 | U23: =VLOOKUP(P23,LeaseTable,8,FALSE) -> 0.06 | V23: =VLOOKUP(P23,LeaseTable,9,FALSE) -> 2 | W23: =VLOOKUP(P23,LeaseTable,4,FALSE) -> 0.55 | X23: =R23*(W23*RenewDiscount+(1-W23)) -> 24.3125 | Y23: =IF(J23="","",EOMONTH(DATE(YEAR(CloseDate)+IF(J23>MONTH(CloseDate),0,1),J23,1),0)) -> 46477
A24: =RANK(F24,$F$5:$F$32) -> 28 | B24: 20 | C24: SouthPark Dental Associates | D24: 120 | E24: 1 | F24: 1800 | G24: 18 | H24: =F24*G24 -> 32400 | I24: 0.02 | J24: 4 | K24: 44287 | L24: 46112 | M24: None | N24: Ghost | O24: =IF(L24<CloseDate,0,DATEDIF(CloseDate,L24,"m")+1) -> 0 | P24: =LOOKUP(F24,{0,2000,5000,15000}) -> 0 | Q24: =VLOOKUP(P24,LeaseTable,2,FALSE) -> <2,000 | R24: =VLOOKUP(P24,LeaseTable,3,FALSE) -> 24 | S24: =VLOOKUP(P24,LeaseTable,5,FALSE) -> 7 | T24: =VLOOKUP(P24,LeaseTable,6,FALSE) -> 28 | U24: =VLOOKUP(P24,LeaseTable,8,FALSE) -> 0.06 | V24: =VLOOKUP(P24,LeaseTable,9,FALSE) -> 3 | W24: =VLOOKUP(P24,LeaseTable,4,FALSE) -> 0.5 | X24: =R24*(W24*RenewDiscount+(1-W24)) -> 23.4 | Y24: =IF(J24="","",EOMONTH(DATE(YEAR(CloseDate)+IF(J24>MONTH(CloseDate),0,1),J24,1),0)) -> 46507
A25: =RANK(F25,$F$5:$F$32) -> 10 | B25: 21 | C25: Vacant — Suite 130 | D25: 130 | E25: 1 | F25: 8500 | G25: 0 | H25: =F25*G25 -> 0 | M25: — | N25: Vacant | O25: 3 | P25: =LOOKUP(F25,{0,2000,5000,15000}) -> 5000 | Q25: =VLOOKUP(P25,LeaseTable,2,FALSE) -> 5,000-15,000 | R25: =VLOOKUP(P25,LeaseTable,3,FALSE) -> 25.5 | S25: =VLOOKUP(P25,LeaseTable,5,FALSE) -> 5 | T25: =VLOOKUP(P25,LeaseTable,6,FALSE) -> 36 | U25: =VLOOKUP(P25,LeaseTable,8,FALSE) -> 0.05 | V25: =VLOOKUP(P25,LeaseTable,9,FALSE) -> 2 | W25: =VLOOKUP(P25,LeaseTable,4,FALSE) -> 0.65 | X25: =R25*(W25*RenewDiscount+(1-W25)) -> 24.67125
A26: =RANK(F26,$F$5:$F$32) -> 17 | B26: 22 | C26: Vacant — Suite 250 | D26: 250 | E26: 2 | F26: 6400 | G26: 0 | H26: =F26*G26 -> 0 | M26: — | N26: Vacant | O26: 4 | P26: =LOOKUP(F26,{0,2000,5000,15000}) -> 5000 | Q26: =VLOOKUP(P26,LeaseTable,2,FALSE) -> 5,000-15,000 | R26: =VLOOKUP(P26,LeaseTable,3,FALSE) -> 25.5 | S26: =VLOOKUP(P26,LeaseTable,5,FALSE) -> 5 | T26: =VLOOKUP(P26,LeaseTable,6,FALSE) -> 36 | U26: =VLOOKUP(P26,LeaseTable,8,FALSE) -> 0.05 | V26: =VLOOKUP(P26,LeaseTable,9,FALSE) -> 2 | W26: =VLOOKUP(P26,LeaseTable,4,FALSE) -> 0.65 | X26: =R26*(W26*RenewDiscount+(1-W26)) -> 24.67125
A27: =RANK(F27,$F$5:$F$32) -> 20 | B27: 23 | C27: Vacant — Suite 360 | D27: 360 | E27: 3 | F27: 5800 | G27: 0 | H27: =F27*G27 -> 0 | M27: — | N27: Vacant | O27: 5 | P27: =LOOKUP(F27,{0,2000,5000,15000}) -> 5000 | Q27: =VLOOKUP(P27,LeaseTable,2,FALSE) -> 5,000-15,000 | R27: =VLOOKUP(P27,LeaseTable,3,FALSE) -> 25.5 | S27: =VLOOKUP(P27,LeaseTable,5,FALSE) -> 5 | T27: =VLOOKUP(P27,LeaseTable,6,FALSE) -> 36 | U27: =VLOOKUP(P27,LeaseTable,8,FALSE) -> 0.05 | V27: =VLOOKUP(P27,LeaseTable,9,FALSE) -> 2 | W27: =VLOOKUP(P27,LeaseTable,4,FALSE) -> 0.65 | X27: =R27*(W27*RenewDiscount+(1-W27)) -> 24.67125
A28: =RANK(F28,$F$5:$F$32) -> 7 | B28: 24 | C28: Vacant — Suite 450 | D28: 450 | E28: 4 | F28: 9200 | G28: 0 | H28: =F28*G28 -> 0 | M28: — | N28: Vacant | O28: 6 | P28: =LOOKUP(F28,{0,2000,5000,15000}) -> 5000 | Q28: =VLOOKUP(P28,LeaseTable,2,FALSE) -> 5,000-15,000 | R28: =VLOOKUP(P28,LeaseTable,3,FALSE) -> 25.5 | S28: =VLOOKUP(P28,LeaseTable,5,FALSE) -> 5 | T28: =VLOOKUP(P28,LeaseTable,6,FALSE) -> 36 | U28: =VLOOKUP(P28,LeaseTable,8,FALSE) -> 0.05 | V28: =VLOOKUP(P28,LeaseTable,9,FALSE) -> 2 | W28: =VLOOKUP(P28,LeaseTable,4,FALSE) -> 0.65 | X28: =R28*(W28*RenewDiscount+(1-W28)) -> 24.67125
A29: =RANK(F29,$F$5:$F$32) -> 14 | B29: 25 | C29: Vacant — Suite 460 | D29: 460 | E29: 4 | F29: 7500 | G29: 0 | H29: =F29*G29 -> 0 | M29: — | N29: Vacant | O29: 7 | P29: =LOOKUP(F29,{0,2000,5000,15000}) -> 5000 | Q29: =VLOOKUP(P29,LeaseTable,2,FALSE) -> 5,000-15,000 | R29: =VLOOKUP(P29,LeaseTable,3,FALSE) -> 25.5 | S29: =VLOOKUP(P29,LeaseTable,5,FALSE) -> 5 | T29: =VLOOKUP(P29,LeaseTable,6,FALSE) -> 36 | U29: =VLOOKUP(P29,LeaseTable,8,FALSE) -> 0.05 | V29: =VLOOKUP(P29,LeaseTable,9,FALSE) -> 2 | W29: =VLOOKUP(P29,LeaseTable,4,FALSE) -> 0.65 | X29: =R29*(W29*RenewDiscount+(1-W29)) -> 24.67125
A30: =RANK(F30,$F$5:$F$32) -> 9 | B30: 26 | C30: Vacant — Suite 540 | D30: 540 | E30: 5 | F30: 8800 | G30: 0 | H30: =F30*G30 -> 0 | M30: — | N30: Vacant | O30: 9 | P30: =LOOKUP(F30,{0,2000,5000,15000}) -> 5000 | Q30: =VLOOKUP(P30,LeaseTable,2,FALSE) -> 5,000-15,000 | R30: =VLOOKUP(P30,LeaseTable,3,FALSE) -> 25.5 | S30: =VLOOKUP(P30,LeaseTable,5,FALSE) -> 5 | T30: =VLOOKUP(P30,LeaseTable,6,FALSE) -> 36 | U30: =VLOOKUP(P30,LeaseTable,8,FALSE) -> 0.05 | V30: =VLOOKUP(P30,LeaseTable,9,FALSE) -> 2 | W30: =VLOOKUP(P30,LeaseTable,4,FALSE) -> 0.65 | X30: =R30*(W30*RenewDiscount+(1-W30)) -> 24.67125
A31: =RANK(F31,$F$5:$F$32) -> 18 | B31: 27 | C31: Vacant — Suite 550 | D31: 550 | E31: 5 | F31: 6200 | G31: 0 | H31: =F31*G31 -> 0 | M31: — | N31: Vacant | O31: 10 | P31: =LOOKUP(F31,{0,2000,5000,15000}) -> 5000 | Q31: =VLOOKUP(P31,LeaseTable,2,FALSE) -> 5,000-15,000 | R31: =VLOOKUP(P31,LeaseTable,3,FALSE) -> 25.5 | S31: =VLOOKUP(P31,LeaseTable,5,FALSE) -> 5 | T31: =VLOOKUP(P31,LeaseTable,6,FALSE) -> 36 | U31: =VLOOKUP(P31,LeaseTable,8,FALSE) -> 0.05 | V31: =VLOOKUP(P31,LeaseTable,9,FALSE) -> 2 | W31: =VLOOKUP(P31,LeaseTable,4,FALSE) -> 0.65 | X31: =R31*(W31*RenewDiscount+(1-W31)) -> 24.67125
A32: =RANK(F32,$F$5:$F$32) -> 7 | B32: 28 | C32: Vacant — Suite 830 | D32: 830 | E32: 8 | F32: 9200 | G32: 0 | H32: =F32*G32 -> 0 | M32: — | N32: Vacant | O32: 12 | P32: =LOOKUP(F32,{0,2000,5000,15000}) -> 5000 | Q32: =VLOOKUP(P32,LeaseTable,2,FALSE) -> 5,000-15,000 | R32: =VLOOKUP(P32,LeaseTable,3,FALSE) -> 25.5 | S32: =VLOOKUP(P32,LeaseTable,5,FALSE) -> 5 | T32: =VLOOKUP(P32,LeaseTable,6,FALSE) -> 36 | U32: =VLOOKUP(P32,LeaseTable,8,FALSE) -> 0.05 | V32: =VLOOKUP(P32,LeaseTable,9,FALSE) -> 2 | W32: =VLOOKUP(P32,LeaseTable,4,FALSE) -> 0.65 | X32: =R32*(W32*RenewDiscount+(1-W32)) -> 24.67125
B34: TOTAL | C34: 28 entries | F34: =SUM(F5:F32) -> 280000 | G34: =H34/F34 -> 15.903036 | H34: =SUM(H5:H32) -> 4452850 | L34: {=SUMPRODUCT((L5:L32)*(H5:H32)*(N5:N32<>"Vacant"))/H34} -> 46928.587 | X34: =SUMPRODUCT(X5:X32,F5:F32)/F34 -> 24.676044
B36: SF check vs Building SF: | F36: =F34-BldgSF -> 0 | G36: =IF(F36=0,"OK","CHECK") -> OK
B38: SPEC SUITES (Meridian re-demise — 76,000 SF, not additive)
B40: # | C40: Suite | D40: Floor | F40: SF | O40: Commence Mo# | T40: TI $/SF | U40: LC % | V40: Free New | X40: Rent $/SF
B41: 29 | C41: Suite 610 | D41: 6 | F41: 14000 | O41: 12 | P41: Adjusted per VP feedback (email 9) | T41: =SpecTI -> 40 | U41: 0.05 | V41: 2 | X41: 26
B42: 30 | C42: Suite 620 | D42: 6 | F42: 13000 | O42: 12 | P42: Adjusted per VP feedback (email 9) | T42: =SpecTI -> 40 | U42: 0.05 | V42: 2 | X42: 26
B43: 31 | C43: Suite 710 | D43: 7 | F43: 13000 | O43: 14 | P43: Adjusted per VP feedback (email 9) | T43: =SpecTI -> 40 | U43: 0.05 | V43: 2 | X43: 26
B44: 32 | C44: Suite 720 | D44: 7 | F44: 12000 | O44: 14 | P44: Adjusted per VP feedback (email 9) | T44: =SpecTI -> 40 | U44: 0.05 | V44: 2 | X44: 26
B45: 33 | C45: Suite 810 | D45: 8 | F45: 12500 | O45: 16 | P45: Adjusted per VP feedback (email 9) | T45: =SpecTI -> 40 | U45: 0.05 | V45: 2 | X45: 26
B46: 34 | C46: Suite 820 | D46: 8 | F46: 11500 | O46: 16 | P46: Adjusted per VP feedback (email 9) | T46: =SpecTI -> 40 | U46: 0.05 | V46: 2 | X46: 26
C47: Total (= Meridian 76,000) | F47: =SUM(F41:F46) -> 76000

Sheet Rent Roll Calc
A1: SouthPark Centre — Rent Roll Calc
A3: Month # | D3: 0 | E3: =D3+1 -> 1 | F3: =E3+1 -> 2 | G3: =F3+1 -> 3 | H3: =G3+1 -> 4 | I3: =H3+1 -> 5 | J3: =I3+1 -> 6 | K3: =J3+1 -> 7 | L3: =K3+1 -> 8 | ... BX3: =BW3+1 -> 72
A4: Period End | D4: =EOMONTH(CloseDate,D3) -> 46265 | E4: =EOMONTH(CloseDate,E3) -> 46295 | F4: =EOMONTH(CloseDate,F3) -> 46326 | G4: =EOMONTH(CloseDate,G3) -> 46356 | H4: =EOMONTH(CloseDate,H3) -> 46387 | I4: =EOMONTH(CloseDate,I3) -> 46418 | J4: =EOMONTH(CloseDate,J3) -> 46446 | K4: =EOMONTH(CloseDate,K3) -> 46477 | ... BX4: =EOMONTH(CloseDate,BX3) -> 48457
A5: Year | D5: =INT((D3-1)/12)+1 -> 0 | E5: =INT((E3-1)/12)+1 -> 1 | F5: =INT((F3-1)/12)+1 -> 1 | G5: =INT((G3-1)/12)+1 -> 1 | H5: =INT((H3-1)/12)+1 -> 1 | I5: =INT((I3-1)/12)+1 -> 1 | J5: =INT((J3-1)/12)+1 -> 1 | K5: =INT((K3-1)/12)+1 -> 1 | ... BX5: =INT((BX3-1)/12)+1 -> 6
A6: Rent Growth Index | D6: =IF(MONTH(D4)=1,(1+RentGrowth),1) -> 1 | E6: =IF(MONTH(E4)=1,D6*(1+RentGrowth),D6) -> 1 | F6: =IF(MONTH(F4)=1,E6*(1+RentGrowth),E6) -> 1 | G6: =IF(MONTH(G4)=1,F6*(1+RentGrowth),F6) -> 1 | H6: =IF(MONTH(H4)=1,G6*(1+RentGrowth),G6) -> 1 | I6: =IF(MONTH(I4)=1,H6*(1+RentGrowth),H6) -> 1.027 | J6: =IF(MONTH(J4)=1,I6*(1+RentGrowth),I6) -> 1.027 | K6: =IF(MONTH(K4)=1,J6*(1+RentGrowth),J6) -> 1.027 | L6: =IF(MONTH(L4)=1,K6*(1+RentGrowth),K6) -> 1.027 | ... BX6: =IF(MONTH(BX4)=1,BW6*(1+RentGrowth),BW6) -> 1.1733367
A7: Expense Growth Index | D7: =IF(MONTH(D4)=1,(1+ExpGrowth),1) -> 1 | E7: =IF(MONTH(E4)=1,D7*(1+ExpGrowth),D7) -> 1 | F7: =IF(MONTH(F4)=1,E7*(1+ExpGrowth),E7) -> 1 | G7: =IF(MONTH(G4)=1,F7*(1+ExpGrowth),F7) -> 1 | H7: =IF(MONTH(H4)=1,G7*(1+ExpGrowth),G7) -> 1 | I7: =IF(MONTH(I4)=1,H7*(1+ExpGrowth),H7) -> 1.027 | J7: =IF(MONTH(J4)=1,I7*(1+ExpGrowth),I7) -> 1.027 | K7: =IF(MONTH(K4)=1,J7*(1+ExpGrowth),J7) -> 1.027 | L7: =IF(MONTH(L4)=1,K7*(1+ExpGrowth),K7) -> 1.027 | ... BX7: =IF(MONTH(BX4)=1,BW7*(1+ExpGrowth),BW7) -> 1.1733367
A9: ='Rent Roll'!C5 -> Meridian Financial Group | B9: =INDEX('Rent Roll'!$F$5:$F$46,MATCH('Rent Roll Calc'!A9,'Rent Roll'!$C$5:$C$46,0)) -> 76000
B10: Occupancy Flag | D10: =IF(AND('Rent Roll'!$N$5<>"Ghost",D$4<='Rent Roll'!$L$5),1,0) -> 1 | E10: =IF(AND('Rent Roll'!$N$5<>"Ghost",E$4<='Rent Roll'!$L$5),1,0) -> 1 | F10: =IF(AND('Rent Roll'!$N$5<>"Ghost",F$4<='Rent Roll'!$L$5),1,0) -> 1 | G10: =IF(AND('Rent Roll'!$N$5<>"Ghost",G$4<='Rent Roll'!$L$5),1,0) -> 0 | H10: =IF(AND('Rent Roll'!$N$5<>"Ghost",H$4<='Rent Roll'!$L$5),1,0) -> 0 | I10: =IF(AND('Rent Roll'!$N$5<>"Ghost",I$4<='Rent Roll'!$L$5),1,0) -> 0 | J10: =IF(AND('Rent Roll'!$N$5<>"Ghost",J$4<='Rent Roll'!$L$5),1,0) -> 0 | K10: =IF(AND('Rent Roll'!$N$5<>"Ghost",K$4<='Rent Roll'!$L$5),1,0) -> 0 | ... BX10: =IF(AND('Rent Roll'!$N$5<>"Ghost",BX$4<='Rent Roll'!$L$5),1,0) -> 0
B11: In-Place Rent | D11: =IF(D10=1,'Rent Roll'!$H$5/12*(1+'Rent Roll'!$I$5)^IF(D$4<'Rent Roll'!$Y$5,0,YEAR(D$4)-YEAR('Rent Roll'!$Y$5)+1),0) -> 123500 | E11: =IF(E10=1,'Rent Roll'!$H$5/12*(1+'Rent Roll'!$I$5)^IF(E$4<'Rent Roll'!$Y$5,0,YEAR(E$4)-YEAR('Rent Roll'!$Y$5)+1),0) -> 123500 | F11: =IF(F10=1,'Rent Roll'!$H$5/12*(1+'Rent Roll'!$I$5)^IF(F$4<'Rent Roll'!$Y$5,0,YEAR(F$4)-YEAR('Rent Roll'!$Y$5)+1),0) -> 123500 | G11: =IF(G10=1,'Rent Roll'!$H$5/12*(1+'Rent Roll'!$I$5)^IF(G$4<'Rent Roll'!$Y$5,0,YEAR(G$4)-YEAR('Rent Roll'!$Y$5)+1),0) -> 0 | H11: =IF(H10=1,'Rent Roll'!$H$5/12*(1+'Rent Roll'!$I$5)^IF(H$4<'Rent Roll'!$Y$5,0,YEAR(H$4)-YEAR('Rent Roll'!$Y$5)+1),0) -> 0 | I11: =IF(I10=1,'Rent Roll'!$H$5/12*(1+'Rent Roll'!$I$5)^IF(I$4<'Rent Roll'!$Y$5,0,YEAR(I$4)-YEAR('Rent Roll'!$Y$5)+1),0) -> 0 | J11: =IF(J10=1,'Rent Roll'!$H$5/12*(1+'Rent Roll'!$I$5)^IF(J$4<'Rent Roll'!$Y$5,0,YEAR(J$4)-YEAR('Rent Roll'!$Y$5)+1),0) -> 0 | K11: =IF(K10=1,'Rent Roll'!$H$5/12*(1+'Rent Roll'!$I$5)^IF(K$4<'Rent Roll'!$Y$5,0,YEAR(K$4)-YEAR('Rent Roll'!$Y$5)+1),0) -> 0 | ... BX11: =IF(BX10=1,'Rent Roll'!$H$5/12*(1+'Rent Roll'!$I$5)^IF(BX$4<'Rent Roll'!$Y$5,0,YEAR(BX$4)-YEAR('Rent Roll'!$Y$5)+1),0) -> 0
B12: Re-Let Flag | D12: =0 -> 0 | E12: =0 -> 0 | F12: =0 -> 0 | G12: =0 -> 0 | H12: =0 -> 0 | I12: =0 -> 0 | J12: =0 -> 0 | K12: =0 -> 0 | ... BX12: =0 -> 0
B13: Re-Let Rent (gross) | D13: =0 -> 0 | E13: =0 -> 0 | F13: =0 -> 0 | G13: =0 -> 0 | H13: =0 -> 0 | I13: =0 -> 0 | J13: =0 -> 0 | K13: =0 -> 0 | ... BX13: =0 -> 0
B14: Free Rent Adj | D14: =0 -> 0 | E14: =0 -> 0 | F14: =0 -> 0 | G14: =0 -> 0 | H14: =0 -> 0 | I14: =0 -> 0 | J14: =0 -> 0 | K14: =0 -> 0 | ... BX14: =0 -> 0
B15: Net Base Rent | D15: =D11+D13+D14 -> 123500 | E15: =E11+E13+E14 -> 123500 | F15: =F11+F13+F14 -> 123500 | G15: =G11+G13+G14 -> 0 | H15: =H11+H13+H14 -> 0 | I15: =I11+I13+I14 -> 0 | J15: =J11+J13+J14 -> 0 | K15: =K11+K13+K14 -> 0 | ... BX15: =BX11+BX13+BX14 -> 0
B16: Opex Recovery (NNN) | D16: =IF(OR(D10=1,D12=1),'Rent Roll'!$F$5/BldgSF*ReimbPool/12*D$7,0) -> 66310 | E16: =IF(OR(E10=1,E12=1),'Rent Roll'!$F$5/BldgSF*ReimbPool/12*E$7,0) -> 66310 | F16: =IF(OR(F10=1,F12=1),'Rent Roll'!$F$5/BldgSF*ReimbPool/12*F$7,0) -> 66310 | G16: =IF(OR(G10=1,G12=1),'Rent Roll'!$F$5/BldgSF*ReimbPool/12*G$7,0) -> 0 | H16: =IF(OR(H10=1,H12=1),'Rent Roll'!$F$5/BldgSF*ReimbPool/12*H$7,0) -> 0 | I16: =IF(OR(I10=1,I12=1),'Rent Roll'!$F$5/BldgSF*ReimbPool/12*I$7,0) -> 0 | J16: =IF(OR(J10=1,J12=1),'Rent Roll'!$F$5/BldgSF*ReimbPool/12*J$7,0) -> 0 | K16: =IF(OR(K10=1,K12=1),'Rent Roll'!$F$5/BldgSF*ReimbPool/12*K$7,0) -> 0 | ... BX16: =IF(OR(BX10=1,BX12=1),'Rent Roll'!$F$5/BldgSF*ReimbPool/12*BX$7,0) -> 0
B17: TI (capital) | D17: =0 -> 0 | E17: =0 -> 0 | F17: =0 -> 0 | G17: =0 -> 0 | H17: =0 -> 0 | I17: =0 -> 0 | J17: =0 -> 0 | K17: =0 -> 0 | ... BX17: =0 -> 0
B18: LC (capital) | D18: =0 -> 0 | E18: =0 -> 0 | F18: =0 -> 0 | G18: =0 -> 0 | H18: =0 -> 0 | I18: =0 -> 0 | J18: =0 -> 0 | K18: =0 -> 0 | ... BX18: =0 -> 0
A19: ='Rent Roll'!C6 -> Southeast Regional Health | B19: =INDEX('Rent Roll'!$F$5:$F$46,MATCH('Rent Roll Calc'!A19,'Rent Roll'!$C$5:$C$46,0)) -> 24000
B20: Occupancy Flag | D20: =IF(AND('Rent Roll'!$N$6<>"Ghost",D$4<='Rent Roll'!$L$6),1,0) -> 1 | E20: =IF(AND('Rent Roll'!$N$6<>"Ghost",E$4<='Rent Roll'!$L$6),1,0) -> 1 | F20: =IF(AND('Rent Roll'!$N$6<>"Ghost",F$4<='Rent Roll'!$L$6),1,0) -> 1 | G20: =IF(AND('Rent Roll'!$N$6<>"Ghost",G$4<='Rent Roll'!$L$6),1,0) -> 1 | H20: =IF(AND('Rent Roll'!$N$6<>"Ghost",H$4<='Rent Roll'!$L$6),1,0) -> 1 | I20: =IF(AND('Rent Roll'!$N$6<>"Ghost",I$4<='Rent Roll'!$L$6),1,0) -> 1 | J20: =IF(AND('Rent Roll'!$N$6<>"Ghost",J$4<='Rent Roll'!$L$6),1,0) -> 1 | K20: =IF(AND('Rent Roll'!$N$6<>"Ghost",K$4<='Rent Roll'!$L$6),1,0) -> 1 | ... BX20: =IF(AND('Rent Roll'!$N$6<>"Ghost",BX$4<='Rent Roll'!$L$6),1,0) -> 0
B21: In-Place Rent | D21: =IF(D20=1,'Rent Roll'!$H$6/12*(1+'Rent Roll'!$I$6)^IF(D$4<'Rent Roll'!$Y$6,0,YEAR(D$4)-YEAR('Rent Roll'!$Y$6)+1),0) -> 43000 | E21: =IF(E20=1,'Rent Roll'!$H$6/12*(1+'Rent Roll'!$I$6)^IF(E$4<'Rent Roll'!$Y$6,0,YEAR(E$4)-YEAR('Rent Roll'!$Y$6)+1),0) -> 43000 | F21: =IF(F20=1,'Rent Roll'!$H$6/12*(1+'Rent Roll'!$I$6)^IF(F$4<'Rent Roll'!$Y$6,0,YEAR(F$4)-YEAR('Rent Roll'!$Y$6)+1),0) -> 43000 | G21: =IF(G20=1,'Rent Roll'!$H$6/12*(1+'Rent Roll'!$I$6)^IF(G$4<'Rent Roll'!$Y$6,0,YEAR(G$4)-YEAR('Rent Roll'!$Y$6)+1),0) -> 43000 | H21: =IF(H20=1,'Rent Roll'!$H$6/12*(1+'Rent Roll'!$I$6)^IF(H$4<'Rent Roll'!$Y$6,0,YEAR(H$4)-YEAR('Rent Roll'!$Y$6)+1),0) -> 43000 | I21: =IF(I20=1,'Rent Roll'!$H$6/12*(1+'Rent Roll'!$I$6)^IF(I$4<'Rent Roll'!$Y$6,0,YEAR(I$4)-YEAR('Rent Roll'!$Y$6)+1),0) -> 43000 | J21: =IF(J20=1,'Rent Roll'!$H$6/12*(1+'Rent Roll'!$I$6)^IF(J$4<'Rent Roll'!$Y$6,0,YEAR(J$4)-YEAR('Rent Roll'!$Y$6)+1),0) -> 43000 | K21: =IF(K20=1,'Rent Roll'!$H$6/12*(1+'Rent Roll'!$I$6)^IF(K$4<'Rent Roll'!$Y$6,0,YEAR(K$4)-YEAR('Rent Roll'!$Y$6)+1),0) -> 43000 | ... BX21: =IF(BX20=1,'Rent Roll'!$H$6/12*(1+'Rent Roll'!$I$6)^IF(BX$4<'Rent Roll'!$Y$6,0,YEAR(BX$4)-YEAR('Rent Roll'!$Y$6)+1),0) -> 0
B22: Re-Let Flag | D22: =IF(D$4>EOMONTH(CloseDate,'Rent Roll'!$O$6+'Rent Roll'!$S$6-1),1,0) -> 0 | E22: =IF(E$4>EOMONTH(CloseDate,'Rent Roll'!$O$6+'Rent Roll'!$S$6-1),1,0) -> 0 | F22: =IF(F$4>EOMONTH(CloseDate,'Rent Roll'!$O$6+'Rent Roll'!$S$6-1),1,0) -> 0 | G22: =IF(G$4>EOMONTH(CloseDate,'Rent Roll'!$O$6+'Rent Roll'!$S$6-1),1,0) -> 0 | H22: =IF(H$4>EOMONTH(CloseDate,'Rent Roll'!$O$6+'Rent Roll'!$S$6-1),1,0) -> 0 | I22: =IF(I$4>EOMONTH(CloseDate,'Rent Roll'!$O$6+'Rent Roll'!$S$6-1),1,0) -> 0 | J22: =IF(J$4>EOMONTH(CloseDate,'Rent Roll'!$O$6+'Rent Roll'!$S$6-1),1,0) -> 0 | K22: =IF(K$4>EOMONTH(CloseDate,'Rent Roll'!$O$6+'Rent Roll'!$S$6-1),1,0) -> 0 | ... BX22: =IF(BX$4>EOMONTH(CloseDate,'Rent Roll'!$O$6+'Rent Roll'!$S$6-1),1,0) -> 1
B23: Re-Let Rent (gross) | D23: =IF(D22=1,'Rent Roll'!$F$6*'Rent Roll'!$X$6/12*D$6,0) -> 0 | E23: =IF(E22=1,'Rent Roll'!$F$6*'Rent Roll'!$X$6/12*E$6,0) -> 0 | F23: =IF(F22=1,'Rent Roll'!$F$6*'Rent Roll'!$X$6/12*F$6,0) -> 0 | G23: =IF(G22=1,'Rent Roll'!$F$6*'Rent Roll'!$X$6/12*G$6,0) -> 0 | H23: =IF(H22=1,'Rent Roll'!$F$6*'Rent Roll'!$X$6/12*H$6,0) -> 0 | I23: =IF(I22=1,'Rent Roll'!$F$6*'Rent Roll'!$X$6/12*I$6,0) -> 0 | J23: =IF(J22=1,'Rent Roll'!$F$6*'Rent Roll'!$X$6/12*J$6,0) -> 0 | K23: =IF(K22=1,'Rent Roll'!$F$6*'Rent Roll'!$X$6/12*K$6,0) -> 0 | ... BX23: =IF(BX22=1,'Rent Roll'!$F$6*'Rent Roll'!$X$6/12*BX$6,0) -> 56466.83
B24: Free Rent Adj | D24: =IF(AND(D$4>EOMONTH(CloseDate,'Rent Roll'!$O$6+'Rent Roll'!$S$6-1),D$4<=EOMONTH(CloseDate,'Rent Roll'!$O$6+'Rent Roll'!$S$6-1+'Rent Roll'!$V$6)),-D23,0) -> 0 | E24: =IF(AND(E$4>EOMONTH(CloseDate,'Rent Roll'!$O$6+'Rent Roll'!$S$6-1),E$4<=EOMONTH(CloseDate,'Rent Roll'!$O$6+'Rent Roll'!$S$6-1+'Rent Roll'!$V$6)),-E23,0) -> 0 | F24: =IF(AND(F$4>EOMONTH(CloseDate,'Rent Roll'!$O$6+'Rent Roll'!$S$6-1),F$4<=EOMONTH(CloseDate,'Rent Roll'!$O$6+'Rent Roll'!$S$6-1+'Rent Roll'!$V$6)),-F23,0) -> 0 | G24: =IF(AND(G$4>EOMONTH(CloseDate,'Rent Roll'!$O$6+'Rent Roll'!$S$6-1),G$4<=EOMONTH(CloseDate,'Rent Roll'!$O$6+'Rent Roll'!$S$6-1+'Rent Roll'!$V$6)),-G23,0) -> 0 | H24: =IF(AND(H$4>EOMONTH(CloseDate,'Rent Roll'!$O$6+'Rent Roll'!$S$6-1),H$4<=EOMONTH(CloseDate,'Rent Roll'!$O$6+'Rent Roll'!$S$6-1+'Rent Roll'!$V$6)),-H23,0) -> 0 | I24: =IF(AND(I$4>EOMONTH(CloseDate,'Rent Roll'!$O$6+'Rent Roll'!$S$6-1),I$4<=EOMONTH(CloseDate,'Rent Roll'!$O$6+'Rent Roll'!$S$6-1+'Rent Roll'!$V$6)),-I23,0) -> 0 | J24: =IF(AND(J$4>EOMONTH(CloseDate,'Rent Roll'!$O$6+'Rent Roll'!$S$6-1),J$4<=EOMONTH(CloseDate,'Rent Roll'!$O$6+'Rent Roll'!$S$6-1+'Rent Roll'!$V$6)),-J23,0) -> 0 | K24: =IF(AND(K$4>EOMONTH(CloseDate,'Rent Roll'!$O$6+'Rent Roll'!$S$6-1),K$4<=EOMONTH(CloseDate,'Rent Roll'!$O$6+'Rent Roll'!$S$6-1+'Rent Roll'!$V$6)),-K23,0) -> 0 | ... BX24: =IF(AND(BX$4>EOMONTH(CloseDate,'Rent Roll'!$O$6+'Rent Roll'!$S$6-1),BX$4<=EOMONTH(CloseDate,'Rent Roll'!$O$6+'Rent Roll'!$S$6-1+'Rent Roll'!$V$6)),-BX23,0) -> 0
B25: Net Base Rent | D25: =D21+D23+D24 -> 43000 | E25: =E21+E23+E24 -> 43000 | F25: =F21+F23+F24 -> 43000 | G25: =G21+G23+G24 -> 43000 | H25: =H21+H23+H24 -> 43000 | I25: =I21+I23+I24 -> 43000 | J25: =J21+J23+J24 -> 43000 | K25: =K21+K23+K24 -> 43000 | ... BX25: =BX21+BX23+BX24 -> 56466.83
B26: Opex Recovery (NNN) | D26: =IF(OR(D20=1,D22=1),'Rent Roll'!$F$6/BldgSF*ReimbPool/12*D$7,0) -> 20940 | E26: =IF(OR(E20=1,E22=1),'Rent Roll'!$F$6/BldgSF*ReimbPool/12*E$7,0) -> 20940 | F26: =IF(OR(F20=1,F22=1),'Rent Roll'!$F$6/BldgSF*ReimbPool/12*F$7,0) -> 20940 | G26: =IF(OR(G20=1,G22=1),'Rent Roll'!$F$6/BldgSF*ReimbPool/12*G$7,0) -> 20940 | H26: =IF(OR(H20=1,H22=1),'Rent Roll'!$F$6/BldgSF*ReimbPool/12*H$7,0) -> 20940 | I26: =IF(OR(I20=1,I22=1),'Rent Roll'!$F$6/BldgSF*ReimbPool/12*I$7,0) -> 21505.38 | J26: =IF(OR(J20=1,J22=1),'Rent Roll'!$F$6/BldgSF*ReimbPool/12*J$7,0) -> 21505.38 | K26: =IF(OR(K20=1,K22=1),'Rent Roll'!$F$6/BldgSF*ReimbPool/12*K$7,0) -> 21505.38 | ... BX26: =IF(OR(BX20=1,BX22=1),'Rent Roll'!$F$6/BldgSF*ReimbPool/12*BX$7,0) -> 24569.671
B27: TI (capital) | D27: =IF(D$4=EOMONTH(CloseDate,'Rent Roll'!$O$6+'Rent Roll'!$S$6),-'Rent Roll'!$F$6*'Rent Roll'!$T$6,0) -> 0 | E27: =IF(E$4=EOMONTH(CloseDate,'Rent Roll'!$O$6+'Rent Roll'!$S$6),-'Rent Roll'!$F$6*'Rent Roll'!$T$6,0) -> 0 | F27: =IF(F$4=EOMONTH(CloseDate,'Rent Roll'!$O$6+'Rent Roll'!$S$6),-'Rent Roll'!$F$6*'Rent Roll'!$T$6,0) -> 0 | G27: =IF(G$4=EOMONTH(CloseDate,'Rent Roll'!$O$6+'Rent Roll'!$S$6),-'Rent Roll'!$F$6*'Rent Roll'!$T$6,0) -> 0 | H27: =IF(H$4=EOMONTH(CloseDate,'Rent Roll'!$O$6+'Rent Roll'!$S$6),-'Rent Roll'!$F$6*'Rent Roll'!$T$6,0) -> 0 | I27: =IF(I$4=EOMONTH(CloseDate,'Rent Roll'!$O$6+'Rent Roll'!$S$6),-'Rent Roll'!$F$6*'Rent Roll'!$T$6,0) -> 0 | J27: =IF(J$4=EOMONTH(CloseDate,'Rent Roll'!$O$6+'Rent Roll'!$S$6),-'Rent Roll'!$F$6*'Rent Roll'!$T$6,0) -> 0 | K27: =IF(K$4=EOMONTH(CloseDate,'Rent Roll'!$O$6+'Rent Roll'!$S$6),-'Rent Roll'!$F$6*'Rent Roll'!$T$6,0) -> 0 | ... BX27: =IF(BX$4=EOMONTH(CloseDate,'Rent Roll'!$O$6+'Rent Roll'!$S$6),-'Rent Roll'!$F$6*'Rent Roll'!$T$6,0) -> 0
B28: LC (capital) | D28: =IF(D$4=EOMONTH(CloseDate,'Rent Roll'!$O$6+'Rent Roll'!$S$6),-'Rent Roll'!$U$6*'Rent Roll'!$F$6*'Rent Roll'!$X$6,0) -> 0 | E28: =IF(E$4=EOMONTH(CloseDate,'Rent Roll'!$O$6+'Rent Roll'!$S$6),-'Rent Roll'!$U$6*'Rent Roll'!$F$6*'Rent Roll'!$X$6,0) -> 0 | F28: =IF(F$4=EOMONTH(CloseDate,'Rent Roll'!$O$6+'Rent Roll'!$S$6),-'Rent Roll'!$U$6*'Rent Roll'!$F$6*'Rent Roll'!$X$6,0) -> 0 | G28: =IF(G$4=EOMONTH(CloseDate,'Rent Roll'!$O$6+'Rent Roll'!$S$6),-'Rent Roll'!$U$6*'Rent Roll'!$F$6*'Rent Roll'!$X$6,0) -> 0 | H28: =IF(H$4=EOMONTH(CloseDate,'Rent Roll'!$O$6+'Rent Roll'!$S$6),-'Rent Roll'!$U$6*'Rent Roll'!$F$6*'Rent Roll'!$X$6,0) -> 0 | I28: =IF(I$4=EOMONTH(CloseDate,'Rent Roll'!$O$6+'Rent Roll'!$S$6),-'Rent Roll'!$U$6*'Rent Roll'!$F$6*'Rent Roll'!$X$6,0) -> 0 | J28: =IF(J$4=EOMONTH(CloseDate,'Rent Roll'!$O$6+'Rent Roll'!$S$6),-'Rent Roll'!$U$6*'Rent Roll'!$F$6*'Rent Roll'!$X$6,0) -> 0 | K28: =IF(K$4=EOMONTH(CloseDate,'Rent Roll'!$O$6+'Rent Roll'!$S$6),-'Rent Roll'!$U$6*'Rent Roll'!$F$6*'Rent Roll'!$X$6,0) -> 0 | ... BX28: =IF(BX$4=EOMONTH(CloseDate,'Rent Roll'!$O$6+'Rent Roll'!$S$6),-'Rent Roll'!$U$6*'Rent Roll'!$F$6*'Rent Roll'!$X$6,0) -> 0
A29: ='Rent Roll'!C7 -> Carter & Associates Law | B29: =INDEX('Rent Roll'!$F$5:$F$46,MATCH('Rent Roll Calc'!A29,'Rent Roll'!$C$5:$C$46,0)) -> 12000
B30: Occupancy Flag | D30: =IF(AND('Rent Roll'!$N$7<>"Ghost",D$4<='Rent Roll'!$L$7),1,0) -> 1 | E30: =IF(AND('Rent Roll'!$N$7<>"Ghost",E$4<='Rent Roll'!$L$7),1,0) -> 1 | F30: =IF(AND('Rent Roll'!$N$7<>"Ghost",F$4<='Rent Roll'!$L$7),1,0) -> 1 | G30: =IF(AND('Rent Roll'!$N$7<>"Ghost",G$4<='Rent Roll'!$L$7),1,0) -> 1 | H30: =IF(AND('Rent Roll'!$N$7<>"Ghost",H$4<='Rent Roll'!$L$7),1,0) -> 1 | I30: =IF(AND('Rent Roll'!$N$7<>"Ghost",I$4<='Rent Roll'!$L$7),1,0) -> 1 | J30: =IF(AND('Rent Roll'!$N$7<>"Ghost",J$4<='Rent Roll'!$L$7),1,0) -> 1 | K30: =IF(AND('Rent Roll'!$N$7<>"Ghost",K$4<='Rent Roll'!$L$7),1,0) -> 1 | ... BX30: =IF(AND('Rent Roll'!$N$7<>"Ghost",BX$4<='Rent Roll'!$L$7),1,0) -> 0
B31: In-Place Rent | D31: =IF(D30=1,'Rent Roll'!$H$7/12*(1+'Rent Roll'!$I$7)^IF(D$4<'Rent Roll'!$Y$7,0,YEAR(D$4)-YEAR('Rent Roll'!$Y$7)+1),0) -> 22000 | E31: =IF(E30=1,'Rent Roll'!$H$7/12*(1+'Rent Roll'!$I$7)^IF(E$4<'Rent Roll'!$Y$7,0,YEAR(E$4)-YEAR('Rent Roll'!$Y$7)+1),0) -> 22000 | F31: =IF(F30=1,'Rent Roll'!$H$7/12*(1+'Rent Roll'!$I$7)^IF(F$4<'Rent Roll'!$Y$7,0,YEAR(F$4)-YEAR('Rent Roll'!$Y$7)+1),0) -> 22550 | G31: =IF(G30=1,'Rent Roll'!$H$7/12*(1+'Rent Roll'!$I$7)^IF(G$4<'Rent Roll'!$Y$7,0,YEAR(G$4)-YEAR('Rent Roll'!$Y$7)+1),0) -> 22550 | H31: =IF(H30=1,'Rent Roll'!$H$7/12*(1+'Rent Roll'!$I$7)^IF(H$4<'Rent Roll'!$Y$7,0,YEAR(H$4)-YEAR('Rent Roll'!$Y$7)+1),0) -> 22550 | I31: =IF(I30=1,'Rent Roll'!$H$7/12*(1+'Rent Roll'!$I$7)^IF(I$4<'Rent Roll'!$Y$7,0,YEAR(I$4)-YEAR('Rent Roll'!$Y$7)+1),0) -> 23113.75 | J31: =IF(J30=1,'Rent Roll'!$H$7/12*(1+'Rent Roll'!$I$7)^IF(J$4<'Rent Roll'!$Y$7,0,YEAR(J$4)-YEAR('Rent Roll'!$Y$7)+1),0) -> 23113.75 | K31: =IF(K30=1,'Rent Roll'!$H$7/12*(1+'Rent Roll'!$I$7)^IF(K$4<'Rent Roll'!$Y$7,0,YEAR(K$4)-YEAR('Rent Roll'!$Y$7)+1),0) -> 23113.75 | ... BX31: =IF(BX30=1,'Rent Roll'!$H$7/12*(1+'Rent Roll'!$I$7)^IF(BX$4<'Rent Roll'!$Y$7,0,YEAR(BX$4)-YEAR('Rent Roll'!$Y$7)+1),0) -> 0
B32: Re-Let Flag | D32: =IF(D$4>EOMONTH(CloseDate,'Rent Roll'!$O$7+'Rent Roll'!$S$7-1),1,0) -> 0 | E32: =IF(E$4>EOMONTH(CloseDate,'Rent Roll'!$O$7+'Rent Roll'!$S$7-1),1,0) -> 0 | F32: =IF(F$4>EOMONTH(CloseDate,'Rent Roll'!$O$7+'Rent Roll'!$S$7-1),1,0) -> 0 | G32: =IF(G$4>EOMONTH(CloseDate,'Rent Roll'!$O$7+'Rent Roll'!$S$7-1),1,0) -> 0 | H32: =IF(H$4>EOMONTH(CloseDate,'Rent Roll'!$O$7+'Rent Roll'!$S$7-1),1,0) -> 0 | I32: =IF(I$4>EOMONTH(CloseDate,'Rent Roll'!$O$7+'Rent Roll'!$S$7-1),1,0) -> 0 | J32: =IF(J$4>EOMONTH(CloseDate,'Rent Roll'!$O$7+'Rent Roll'!$S$7-1),1,0) -> 0 | K32: =IF(K$4>EOMONTH(CloseDate,'Rent Roll'!$O$7+'Rent Roll'!$S$7-1),1,0) -> 0 | ... BX32: =IF(BX$4>EOMONTH(CloseDate,'Rent Roll'!$O$7+'Rent Roll'!$S$7-1),1,0) -> 1
B33: Re-Let Rent (gross) | D33: =IF(D32=1,'Rent Roll'!$F$7*'Rent Roll'!$X$7/12*D$6,0) -> 0 | E33: =IF(E32=1,'Rent Roll'!$F$7*'Rent Roll'!$X$7/12*E$6,0) -> 0 | F33: =IF(F32=1,'Rent Roll'!$F$7*'Rent Roll'!$X$7/12*F$6,0) -> 0 | G33: =IF(G32=1,'Rent Roll'!$F$7*'Rent Roll'!$X$7/12*G$6,0) -> 0 | H33: =IF(H32=1,'Rent Roll'!$F$7*'Rent Roll'!$X$7/12*H$6,0) -> 0 | I33: =IF(I32=1,'Rent Roll'!$F$7*'Rent Roll'!$X$7/12*I$6,0) -> 0 | J33: =IF(J32=1,'Rent Roll'!$F$7*'Rent Roll'!$X$7/12*J$6,0) -> 0 | K33: =IF(K32=1,'Rent Roll'!$F$7*'Rent Roll'!$X$7/12*K$6,0) -> 0 | ... BX33: =IF(BX32=1,'Rent Roll'!$F$7*'Rent Roll'!$X$7/12*BX$6,0) -> 28947.684
B34: Free Rent Adj | D34: =IF(AND(D$4>EOMONTH(CloseDate,'Rent Roll'!$O$7+'Rent Roll'!$S$7-1),D$4<=EOMONTH(CloseDate,'Rent Roll'!$O$7+'Rent Roll'!$S$7-1+'Rent Roll'!$V$7)),-D33,0) -> 0 | E34: =IF(AND(E$4>EOMONTH(CloseDate,'Rent Roll'!$O$7+'Rent Roll'!$S$7-1),E$4<=EOMONTH(CloseDate,'Rent Roll'!$O$7+'Rent Roll'!$S$7-1+'Rent Roll'!$V$7)),-E33,0) -> 0 | F34: =IF(AND(F$4>EOMONTH(CloseDate,'Rent Roll'!$O$7+'Rent Roll'!$S$7-1),F$4<=EOMONTH(CloseDate,'Rent Roll'!$O$7+'Rent Roll'!$S$7-1+'Rent Roll'!$V$7)),-F33,0) -> 0 | G34: =IF(AND(G$4>EOMONTH(CloseDate,'Rent Roll'!$O$7+'Rent Roll'!$S$7-1),G$4<=EOMONTH(CloseDate,'Rent Roll'!$O$7+'Rent Roll'!$S$7-1+'Rent Roll'!$V$7)),-G33,0) -> 0 | H34: =IF(AND(H$4>EOMONTH(CloseDate,'Rent Roll'!$O$7+'Rent Roll'!$S$7-1),H$4<=EOMONTH(CloseDate,'Rent Roll'!$O$7+'Rent Roll'!$S$7-1+'Rent Roll'!$V$7)),-H33,0) -> 0 | I34: =IF(AND(I$4>EOMONTH(CloseDate,'Rent Roll'!$O$7+'Rent Roll'!$S$7-1),I$4<=EOMONTH(CloseDate,'Rent Roll'!$O$7+'Rent Roll'!$S$7-1+'Rent Roll'!$V$7)),-I33,0) -> 0 | J34: =IF(AND(J$4>EOMONTH(CloseDate,'Rent Roll'!$O$7+'Rent Roll'!$S$7-1),J$4<=EOMONTH(CloseDate,'Rent Roll'!$O$7+'Rent Roll'!$S$7-1+'Rent Roll'!$V$7)),-J33,0) -> 0 | K34: =IF(AND(K$4>EOMONTH(CloseDate,'Rent Roll'!$O$7+'Rent Roll'!$S$7-1),K$4<=EOMONTH(CloseDate,'Rent Roll'!$O$7+'Rent Roll'!$S$7-1+'Rent Roll'!$V$7)),-K33,0) -> 0 | ... BX34: =IF(AND(BX$4>EOMONTH(CloseDate,'Rent Roll'!$O$7+'Rent Roll'!$S$7-1),BX$4<=EOMONTH(CloseDate,'Rent Roll'!$O$7+'Rent Roll'!$S$7-1+'Rent Roll'!$V$7)),-BX33,0) -> 0
B35: Net Base Rent | D35: =D31+D33+D34 -> 22000 | E35: =E31+E33+E34 -> 22000 | F35: =F31+F33+F34 -> 22550 | G35: =G31+G33+G34 -> 22550 | H35: =H31+H33+H34 -> 22550 | I35: =I31+I33+I34 -> 23113.75 | J35: =J31+J33+J34 -> 23113.75 | K35: =K31+K33+K34 -> 23113.75 | ... BX35: =BX31+BX33+BX34 -> 28947.684
B36: Opex Recovery (NNN) | D36: =IF(OR(D30=1,D32=1),'Rent Roll'!$F$7/BldgSF*ReimbPool/12*D$7,0) -> 10470 | E36: =IF(OR(E30=1,E32=1),'Rent Roll'!$F$7/BldgSF*ReimbPool/12*E$7,0) -> 10470 | F36: =IF(OR(F30=1,F32=1),'Rent Roll'!$F$7/BldgSF*ReimbPool/12*F$7,0) -> 10470 | G36: =IF(OR(G30=1,G32=1),'Rent Roll'!$F$7/BldgSF*ReimbPool/12*G$7,0) -> 10470 | H36: =IF(OR(H30=1,H32=1),'Rent Roll'!$F$7/BldgSF*ReimbPool/12*H$7,0) -> 10470 | I36: =IF(OR(I30=1,I32=1),'Rent Roll'!$F$7/BldgSF*ReimbPool/12*I$7,0) -> 10752.69 | J36: =IF(OR(J30=1,J32=1),'Rent Roll'!$F$7/BldgSF*ReimbPool/12*J$7,0) -> 10752.69 | K36: =IF(OR(K30=1,K32=1),'Rent Roll'!$F$7/BldgSF*ReimbPool/12*K$7,0) -> 10752.69 | ... BX36: =IF(OR(BX30=1,BX32=1),'Rent Roll'!$F$7/BldgSF*ReimbPool/12*BX$7,0) -> 12284.835
B37: TI (capital) | D37: =IF(D$4=EOMONTH(CloseDate,'Rent Roll'!$O$7+'Rent Roll'!$S$7),-'Rent Roll'!$F$7*'Rent Roll'!$T$7,0) -> 0 | E37: =IF(E$4=EOMONTH(CloseDate,'Rent Roll'!$O$7+'Rent Roll'!$S$7),-'Rent Roll'!$F$7*'Rent Roll'!$T$7,0) -> 0 | F37: =IF(F$4=EOMONTH(CloseDate,'Rent Roll'!$O$7+'Rent Roll'!$S$7),-'Rent Roll'!$F$7*'Rent Roll'!$T$7,0) -> 0 | G37: =IF(G$4=EOMONTH(CloseDate,'Rent Roll'!$O$7+'Rent Roll'!$S$7),-'Rent Roll'!$F$7*'Rent Roll'!$T$7,0) -> 0 | H37: =IF(H$4=EOMONTH(CloseDate,'Rent Roll'!$O$7+'Rent Roll'!$S$7),-'Rent Roll'!$F$7*'Rent Roll'!$T$7,0) -> 0 | I37: =IF(I$4=EOMONTH(CloseDate,'Rent Roll'!$O$7+'Rent Roll'!$S$7),-'Rent Roll'!$F$7*'Rent Roll'!$T$7,0) -> 0 | J37: =IF(J$4=EOMONTH(CloseDate,'Rent Roll'!$O$7+'Rent Roll'!$S$7),-'Rent Roll'!$F$7*'Rent Roll'!$T$7,0) -> 0 | K37: =IF(K$4=EOMONTH(CloseDate,'Rent Roll'!$O$7+'Rent Roll'!$S$7),-'Rent Roll'!$F$7*'Rent Roll'!$T$7,0) -> 0 | ... BX37: =IF(BX$4=EOMONTH(CloseDate,'Rent Roll'!$O$7+'Rent Roll'!$S$7),-'Rent Roll'!$F$7*'Rent Roll'!$T$7,0) -> 0
B38: LC (capital) | D38: =IF(D$4=EOMONTH(CloseDate,'Rent Roll'!$O$7+'Rent Roll'!$S$7),-'Rent Roll'!$U$7*'Rent Roll'!$F$7*'Rent Roll'!$X$7,0) -> 0 | E38: =IF(E$4=EOMONTH(CloseDate,'Rent Roll'!$O$7+'Rent Roll'!$S$7),-'Rent Roll'!$U$7*'Rent Roll'!$F$7*'Rent Roll'!$X$7,0) -> 0 | F38: =IF(F$4=EOMONTH(CloseDate,'Rent Roll'!$O$7+'Rent Roll'!$S$7),-'Rent Roll'!$U$7*'Rent Roll'!$F$7*'Rent Roll'!$X$7,0) -> 0 | G38: =IF(G$4=EOMONTH(CloseDate,'Rent Roll'!$O$7+'Rent Roll'!$S$7),-'Rent Roll'!$U$7*'Rent Roll'!$F$7*'Rent Roll'!$X$7,0) -> 0 | H38: =IF(H$4=EOMONTH(CloseDate,'Rent Roll'!$O$7+'Rent Roll'!$S$7),-'Rent Roll'!$U$7*'Rent Roll'!$F$7*'Rent Roll'!$X$7,0) -> 0 | I38: =IF(I$4=EOMONTH(CloseDate,'Rent Roll'!$O$7+'Rent Roll'!$S$7),-'Rent Roll'!$U$7*'Rent Roll'!$F$7*'Rent Roll'!$X$7,0) -> 0 | J38: =IF(J$4=EOMONTH(CloseDate,'Rent Roll'!$O$7+'Rent Roll'!$S$7),-'Rent Roll'!$U$7*'Rent Roll'!$F$7*'Rent Roll'!$X$7,0) -> 0 | K38: =IF(K$4=EOMONTH(CloseDate,'Rent Roll'!$O$7+'Rent Roll'!$S$7),-'Rent Roll'!$U$7*'Rent Roll'!$F$7*'Rent Roll'!$X$7,0) -> 0 | ... BX38: =IF(BX$4=EOMONTH(CloseDate,'Rent Roll'!$O$7+'Rent Roll'!$S$7),-'Rent Roll'!$U$7*'Rent Roll'!$F$7*'Rent Roll'!$X$7,0) -> 0
A39: ='Rent Roll'!C8 -> Pinnacle Wealth Advisors | B39: =INDEX('Rent Roll'!$F$5:$F$46,MATCH('Rent Roll Calc'!A39,'Rent Roll'!$C$5:$C$46,0)) -> 11000
B40: Occupancy Flag | D40: =IF(AND('Rent Roll'!$N$8<>"Ghost",D$4<='Rent Roll'!$L$8),1,0) -> 1 | E40: =IF(AND('Rent Roll'!$N$8<>"Ghost",E$4<='Rent Roll'!$L$8),1,0) -> 1 | F40: =IF(AND('Rent Roll'!$N$8<>"Ghost",F$4<='Rent Roll'!$L$8),1,0) -> 1 | G40: =IF(AND('Rent Roll'!$N$8<>"Ghost",G$4<='Rent Roll'!$L$8),1,0) -> 1 | H40: =IF(AND('Rent Roll'!$N$8<>"Ghost",H$4<='Rent Roll'!$L$8),1,0) -> 1 | I40: =IF(AND('Rent Roll'!$N$8<>"Ghost",I$4<='Rent Roll'!$L$8),1,0) -> 1 | J40: =IF(AND('Rent Roll'!$N$8<>"Ghost",J$4<='Rent Roll'!$L$8),1,0) -> 1 | K40: =IF(AND('Rent Roll'!$N$8<>"Ghost",K$4<='Rent Roll'!$L$8),1,0) -> 1 | ... BX40: =IF(AND('Rent Roll'!$N$8<>"Ghost",BX$4<='Rent Roll'!$L$8),1,0) -> 0
B41: In-Place Rent | D41: =IF(D40=1,'Rent Roll'!$H$8/12*(1+'Rent Roll'!$I$8)^IF(D$4<'Rent Roll'!$Y$8,0,YEAR(D$4)-YEAR('Rent Roll'!$Y$8)+1),0) -> 18562.5 | E41: =IF(E40=1,'Rent Roll'!$H$8/12*(1+'Rent Roll'!$I$8)^IF(E$4<'Rent Roll'!$Y$8,0,YEAR(E$4)-YEAR('Rent Roll'!$Y$8)+1),0) -> 18562.5 | F41: =IF(F40=1,'Rent Roll'!$H$8/12*(1+'Rent Roll'!$I$8)^IF(F$4<'Rent Roll'!$Y$8,0,YEAR(F$4)-YEAR('Rent Roll'!$Y$8)+1),0) -> 18562.5 | G41: =IF(G40=1,'Rent Roll'!$H$8/12*(1+'Rent Roll'!$I$8)^IF(G$4<'Rent Roll'!$Y$8,0,YEAR(G$4)-YEAR('Rent Roll'!$Y$8)+1),0) -> 18562.5 | H41: =IF(H40=1,'Rent Roll'!$H$8/12*(1+'Rent Roll'!$I$8)^IF(H$4<'Rent Roll'!$Y$8,0,YEAR(H$4)-YEAR('Rent Roll'!$Y$8)+1),0) -> 18562.5 | I41: =IF(I40=1,'Rent Roll'!$H$8/12*(1+'Rent Roll'!$I$8)^IF(I$4<'Rent Roll'!$Y$8,0,YEAR(I$4)-YEAR('Rent Roll'!$Y$8)+1),0) -> 18933.75 | J41: =IF(J40=1,'Rent Roll'!$H$8/12*(1+'Rent Roll'!$I$8)^IF(J$4<'Rent Roll'!$Y$8,0,YEAR(J$4)-YEAR('Rent Roll'!$Y$8)+1),0) -> 18933.75 | K41: =IF(K40=1,'Rent Roll'!$H$8/12*(1+'Rent Roll'!$I$8)^IF(K$4<'Rent Roll'!$Y$8,0,YEAR(K$4)-YEAR('Rent Roll'!$Y$8)+1),0) -> 18933.75 | ... BX41: =IF(BX40=1,'Rent Roll'!$H$8/12*(1+'Rent Roll'!$I$8)^IF(BX$4<'Rent Roll'!$Y$8,0,YEAR(BX$4)-YEAR('Rent Roll'!$Y$8)+1),0) -> 0
B42: Re-Let Flag | D42: =IF(D$4>EOMONTH(CloseDate,'Rent Roll'!$O$8+'Rent Roll'!$S$8-1),1,0) -> 0 | E42: =IF(E$4>EOMONTH(CloseDate,'Rent Roll'!$O$8+'Rent Roll'!$S$8-1),1,0) -> 0 | F42: =IF(F$4>EOMONTH(CloseDate,'Rent Roll'!$O$8+'Rent Roll'!$S$8-1),1,0) -> 0 | G42: =IF(G$4>EOMONTH(CloseDate,'Rent Roll'!$O$8+'Rent Roll'!$S$8-1),1,0) -> 0 | H42: =IF(H$4>EOMONTH(CloseDate,'Rent Roll'!$O$8+'Rent Roll'!$S$8-1),1,0) -> 0 | I42: =IF(I$4>EOMONTH(CloseDate,'Rent Roll'!$O$8+'Rent Roll'!$S$8-1),1,0) -> 0 | J42: =IF(J$4>EOMONTH(CloseDate,'Rent Roll'!$O$8+'Rent Roll'!$S$8-1),1,0) -> 0 | K42: =IF(K$4>EOMONTH(CloseDate,'Rent Roll'!$O$8+'Rent Roll'!$S$8-1),1,0) -> 0 | ... BX42: =IF(BX$4>EOMONTH(CloseDate,'Rent Roll'!$O$8+'Rent Roll'!$S$8-1),1,0) -> 1
B43: Re-Let Rent (gross) | D43: =IF(D42=1,'Rent Roll'!$F$8*'Rent Roll'!$X$8/12*D$6,0) -> 0 | E43: =IF(E42=1,'Rent Roll'!$F$8*'Rent Roll'!$X$8/12*E$6,0) -> 0 | F43: =IF(F42=1,'Rent Roll'!$F$8*'Rent Roll'!$X$8/12*F$6,0) -> 0 | G43: =IF(G42=1,'Rent Roll'!$F$8*'Rent Roll'!$X$8/12*G$6,0) -> 0 | H43: =IF(H42=1,'Rent Roll'!$F$8*'Rent Roll'!$X$8/12*H$6,0) -> 0 | I43: =IF(I42=1,'Rent Roll'!$F$8*'Rent Roll'!$X$8/12*I$6,0) -> 0 | J43: =IF(J42=1,'Rent Roll'!$F$8*'Rent Roll'!$X$8/12*J$6,0) -> 0 | K43: =IF(K42=1,'Rent Roll'!$F$8*'Rent Roll'!$X$8/12*K$6,0) -> 0 | ... BX43: =IF(BX42=1,'Rent Roll'!$F$8*'Rent Roll'!$X$8/12*BX$6,0) -> 26535.377
B44: Free Rent Adj | D44: =IF(AND(D$4>EOMONTH(CloseDate,'Rent Roll'!$O$8+'Rent Roll'!$S$8-1),D$4<=EOMONTH(CloseDate,'Rent Roll'!$O$8+'Rent Roll'!$S$8-1+'Rent Roll'!$V$8)),-D43,0) -> 0 | E44: =IF(AND(E$4>EOMONTH(CloseDate,'Rent Roll'!$O$8+'Rent Roll'!$S$8-1),E$4<=EOMONTH(CloseDate,'Rent Roll'!$O$8+'Rent Roll'!$S$8-1+'Rent Roll'!$V$8)),-E43,0) -> 0 | F44: =IF(AND(F$4>EOMONTH(CloseDate,'Rent Roll'!$O$8+'Rent Roll'!$S$8-1),F$4<=EOMONTH(CloseDate,'Rent Roll'!$O$8+'Rent Roll'!$S$8-1+'Rent Roll'!$V$8)),-F43,0) -> 0 | G44: =IF(AND(G$4>EOMONTH(CloseDate,'Rent Roll'!$O$8+'Rent Roll'!$S$8-1),G$4<=EOMONTH(CloseDate,'Rent Roll'!$O$8+'Rent Roll'!$S$8-1+'Rent Roll'!$V$8)),-G43,0) -> 0 | H44: =IF(AND(H$4>EOMONTH(CloseDate,'Rent Roll'!$O$8+'Rent Roll'!$S$8-1),H$4<=EOMONTH(CloseDate,'Rent Roll'!$O$8+'Rent Roll'!$S$8-1+'Rent Roll'!$V$8)),-H43,0) -> 0 | I44: =IF(AND(I$4>EOMONTH(CloseDate,'Rent Roll'!$O$8+'Rent Roll'!$S$8-1),I$4<=EOMONTH(CloseDate,'Rent Roll'!$O$8+'Rent Roll'!$S$8-1+'Rent Roll'!$V$8)),-I43,0) -> 0 | J44: =IF(AND(J$4>EOMONTH(CloseDate,'Rent Roll'!$O$8+'Rent Roll'!$S$8-1),J$4<=EOMONTH(CloseDate,'Rent Roll'!$O$8+'Rent Roll'!$S$8-1+'Rent Roll'!$V$8)),-J43,0) -> 0 | K44: =IF(AND(K$4>EOMONTH(CloseDate,'Rent Roll'!$O$8+'Rent Roll'!$S$8-1),K$4<=EOMONTH(CloseDate,'Rent Roll'!$O$8+'Rent Roll'!$S$8-1+'Rent Roll'!$V$8)),-K43,0) -> 0 | ... BX44: =IF(AND(BX$4>EOMONTH(CloseDate,'Rent Roll'!$O$8+'Rent Roll'!$S$8-1),BX$4<=EOMONTH(CloseDate,'Rent Roll'!$O$8+'Rent Roll'!$S$8-1+'Rent Roll'!$V$8)),-BX43,0) -> 0
B45: Net Base Rent | D45: =D41+D43+D44 -> 18562.5 | E45: =E41+E43+E44 -> 18562.5 | F45: =F41+F43+F44 -> 18562.5 | G45: =G41+G43+G44 -> 18562.5 | H45: =H41+H43+H44 -> 18562.5 | I45: =I41+I43+I44 -> 18933.75 | J45: =J41+J43+J44 -> 18933.75 | K45: =K41+K43+K44 -> 18933.75 | ... BX45: =BX41+BX43+BX44 -> 26535.377
B46: Opex Recovery (NNN) | D46: =IF(OR(D40=1,D42=1),'Rent Roll'!$F$8/BldgSF*ReimbPool/12*D$7,0) -> 9597.5 | E46: =IF(OR(E40=1,E42=1),'Rent Roll'!$F$8/BldgSF*ReimbPool/12*E$7,0) -> 9597.5 | F46: =IF(OR(F40=1,F42=1),'Rent Roll'!$F$8/BldgSF*ReimbPool/12*F$7,0) -> 9597.5 | G46: =IF(OR(G40=1,G42=1),'Rent Roll'!$F$8/BldgSF*ReimbPool/12*G$7,0) -> 9597.5 | H46: =IF(OR(H40=1,H42=1),'Rent Roll'!$F$8/BldgSF*ReimbPool/12*H$7,0) -> 9597.5 | I46: =IF(OR(I40=1,I42=1),'Rent Roll'!$F$8/BldgSF*ReimbPool/12*I$7,0) -> 9856.6325 | J46: =IF(OR(J40=1,J42=1),'Rent Roll'!$F$8/BldgSF*ReimbPool/12*J$7,0) -> 9856.6325 | K46: =IF(OR(K40=1,K42=1),'Rent Roll'!$F$8/BldgSF*ReimbPool/12*K$7,0) -> 9856.6325 | ... BX46: =IF(OR(BX40=1,BX42=1),'Rent Roll'!$F$8/BldgSF*ReimbPool/12*BX$7,0) -> 11261.099
B47: TI (capital) | D47: =IF(D$4=EOMONTH(CloseDate,'Rent Roll'!$O$8+'Rent Roll'!$S$8),-'Rent Roll'!$F$8*'Rent Roll'!$T$8,0) -> 0 | E47: =IF(E$4=EOMONTH(CloseDate,'Rent Roll'!$O$8+'Rent Roll'!$S$8),-'Rent Roll'!$F$8*'Rent Roll'!$T$8,0) -> 0 | F47: =IF(F$4=EOMONTH(CloseDate,'Rent Roll'!$O$8+'Rent Roll'!$S$8),-'Rent Roll'!$F$8*'Rent Roll'!$T$8,0) -> 0 | G47: =IF(G$4=EOMONTH(CloseDate,'Rent Roll'!$O$8+'Rent Roll'!$S$8),-'Rent Roll'!$F$8*'Rent Roll'!$T$8,0) -> 0 | H47: =IF(H$4=EOMONTH(CloseDate,'Rent Roll'!$O$8+'Rent Roll'!$S$8),-'Rent Roll'!$F$8*'Rent Roll'!$T$8,0) -> 0 | I47: =IF(I$4=EOMONTH(CloseDate,'Rent Roll'!$O$8+'Rent Roll'!$S$8),-'Rent Roll'!$F$8*'Rent Roll'!$T$8,0) -> 0 | J47: =IF(J$4=EOMONTH(CloseDate,'Rent Roll'!$O$8+'Rent Roll'!$S$8),-'Rent Roll'!$F$8*'Rent Roll'!$T$8,0) -> 0 | K47: =IF(K$4=EOMONTH(CloseDate,'Rent Roll'!$O$8+'Rent Roll'!$S$8),-'Rent Roll'!$F$8*'Rent Roll'!$T$8,0) -> 0 | ... BX47: =IF(BX$4=EOMONTH(CloseDate,'Rent Roll'!$O$8+'Rent Roll'!$S$8),-'Rent Roll'!$F$8*'Rent Roll'!$T$8,0) -> 0
B48: LC (capital) | D48: =IF(D$4=EOMONTH(CloseDate,'Rent Roll'!$O$8+'Rent Roll'!$S$8),-'Rent Roll'!$U$8*'Rent Roll'!$F$8*'Rent Roll'!$X$8,0) -> 0 | E48: =IF(E$4=EOMONTH(CloseDate,'Rent Roll'!$O$8+'Rent Roll'!$S$8),-'Rent Roll'!$U$8*'Rent Roll'!$F$8*'Rent Roll'!$X$8,0) -> 0 | F48: =IF(F$4=EOMONTH(CloseDate,'Rent Roll'!$O$8+'Rent Roll'!$S$8),-'Rent Roll'!$U$8*'Rent Roll'!$F$8*'Rent Roll'!$X$8,0) -> 0 | G48: =IF(G$4=EOMONTH(CloseDate,'Rent Roll'!$O$8+'Rent Roll'!$S$8),-'Rent Roll'!$U$8*'Rent Roll'!$F$8*'Rent Roll'!$X$8,0) -> 0 | H48: =IF(H$4=EOMONTH(CloseDate,'Rent Roll'!$O$8+'Rent Roll'!$S$8),-'Rent Roll'!$U$8*'Rent Roll'!$F$8*'Rent Roll'!$X$8,0) -> 0 | I48: =IF(I$4=EOMONTH(CloseDate,'Rent Roll'!$O$8+'Rent Roll'!$S$8),-'Rent Roll'!$U$8*'Rent Roll'!$F$8*'Rent Roll'!$X$8,0) -> 0 | J48: =IF(J$4=EOMONTH(CloseDate,'Rent Roll'!$O$8+'Rent Roll'!$S$8),-'Rent Roll'!$U$8*'Rent Roll'!$F$8*'Rent Roll'!$X$8,0) -> 0 | K48: =IF(K$4=EOMONTH(CloseDate,'Rent Roll'!$O$8+'Rent Roll'!$S$8),-'Rent Roll'!$U$8*'Rent Roll'!$F$8*'Rent Roll'!$X$8,0) -> 0 | ... BX48: =IF(BX$4=EOMONTH(CloseDate,'Rent Roll'!$O$8+'Rent Roll'!$S$8),-'Rent Roll'!$U$8*'Rent Roll'!$F$8*'Rent Roll'!$X$8,0) -> 0
A49: ='Rent Roll'!C9 -> TechBridge Solutions | B49: =INDEX('Rent Roll'!$F$5:$F$46,MATCH('Rent Roll Calc'!A49,'Rent Roll'!$C$5:$C$46,0)) -> 10500
B50: Occupancy Flag | D50: =IF(AND('Rent Roll'!$N$9<>"Ghost",D$4<='Rent Roll'!$L$9),1,0) -> 1 | E50: =IF(AND('Rent Roll'!$N$9<>"Ghost",E$4<='Rent Roll'!$L$9),1,0) -> 1 | F50: =IF(AND('Rent Roll'!$N$9<>"Ghost",F$4<='Rent Roll'!$L$9),1,0) -> 1 | G50: =IF(AND('Rent Roll'!$N$9<>"Ghost",G$4<='Rent Roll'!$L$9),1,0) -> 1 | H50: =IF(AND('Rent Roll'!$N$9<>"Ghost",H$4<='Rent Roll'!$L$9),1,0) -> 1 | I50: =IF(AND('Rent Roll'!$N$9<>"Ghost",I$4<='Rent Roll'!$L$9),1,0) -> 1 | J50: =IF(AND('Rent Roll'!$N$9<>"Ghost",J$4<='Rent Roll'!$L$9),1,0) -> 1 | K50: =IF(AND('Rent Roll'!$N$9<>"Ghost",K$4<='Rent Roll'!$L$9),1,0) -> 1 | ... BX50: =IF(AND('Rent Roll'!$N$9<>"Ghost",BX$4<='Rent Roll'!$L$9),1,0) -> 0
B51: In-Place Rent | D51: =IF(D50=1,'Rent Roll'!$H$9/12*(1+'Rent Roll'!$I$9)^IF(D$4<'Rent Roll'!$Y$9,0,YEAR(D$4)-YEAR('Rent Roll'!$Y$9)+1),0) -> 19031.25 | E51: =IF(E50=1,'Rent Roll'!$H$9/12*(1+'Rent Roll'!$I$9)^IF(E$4<'Rent Roll'!$Y$9,0,YEAR(E$4)-YEAR('Rent Roll'!$Y$9)+1),0) -> 19031.25 | F51: =IF(F50=1,'Rent Roll'!$H$9/12*(1+'Rent Roll'!$I$9)^IF(F$4<'Rent Roll'!$Y$9,0,YEAR(F$4)-YEAR('Rent Roll'!$Y$9)+1),0) -> 19031.25 | G51: =IF(G50=1,'Rent Roll'!$H$9/12*(1+'Rent Roll'!$I$9)^IF(G$4<'Rent Roll'!$Y$9,0,YEAR(G$4)-YEAR('Rent Roll'!$Y$9)+1),0) -> 19031.25 | H51: =IF(H50=1,'Rent Roll'!$H$9/12*(1+'Rent Roll'!$I$9)^IF(H$4<'Rent Roll'!$Y$9,0,YEAR(H$4)-YEAR('Rent Roll'!$Y$9)+1),0) -> 19031.25 | I51: =IF(I50=1,'Rent Roll'!$H$9/12*(1+'Rent Roll'!$I$9)^IF(I$4<'Rent Roll'!$Y$9,0,YEAR(I$4)-YEAR('Rent Roll'!$Y$9)+1),0) -> 19031.25 | J51: =IF(J50=1,'Rent Roll'!$H$9/12*(1+'Rent Roll'!$I$9)^IF(J$4<'Rent Roll'!$Y$9,0,YEAR(J$4)-YEAR('Rent Roll'!$Y$9)+1),0) -> 19031.25 | K51: =IF(K50=1,'Rent Roll'!$H$9/12*(1+'Rent Roll'!$I$9)^IF(K$4<'Rent Roll'!$Y$9,0,YEAR(K$4)-YEAR('Rent Roll'!$Y$9)+1),0) -> 19031.25 | ... BX51: =IF(BX50=1,'Rent Roll'!$H$9/12*(1+'Rent Roll'!$I$9)^IF(BX$4<'Rent Roll'!$Y$9,0,YEAR(BX$4)-YEAR('Rent Roll'!$Y$9)+1),0) -> 0
B52: Re-Let Flag | D52: =IF(D$4>EOMONTH(CloseDate,'Rent Roll'!$O$9+'Rent Roll'!$S$9-1),1,0) -> 0 | E52: =IF(E$4>EOMONTH(CloseDate,'Rent Roll'!$O$9+'Rent Roll'!$S$9-1),1,0) -> 0 | F52: =IF(F$4>EOMONTH(CloseDate,'Rent Roll'!$O$9+'Rent Roll'!$S$9-1),1,0) -> 0 | G52: =IF(G$4>EOMONTH(CloseDate,'Rent Roll'!$O$9+'Rent Roll'!$S$9-1),1,0) -> 0 | H52: =IF(H$4>EOMONTH(CloseDate,'Rent Roll'!$O$9+'Rent Roll'!$S$9-1),1,0) -> 0 | I52: =IF(I$4>EOMONTH(CloseDate,'Rent Roll'!$O$9+'Rent Roll'!$S$9-1),1,0) -> 0 | J52: =IF(J$4>EOMONTH(CloseDate,'Rent Roll'!$O$9+'Rent Roll'!$S$9-1),1,0) -> 0 | K52: =IF(K$4>EOMONTH(CloseDate,'Rent Roll'!$O$9+'Rent Roll'!$S$9-1),1,0) -> 0 | ... BX52: =IF(BX$4>EOMONTH(CloseDate,'Rent Roll'!$O$9+'Rent Roll'!$S$9-1),1,0) -> 1
B53: Re-Let Rent (gross) | D53: =IF(D52=1,'Rent Roll'!$F$9*'Rent Roll'!$X$9/12*D$6,0) -> 0 | E53: =IF(E52=1,'Rent Roll'!$F$9*'Rent Roll'!$X$9/12*E$6,0) -> 0 | F53: =IF(F52=1,'Rent Roll'!$F$9*'Rent Roll'!$X$9/12*F$6,0) -> 0 | G53: =IF(G52=1,'Rent Roll'!$F$9*'Rent Roll'!$X$9/12*G$6,0) -> 0 | H53: =IF(H52=1,'Rent Roll'!$F$9*'Rent Roll'!$X$9/12*H$6,0) -> 0 | I53: =IF(I52=1,'Rent Roll'!$F$9*'Rent Roll'!$X$9/12*I$6,0) -> 0 | J53: =IF(J52=1,'Rent Roll'!$F$9*'Rent Roll'!$X$9/12*J$6,0) -> 0 | K53: =IF(K52=1,'Rent Roll'!$F$9*'Rent Roll'!$X$9/12*K$6,0) -> 0 | ... BX53: =IF(BX52=1,'Rent Roll'!$F$9*'Rent Roll'!$X$9/12*BX$6,0) -> 25329.223
B54: Free Rent Adj | D54: =IF(AND(D$4>EOMONTH(CloseDate,'Rent Roll'!$O$9+'Rent Roll'!$S$9-1),D$4<=EOMONTH(CloseDate,'Rent Roll'!$O$9+'Rent Roll'!$S$9-1+'Rent Roll'!$V$9)),-D53,0) -> 0 | E54: =IF(AND(E$4>EOMONTH(CloseDate,'Rent Roll'!$O$9+'Rent Roll'!$S$9-1),E$4<=EOMONTH(CloseDate,'Rent Roll'!$O$9+'Rent Roll'!$S$9-1+'Rent Roll'!$V$9)),-E53,0) -> 0 | F54: =IF(AND(F$4>EOMONTH(CloseDate,'Rent Roll'!$O$9+'Rent Roll'!$S$9-1),F$4<=EOMONTH(CloseDate,'Rent Roll'!$O$9+'Rent Roll'!$S$9-1+'Rent Roll'!$V$9)),-F53,0) -> 0 | G54: =IF(AND(G$4>EOMONTH(CloseDate,'Rent Roll'!$O$9+'Rent Roll'!$S$9-1),G$4<=EOMONTH(CloseDate,'Rent Roll'!$O$9+'Rent Roll'!$S$9-1+'Rent Roll'!$V$9)),-G53,0) -> 0 | H54: =IF(AND(H$4>EOMONTH(CloseDate,'Rent Roll'!$O$9+'Rent Roll'!$S$9-1),H$4<=EOMONTH(CloseDate,'Rent Roll'!$O$9+'Rent Roll'!$S$9-1+'Rent Roll'!$V$9)),-H53,0) -> 0 | I54: =IF(AND(I$4>EOMONTH(CloseDate,'Rent Roll'!$O$9+'Rent Roll'!$S$9-1),I$4<=EOMONTH(CloseDate,'Rent Roll'!$O$9+'Rent Roll'!$S$9-1+'Rent Roll'!$V$9)),-I53,0) -> 0 | J54: =IF(AND(J$4>EOMONTH(CloseDate,'Rent Roll'!$O$9+'Rent Roll'!$S$9-1),J$4<=EOMONTH(CloseDate,'Rent Roll'!$O$9+'Rent Roll'!$S$9-1+'Rent Roll'!$V$9)),-J53,0) -> 0 | K54: =IF(AND(K$4>EOMONTH(CloseDate,'Rent Roll'!$O$9+'Rent Roll'!$S$9-1),K$4<=EOMONTH(CloseDate,'Rent Roll'!$O$9+'Rent Roll'!$S$9-1+'Rent Roll'!$V$9)),-K53,0) -> 0 | ... BX54: =IF(AND(BX$4>EOMONTH(CloseDate,'Rent Roll'!$O$9+'Rent Roll'!$S$9-1),BX$4<=EOMONTH(CloseDate,'Rent Roll'!$O$9+'Rent Roll'!$S$9-1+'Rent Roll'!$V$9)),-BX53,0) -> 0
B55: Net Base Rent | D55: =D51+D53+D54 -> 19031.25 | E55: =E51+E53+E54 -> 19031.25 | F55: =F51+F53+F54 -> 19031.25 | G55: =G51+G53+G54 -> 19031.25 | H55: =H51+H53+H54 -> 19031.25 | I55: =I51+I53+I54 -> 19031.25 | J55: =J51+J53+J54 -> 19031.25 | K55: =K51+K53+K54 -> 19031.25 | ... BX55: =BX51+BX53+BX54 -> 25329.223
B56: Opex Recovery (NNN) | D56: =IF(OR(D50=1,D52=1),'Rent Roll'!$F$9/BldgSF*ReimbPool/12*D$7,0) -> 9161.25 | E56: =IF(OR(E50=1,E52=1),'Rent Roll'!$F$9/BldgSF*ReimbPool/12*E$7,0) -> 9161.25 | F56: =IF(OR(F50=1,F52=1),'Rent Roll'!$F$9/BldgSF*ReimbPool/12*F$7,0) -> 9161.25 | G56: =IF(OR(G50=1,G52=1),'Rent Roll'!$F$9/BldgSF*ReimbPool/12*G$7,0) -> 9161.25 | H56: =IF(OR(H50=1,H52=1),'Rent Roll'!$F$9/BldgSF*ReimbPool/12*H$7,0) -> 9161.25 | I56: =IF(OR(I50=1,I52=1),'Rent Roll'!$F$9/BldgSF*ReimbPool/12*I$7,0) -> 9408.6037 | J56: =IF(OR(J50=1,J52=1),'Rent Roll'!$F$9/BldgSF*ReimbPool/12*J$7,0) -> 9408.6037 | K56: =IF(OR(K50=1,K52=1),'Rent Roll'!$F$9/BldgSF*ReimbPool/12*K$7,0) -> 9408.6037 | ... BX56: =IF(OR(BX50=1,BX52=1),'Rent Roll'!$F$9/BldgSF*ReimbPool/12*BX$7,0) -> 10749.231
B57: TI (capital) | D57: =IF(D$4=EOMONTH(CloseDate,'Rent Roll'!$O$9+'Rent Roll'!$S$9),-'Rent Roll'!$F$9*'Rent Roll'!$T$9,0) -> 0 | E57: =IF(E$4=EOMONTH(CloseDate,'Rent Roll'!$O$9+'Rent Roll'!$S$9),-'Rent Roll'!$F$9*'Rent Roll'!$T$9,0) -> 0 | F57: =IF(F$4=EOMONTH(CloseDate,'Rent Roll'!$O$9+'Rent Roll'!$S$9),-'Rent Roll'!$F$9*'Rent Roll'!$T$9,0) -> 0 | G57: =IF(G$4=EOMONTH(CloseDate,'Rent Roll'!$O$9+'Rent Roll'!$S$9),-'Rent Roll'!$F$9*'Rent Roll'!$T$9,0) -> 0 | H57: =IF(H$4=EOMONTH(CloseDate,'Rent Roll'!$O$9+'Rent Roll'!$S$9),-'Rent Roll'!$F$9*'Rent Roll'!$T$9,0) -> 0 | I57: =IF(I$4=EOMONTH(CloseDate,'Rent Roll'!$O$9+'Rent Roll'!$S$9),-'Rent Roll'!$F$9*'Rent Roll'!$T$9,0) -> 0 | J57: =IF(J$4=EOMONTH(CloseDate,'Rent Roll'!$O$9+'Rent Roll'!$S$9),-'Rent Roll'!$F$9*'Rent Roll'!$T$9,0) -> 0 | K57: =IF(K$4=EOMONTH(CloseDate,'Rent Roll'!$O$9+'Rent Roll'!$S$9),-'Rent Roll'!$F$9*'Rent Roll'!$T$9,0) -> 0 | ... BX57: =IF(BX$4=EOMONTH(CloseDate,'Rent Roll'!$O$9+'Rent Roll'!$S$9),-'Rent Roll'!$F$9*'Rent Roll'!$T$9,0) -> 0
B58: LC (capital) | D58: =IF(D$4=EOMONTH(CloseDate,'Rent Roll'!$O$9+'Rent Roll'!$S$9),-'Rent Roll'!$U$9*'Rent Roll'!$F$9*'Rent Roll'!$X$9,0) -> 0 | E58: =IF(E$4=EOMONTH(CloseDate,'Rent Roll'!$O$9+'Rent Roll'!$S$9),-'Rent Roll'!$U$9*'Rent Roll'!$F$9*'Rent Roll'!$X$9,0) -> 0 | F58: =IF(F$4=EOMONTH(CloseDate,'Rent Roll'!$O$9+'Rent Roll'!$S$9),-'Rent Roll'!$U$9*'Rent Roll'!$F$9*'Rent Roll'!$X$9,0) -> 0 | G58: =IF(G$4=EOMONTH(CloseDate,'Rent Roll'!$O$9+'Rent Roll'!$S$9),-'Rent Roll'!$U$9*'Rent Roll'!$F$9*'Rent Roll'!$X$9,0) -> 0 | H58: =IF(H$4=EOMONTH(CloseDate,'Rent Roll'!$O$9+'Rent Roll'!$S$9),-'Rent Roll'!$U$9*'Rent Roll'!$F$9*'Rent Roll'!$X$9,0) -> 0 | I58: =IF(I$4=EOMONTH(CloseDate,'Rent Roll'!$O$9+'Rent Roll'!$S$9),-'Rent Roll'!$U$9*'Rent Roll'!$F$9*'Rent Roll'!$X$9,0) -> 0 | J58: =IF(J$4=EOMONTH(CloseDate,'Rent Roll'!$O$9+'Rent Roll'!$S$9),-'Rent Roll'!$U$9*'Rent Roll'!$F$9*'Rent Roll'!$X$9,0) -> 0 | K58: =IF(K$4=EOMONTH(CloseDate,'Rent Roll'!$O$9+'Rent Roll'!$S$9),-'Rent Roll'!$U$9*'Rent Roll'!$F$9*'Rent Roll'!$X$9,0) -> 0 | ... BX58: =IF(BX$4=EOMONTH(CloseDate,'Rent Roll'!$O$9+'Rent Roll'!$S$9),-'Rent Roll'!$U$9*'Rent Roll'!$F$9*'Rent Roll'!$X$9,0) -> 0
A59: ='Rent Roll'!C10 -> Brightpath Insurance | B59: =INDEX('Rent Roll'!$F$5:$F$46,MATCH('Rent Roll Calc'!A59,'Rent Roll'!$C$5:$C$46,0)) -> 7900
B60: Occupancy Flag | D60: =IF(AND('Rent Roll'!$N$10<>"Ghost",D$4<='Rent Roll'!$L$10),1,0) -> 1 | E60: =IF(AND('Rent Roll'!$N$10<>"Ghost",E$4<='Rent Roll'!$L$10),1,0) -> 1 | F60: =IF(AND('Rent Roll'!$N$10<>"Ghost",F$4<='Rent Roll'!$L$10),1,0) -> 1 | G60: =IF(AND('Rent Roll'!$N$10<>"Ghost",G$4<='Rent Roll'!$L$10),1,0) -> 1 | H60: =IF(AND('Rent Roll'!$N$10<>"Ghost",H$4<='Rent Roll'!$L$10),1,0) -> 1 | I60: =IF(AND('Rent Roll'!$N$10<>"Ghost",I$4<='Rent Roll'!$L$10),1,0) -> 1 | J60: =IF(AND('Rent Roll'!$N$10<>"Ghost",J$4<='Rent Roll'!$L$10),1,0) -> 1 | K60: =IF(AND('Rent Roll'!$N$10<>"Ghost",K$4<='Rent Roll'!$L$10),1,0) -> 1 | ... BX60: =IF(AND('Rent Roll'!$N$10<>"Ghost",BX$4<='Rent Roll'!$L$10),1,0) -> 0
B61: In-Place Rent | D61: =IF(D60=1,'Rent Roll'!$H$10/12*(1+'Rent Roll'!$I$10)^IF(D$4<'Rent Roll'!$Y$10,0,YEAR(D$4)-YEAR('Rent Roll'!$Y$10)+1),0) -> 13660.417 | E61: =IF(E60=1,'Rent Roll'!$H$10/12*(1+'Rent Roll'!$I$10)^IF(E$4<'Rent Roll'!$Y$10,0,YEAR(E$4)-YEAR('Rent Roll'!$Y$10)+1),0) -> 13660.417 | F61: =IF(F60=1,'Rent Roll'!$H$10/12*(1+'Rent Roll'!$I$10)^IF(F$4<'Rent Roll'!$Y$10,0,YEAR(F$4)-YEAR('Rent Roll'!$Y$10)+1),0) -> 13660.417 | G61: =IF(G60=1,'Rent Roll'!$H$10/12*(1+'Rent Roll'!$I$10)^IF(G$4<'Rent Roll'!$Y$10,0,YEAR(G$4)-YEAR('Rent Roll'!$Y$10)+1),0) -> 13660.417 | H61: =IF(H60=1,'Rent Roll'!$H$10/12*(1+'Rent Roll'!$I$10)^IF(H$4<'Rent Roll'!$Y$10,0,YEAR(H$4)-YEAR('Rent Roll'!$Y$10)+1),0) -> 13660.417 | I61: =IF(I60=1,'Rent Roll'!$H$10/12*(1+'Rent Roll'!$I$10)^IF(I$4<'Rent Roll'!$Y$10,0,YEAR(I$4)-YEAR('Rent Roll'!$Y$10)+1),0) -> 13660.417 | J61: =IF(J60=1,'Rent Roll'!$H$10/12*(1+'Rent Roll'!$I$10)^IF(J$4<'Rent Roll'!$Y$10,0,YEAR(J$4)-YEAR('Rent Roll'!$Y$10)+1),0) -> 13660.417 | K61: =IF(K60=1,'Rent Roll'!$H$10/12*(1+'Rent Roll'!$I$10)^IF(K$4<'Rent Roll'!$Y$10,0,YEAR(K$4)-YEAR('Rent Roll'!$Y$10)+1),0) -> 14001.927 | ... BX61: =IF(BX60=1,'Rent Roll'!$H$10/12*(1+'Rent Roll'!$I$10)^IF(BX$4<'Rent Roll'!$Y$10,0,YEAR(BX$4)-YEAR('Rent Roll'!$Y$10)+1),0) -> 0
B62: Re-Let Flag | D62: =IF(D$4>EOMONTH(CloseDate,'Rent Roll'!$O$10+'Rent Roll'!$S$10-1),1,0) -> 0 | E62: =IF(E$4>EOMONTH(CloseDate,'Rent Roll'!$O$10+'Rent Roll'!$S$10-1),1,0) -> 0 | F62: =IF(F$4>EOMONTH(CloseDate,'Rent Roll'!$O$10+'Rent Roll'!$S$10-1),1,0) -> 0 | G62: =IF(G$4>EOMONTH(CloseDate,'Rent Roll'!$O$10+'Rent Roll'!$S$10-1),1,0) -> 0 | H62: =IF(H$4>EOMONTH(CloseDate,'Rent Roll'!$O$10+'Rent Roll'!$S$10-1),1,0) -> 0 | I62: =IF(I$4>EOMONTH(CloseDate,'Rent Roll'!$O$10+'Rent Roll'!$S$10-1),1,0) -> 0 | J62: =IF(J$4>EOMONTH(CloseDate,'Rent Roll'!$O$10+'Rent Roll'!$S$10-1),1,0) -> 0 | K62: =IF(K$4>EOMONTH(CloseDate,'Rent Roll'!$O$10+'Rent Roll'!$S$10-1),1,0) -> 0 | ... BX62: =IF(BX$4>EOMONTH(CloseDate,'Rent Roll'!$O$10+'Rent Roll'!$S$10-1),1,0) -> 1
B63: Re-Let Rent (gross) | D63: =IF(D62=1,'Rent Roll'!$F$10*'Rent Roll'!$X$10/12*D$6,0) -> 0 | E63: =IF(E62=1,'Rent Roll'!$F$10*'Rent Roll'!$X$10/12*E$6,0) -> 0 | F63: =IF(F62=1,'Rent Roll'!$F$10*'Rent Roll'!$X$10/12*F$6,0) -> 0 | G63: =IF(G62=1,'Rent Roll'!$F$10*'Rent Roll'!$X$10/12*G$6,0) -> 0 | H63: =IF(H62=1,'Rent Roll'!$F$10*'Rent Roll'!$X$10/12*H$6,0) -> 0 | I63: =IF(I62=1,'Rent Roll'!$F$10*'Rent Roll'!$X$10/12*I$6,0) -> 0 | J63: =IF(J62=1,'Rent Roll'!$F$10*'Rent Roll'!$X$10/12*J$6,0) -> 0 | K63: =IF(K62=1,'Rent Roll'!$F$10*'Rent Roll'!$X$10/12*K$6,0) -> 0 | ... BX63: =IF(BX62=1,'Rent Roll'!$F$10*'Rent Roll'!$X$10/12*BX$6,0) -> 19057.225
B64: Free Rent Adj | D64: =IF(AND(D$4>EOMONTH(CloseDate,'Rent Roll'!$O$10+'Rent Roll'!$S$10-1),D$4<=EOMONTH(CloseDate,'Rent Roll'!$O$10+'Rent Roll'!$S$10-1+'Rent Roll'!$V$10)),-D63,0) -> 0 | E64: =IF(AND(E$4>EOMONTH(CloseDate,'Rent Roll'!$O$10+'Rent Roll'!$S$10-1),E$4<=EOMONTH(CloseDate,'Rent Roll'!$O$10+'Rent Roll'!$S$10-1+'Rent Roll'!$V$10)),-E63,0) -> 0 | F64: =IF(AND(F$4>EOMONTH(CloseDate,'Rent Roll'!$O$10+'Rent Roll'!$S$10-1),F$4<=EOMONTH(CloseDate,'Rent Roll'!$O$10+'Rent Roll'!$S$10-1+'Rent Roll'!$V$10)),-F63,0) -> 0 | G64: =IF(AND(G$4>EOMONTH(CloseDate,'Rent Roll'!$O$10+'Rent Roll'!$S$10-1),G$4<=EOMONTH(CloseDate,'Rent Roll'!$O$10+'Rent Roll'!$S$10-1+'Rent Roll'!$V$10)),-G63,0) -> 0 | H64: =IF(AND(H$4>EOMONTH(CloseDate,'Rent Roll'!$O$10+'Rent Roll'!$S$10-1),H$4<=EOMONTH(CloseDate,'Rent Roll'!$O$10+'Rent Roll'!$S$10-1+'Rent Roll'!$V$10)),-H63,0) -> 0 | I64: =IF(AND(I$4>EOMONTH(CloseDate,'Rent Roll'!$O$10+'Rent Roll'!$S$10-1),I$4<=EOMONTH(CloseDate,'Rent Roll'!$O$10+'Rent Roll'!$S$10-1+'Rent Roll'!$V$10)),-I63,0) -> 0 | J64: =IF(AND(J$4>EOMONTH(CloseDate,'Rent Roll'!$O$10+'Rent Roll'!$S$10-1),J$4<=EOMONTH(CloseDate,'Rent Roll'!$O$10+'Rent Roll'!$S$10-1+'Rent Roll'!$V$10)),-J63,0) -> 0 | K64: =IF(AND(K$4>EOMONTH(CloseDate,'Rent Roll'!$O$10+'Rent Roll'!$S$10-1),K$4<=EOMONTH(CloseDate,'Rent Roll'!$O$10+'Rent Roll'!$S$10-1+'Rent Roll'!$V$10)),-K63,0) -> 0 | ... BX64: =IF(AND(BX$4>EOMONTH(CloseDate,'Rent Roll'!$O$10+'Rent Roll'!$S$10-1),BX$4<=EOMONTH(CloseDate,'Rent Roll'!$O$10+'Rent Roll'!$S$10-1+'Rent Roll'!$V$10)),-BX63,0) -> 0
B65: Net Base Rent | D65: =D61+D63+D64 -> 13660.417 | E65: =E61+E63+E64 -> 13660.417 | F65: =F61+F63+F64 -> 13660.417 | G65: =G61+G63+G64 -> 13660.417 | H65: =H61+H63+H64 -> 13660.417 | I65: =I61+I63+I64 -> 13660.417 | J65: =J61+J63+J64 -> 13660.417 | K65: =K61+K63+K64 -> 14001.927 | ... BX65: =BX61+BX63+BX64 -> 19057.225
B66: Opex Recovery (NNN) | D66: =IF(OR(D60=1,D62=1),'Rent Roll'!$F$10/BldgSF*ReimbPool/12*D$7,0) -> 6892.75 | E66: =IF(OR(E60=1,E62=1),'Rent Roll'!$F$10/BldgSF*ReimbPool/12*E$7,0) -> 6892.75 | F66: =IF(OR(F60=1,F62=1),'Rent Roll'!$F$10/BldgSF*ReimbPool/12*F$7,0) -> 6892.75 | G66: =IF(OR(G60=1,G62=1),'Rent Roll'!$F$10/BldgSF*ReimbPool/12*G$7,0) -> 6892.75 | H66: =IF(OR(H60=1,H62=1),'Rent Roll'!$F$10/BldgSF*ReimbPool/12*H$7,0) -> 6892.75 | I66: =IF(OR(I60=1,I62=1),'Rent Roll'!$F$10/BldgSF*ReimbPool/12*I$7,0) -> 7078.8542 | J66: =IF(OR(J60=1,J62=1),'Rent Roll'!$F$10/BldgSF*ReimbPool/12*J$7,0) -> 7078.8542 | K66: =IF(OR(K60=1,K62=1),'Rent Roll'!$F$10/BldgSF*ReimbPool/12*K$7,0) -> 7078.8542 | ... BX66: =IF(OR(BX60=1,BX62=1),'Rent Roll'!$F$10/BldgSF*ReimbPool/12*BX$7,0) -> 8087.5167
B67: TI (capital) | D67: =IF(D$4=EOMONTH(CloseDate,'Rent Roll'!$O$10+'Rent Roll'!$S$10),-'Rent Roll'!$F$10*'Rent Roll'!$T$10,0) -> 0 | E67: =IF(E$4=EOMONTH(CloseDate,'Rent Roll'!$O$10+'Rent Roll'!$S$10),-'Rent Roll'!$F$10*'Rent Roll'!$T$10,0) -> 0 | F67: =IF(F$4=EOMONTH(CloseDate,'Rent Roll'!$O$10+'Rent Roll'!$S$10),-'Rent Roll'!$F$10*'Rent Roll'!$T$10,0) -> 0 | G67: =IF(G$4=EOMONTH(CloseDate,'Rent Roll'!$O$10+'Rent Roll'!$S$10),-'Rent Roll'!$F$10*'Rent Roll'!$T$10,0) -> 0 | H67: =IF(H$4=EOMONTH(CloseDate,'Rent Roll'!$O$10+'Rent Roll'!$S$10),-'Rent Roll'!$F$10*'Rent Roll'!$T$10,0) -> 0 | I67: =IF(I$4=EOMONTH(CloseDate,'Rent Roll'!$O$10+'Rent Roll'!$S$10),-'Rent Roll'!$F$10*'Rent Roll'!$T$10,0) -> 0 | J67: =IF(J$4=EOMONTH(CloseDate,'Rent Roll'!$O$10+'Rent Roll'!$S$10),-'Rent Roll'!$F$10*'Rent Roll'!$T$10,0) -> 0 | K67: =IF(K$4=EOMONTH(CloseDate,'Rent Roll'!$O$10+'Rent Roll'!$S$10),-'Rent Roll'!$F$10*'Rent Roll'!$T$10,0) -> 0 | ... BX67: =IF(BX$4=EOMONTH(CloseDate,'Rent Roll'!$O$10+'Rent Roll'!$S$10),-'Rent Roll'!$F$10*'Rent Roll'!$T$10,0) -> 0
B68: LC (capital) | D68: =IF(D$4=EOMONTH(CloseDate,'Rent Roll'!$O$10+'Rent Roll'!$S$10),-'Rent Roll'!$U$10*'Rent Roll'!$F$10*'Rent Roll'!$X$10,0) -> 0 | E68: =IF(E$4=EOMONTH(CloseDate,'Rent Roll'!$O$10+'Rent Roll'!$S$10),-'Rent Roll'!$U$10*'Rent Roll'!$F$10*'Rent Roll'!$X$10,0) -> 0 | F68: =IF(F$4=EOMONTH(CloseDate,'Rent Roll'!$O$10+'Rent Roll'!$S$10),-'Rent Roll'!$U$10*'Rent Roll'!$F$10*'Rent Roll'!$X$10,0) -> 0 | G68: =IF(G$4=EOMONTH(CloseDate,'Rent Roll'!$O$10+'Rent Roll'!$S$10),-'Rent Roll'!$U$10*'Rent Roll'!$F$10*'Rent Roll'!$X$10,0) -> 0 | H68: =IF(H$4=EOMONTH(CloseDate,'Rent Roll'!$O$10+'Rent Roll'!$S$10),-'Rent Roll'!$U$10*'Rent Roll'!$F$10*'Rent Roll'!$X$10,0) -> 0 | I68: =IF(I$4=EOMONTH(CloseDate,'Rent Roll'!$O$10+'Rent Roll'!$S$10),-'Rent Roll'!$U$10*'Rent Roll'!$F$10*'Rent Roll'!$X$10,0) -> 0 | J68: =IF(J$4=EOMONTH(CloseDate,'Rent Roll'!$O$10+'Rent Roll'!$S$10),-'Rent Roll'!$U$10*'Rent Roll'!$F$10*'Rent Roll'!$X$10,0) -> 0 | K68: =IF(K$4=EOMONTH(CloseDate,'Rent Roll'!$O$10+'Rent Roll'!$S$10),-'Rent Roll'!$U$10*'Rent Roll'!$F$10*'Rent Roll'!$X$10,0) -> 0 | ... BX68: =IF(BX$4=EOMONTH(CloseDate,'Rent Roll'!$O$10+'Rent Roll'!$S$10),-'Rent Roll'!$U$10*'Rent Roll'!$F$10*'Rent Roll'!$X$10,0) -> 0
A69: ='Rent Roll'!C11 -> Caldwell Consulting Group | B69: =INDEX('Rent Roll'!$F$5:$F$46,MATCH('Rent Roll Calc'!A69,'Rent Roll'!$C$5:$C$46,0)) -> 9500
B70: Occupancy Flag | D70: =IF(AND('Rent Roll'!$N$11<>"Ghost",D$4<='Rent Roll'!$L$11),1,0) -> 1 | E70: =IF(AND('Rent Roll'!$N$11<>"Ghost",E$4<='Rent Roll'!$L$11),1,0) -> 1 | F70: =IF(AND('Rent Roll'!$N$11<>"Ghost",F$4<='Rent Roll'!$L$11),1,0) -> 1 | G70: =IF(AND('Rent Roll'!$N$11<>"Ghost",G$4<='Rent Roll'!$L$11),1,0) -> 1 | H70: =IF(AND('Rent Roll'!$N$11<>"Ghost",H$4<='Rent Roll'!$L$11),1,0) -> 1 | I70: =IF(AND('Rent Roll'!$N$11<>"Ghost",I$4<='Rent Roll'!$L$11),1,0) -> 1 | J70: =IF(AND('Rent Roll'!$N$11<>"Ghost",J$4<='Rent Roll'!$L$11),1,0) -> 1 | K70: =IF(AND('Rent Roll'!$N$11<>"Ghost",K$4<='Rent Roll'!$L$11),1,0) -> 1 | ... BX70: =IF(AND('Rent Roll'!$N$11<>"Ghost",BX$4<='Rent Roll'!$L$11),1,0) -> 0
B71: In-Place Rent | D71: =IF(D70=1,'Rent Roll'!$H$11/12*(1+'Rent Roll'!$I$11)^IF(D$4<'Rent Roll'!$Y$11,0,YEAR(D$4)-YEAR('Rent Roll'!$Y$11)+1),0) -> 16229.167 | E71: =IF(E70=1,'Rent Roll'!$H$11/12*(1+'Rent Roll'!$I$11)^IF(E$4<'Rent Roll'!$Y$11,0,YEAR(E$4)-YEAR('Rent Roll'!$Y$11)+1),0) -> 16553.75 | F71: =IF(F70=1,'Rent Roll'!$H$11/12*(1+'Rent Roll'!$I$11)^IF(F$4<'Rent Roll'!$Y$11,0,YEAR(F$4)-YEAR('Rent Roll'!$Y$11)+1),0) -> 16553.75 | G71: =IF(G70=1,'Rent Roll'!$H$11/12*(1+'Rent Roll'!$I$11)^IF(G$4<'Rent Roll'!$Y$11,0,YEAR(G$4)-YEAR('Rent Roll'!$Y$11)+1),0) -> 16553.75 | H71: =IF(H70=1,'Rent Roll'!$H$11/12*(1+'Rent Roll'!$I$11)^IF(H$4<'Rent Roll'!$Y$11,0,YEAR(H$4)-YEAR('Rent Roll'!$Y$11)+1),0) -> 16553.75 | I71: =IF(I70=1,'Rent Roll'!$H$11/12*(1+'Rent Roll'!$I$11)^IF(I$4<'Rent Roll'!$Y$11,0,YEAR(I$4)-YEAR('Rent Roll'!$Y$11)+1),0) -> 16884.825 | J71: =IF(J70=1,'Rent Roll'!$H$11/12*(1+'Rent Roll'!$I$11)^IF(J$4<'Rent Roll'!$Y$11,0,YEAR(J$4)-YEAR('Rent Roll'!$Y$11)+1),0) -> 16884.825 | K71: =IF(K70=1,'Rent Roll'!$H$11/12*(1+'Rent Roll'!$I$11)^IF(K$4<'Rent Roll'!$Y$11,0,YEAR(K$4)-YEAR('Rent Roll'!$Y$11)+1),0) -> 16884.825 | ... BX71: =IF(BX70=1,'Rent Roll'!$H$11/12*(1+'Rent Roll'!$I$11)^IF(BX$4<'Rent Roll'!$Y$11,0,YEAR(BX$4)-YEAR('Rent Roll'!$Y$11)+1),0) -> 0
B72: Re-Let Flag | D72: =IF(D$4>EOMONTH(CloseDate,'Rent Roll'!$O$11+'Rent Roll'!$S$11-1),1,0) -> 0 | E72: =IF(E$4>EOMONTH(CloseDate,'Rent Roll'!$O$11+'Rent Roll'!$S$11-1),1,0) -> 0 | F72: =IF(F$4>EOMONTH(CloseDate,'Rent Roll'!$O$11+'Rent Roll'!$S$11-1),1,0) -> 0 | G72: =IF(G$4>EOMONTH(CloseDate,'Rent Roll'!$O$11+'Rent Roll'!$S$11-1),1,0) -> 0 | H72: =IF(H$4>EOMONTH(CloseDate,'Rent Roll'!$O$11+'Rent Roll'!$S$11-1),1,0) -> 0 | I72: =IF(I$4>EOMONTH(CloseDate,'Rent Roll'!$O$11+'Rent Roll'!$S$11-1),1,0) -> 0 | J72: =IF(J$4>EOMONTH(CloseDate,'Rent Roll'!$O$11+'Rent Roll'!$S$11-1),1,0) -> 0 | K72: =IF(K$4>EOMONTH(CloseDate,'Rent Roll'!$O$11+'Rent Roll'!$S$11-1),1,0) -> 0 | ... BX72: =IF(BX$4>EOMONTH(CloseDate,'Rent Roll'!$O$11+'Rent Roll'!$S$11-1),1,0) -> 1
B73: Re-Let Rent (gross) | D73: =IF(D72=1,'Rent Roll'!$F$11*'Rent Roll'!$X$11/12*D$6,0) -> 0 | E73: =IF(E72=1,'Rent Roll'!$F$11*'Rent Roll'!$X$11/12*E$6,0) -> 0 | F73: =IF(F72=1,'Rent Roll'!$F$11*'Rent Roll'!$X$11/12*F$6,0) -> 0 | G73: =IF(G72=1,'Rent Roll'!$F$11*'Rent Roll'!$X$11/12*G$6,0) -> 0 | H73: =IF(H72=1,'Rent Roll'!$F$11*'Rent Roll'!$X$11/12*H$6,0) -> 0 | I73: =IF(I72=1,'Rent Roll'!$F$11*'Rent Roll'!$X$11/12*I$6,0) -> 0 | J73: =IF(J72=1,'Rent Roll'!$F$11*'Rent Roll'!$X$11/12*J$6,0) -> 0 | K73: =IF(K72=1,'Rent Roll'!$F$11*'Rent Roll'!$X$11/12*K$6,0) -> 0 | ... BX73: =IF(BX72=1,'Rent Roll'!$F$11*'Rent Roll'!$X$11/12*BX$6,0) -> 22916.916
B74: Free Rent Adj | D74: =IF(AND(D$4>EOMONTH(CloseDate,'Rent Roll'!$O$11+'Rent Roll'!$S$11-1),D$4<=EOMONTH(CloseDate,'Rent Roll'!$O$11+'Rent Roll'!$S$11-1+'Rent Roll'!$V$11)),-D73,0) -> 0 | E74: =IF(AND(E$4>EOMONTH(CloseDate,'Rent Roll'!$O$11+'Rent Roll'!$S$11-1),E$4<=EOMONTH(CloseDate,'Rent Roll'!$O$11+'Rent Roll'!$S$11-1+'Rent Roll'!$V$11)),-E73,0) -> 0 | F74: =IF(AND(F$4>EOMONTH(CloseDate,'Rent Roll'!$O$11+'Rent Roll'!$S$11-1),F$4<=EOMONTH(CloseDate,'Rent Roll'!$O$11+'Rent Roll'!$S$11-1+'Rent Roll'!$V$11)),-F73,0) -> 0 | G74: =IF(AND(G$4>EOMONTH(CloseDate,'Rent Roll'!$O$11+'Rent Roll'!$S$11-1),G$4<=EOMONTH(CloseDate,'Rent Roll'!$O$11+'Rent Roll'!$S$11-1+'Rent Roll'!$V$11)),-G73,0) -> 0 | H74: =IF(AND(H$4>EOMONTH(CloseDate,'Rent Roll'!$O$11+'Rent Roll'!$S$11-1),H$4<=EOMONTH(CloseDate,'Rent Roll'!$O$11+'Rent Roll'!$S$11-1+'Rent Roll'!$V$11)),-H73,0) -> 0 | I74: =IF(AND(I$4>EOMONTH(CloseDate,'Rent Roll'!$O$11+'Rent Roll'!$S$11-1),I$4<=EOMONTH(CloseDate,'Rent Roll'!$O$11+'Rent Roll'!$S$11-1+'Rent Roll'!$V$11)),-I73,0) -> 0 | J74: =IF(AND(J$4>EOMONTH(CloseDate,'Rent Roll'!$O$11+'Rent Roll'!$S$11-1),J$4<=EOMONTH(CloseDate,'Rent Roll'!$O$11+'Rent Roll'!$S$11-1+'Rent Roll'!$V$11)),-J73,0) -> 0 | K74: =IF(AND(K$4>EOMONTH(CloseDate,'Rent Roll'!$O$11+'Rent Roll'!$S$11-1),K$4<=EOMONTH(CloseDate,'Rent Roll'!$O$11+'Rent Roll'!$S$11-1+'Rent Roll'!$V$11)),-K73,0) -> 0 | ... BX74: =IF(AND(BX$4>EOMONTH(CloseDate,'Rent Roll'!$O$11+'Rent Roll'!$S$11-1),BX$4<=EOMONTH(CloseDate,'Rent Roll'!$O$11+'Rent Roll'!$S$11-1+'Rent Roll'!$V$11)),-BX73,0) -> 0
B75: Net Base Rent | D75: =D71+D73+D74 -> 16229.167 | E75: =E71+E73+E74 -> 16553.75 | F75: =F71+F73+F74 -> 16553.75 | G75: =G71+G73+G74 -> 16553.75 | H75: =H71+H73+H74 -> 16553.75 | I75: =I71+I73+I74 -> 16884.825 | J75: =J71+J73+J74 -> 16884.825 | K75: =K71+K73+K74 -> 16884.825 | ... BX75: =BX71+BX73+BX74 -> 22916.916
B76: Opex Recovery (NNN) | D76: =IF(OR(D70=1,D72=1),'Rent Roll'!$F$11/BldgSF*ReimbPool/12*D$7,0) -> 8288.75 | E76: =IF(OR(E70=1,E72=1),'Rent Roll'!$F$11/BldgSF*ReimbPool/12*E$7,0) -> 8288.75 | F76: =IF(OR(F70=1,F72=1),'Rent Roll'!$F$11/BldgSF*ReimbPool/12*F$7,0) -> 8288.75 | G76: =IF(OR(G70=1,G72=1),'Rent Roll'!$F$11/BldgSF*ReimbPool/12*G$7,0) -> 8288.75 | H76: =IF(OR(H70=1,H72=1),'Rent Roll'!$F$11/BldgSF*ReimbPool/12*H$7,0) -> 8288.75 | I76: =IF(OR(I70=1,I72=1),'Rent Roll'!$F$11/BldgSF*ReimbPool/12*I$7,0) -> 8512.5462 | J76: =IF(OR(J70=1,J72=1),'Rent Roll'!$F$11/BldgSF*ReimbPool/12*J$7,0) -> 8512.5462 | K76: =IF(OR(K70=1,K72=1),'Rent Roll'!$F$11/BldgSF*ReimbPool/12*K$7,0) -> 8512.5462 | ... BX76: =IF(OR(BX70=1,BX72=1),'Rent Roll'!$F$11/BldgSF*ReimbPool/12*BX$7,0) -> 9725.4947
B77: TI (capital) | D77: =IF(D$4=EOMONTH(CloseDate,'Rent Roll'!$O$11+'Rent Roll'!$S$11),-'Rent Roll'!$F$11*'Rent Roll'!$T$11,0) -> 0 | E77: =IF(E$4=EOMONTH(CloseDate,'Rent Roll'!$O$11+'Rent Roll'!$S$11),-'Rent Roll'!$F$11*'Rent Roll'!$T$11,0) -> 0 | F77: =IF(F$4=EOMONTH(CloseDate,'Rent Roll'!$O$11+'Rent Roll'!$S$11),-'Rent Roll'!$F$11*'Rent Roll'!$T$11,0) -> 0 | G77: =IF(G$4=EOMONTH(CloseDate,'Rent Roll'!$O$11+'Rent Roll'!$S$11),-'Rent Roll'!$F$11*'Rent Roll'!$T$11,0) -> 0 | H77: =IF(H$4=EOMONTH(CloseDate,'Rent Roll'!$O$11+'Rent Roll'!$S$11),-'Rent Roll'!$F$11*'Rent Roll'!$T$11,0) -> 0 | I77: =IF(I$4=EOMONTH(CloseDate,'Rent Roll'!$O$11+'Rent Roll'!$S$11),-'Rent Roll'!$F$11*'Rent Roll'!$T$11,0) -> 0 | J77: =IF(J$4=EOMONTH(CloseDate,'Rent Roll'!$O$11+'Rent Roll'!$S$11),-'Rent Roll'!$F$11*'Rent Roll'!$T$11,0) -> 0 | K77: =IF(K$4=EOMONTH(CloseDate,'Rent Roll'!$O$11+'Rent Roll'!$S$11),-'Rent Roll'!$F$11*'Rent Roll'!$T$11,0) -> 0 | ... BX77: =IF(BX$4=EOMONTH(CloseDate,'Rent Roll'!$O$11+'Rent Roll'!$S$11),-'Rent Roll'!$F$11*'Rent Roll'!$T$11,0) -> 0
B78: LC (capital) | D78: =IF(D$4=EOMONTH(CloseDate,'Rent Roll'!$O$11+'Rent Roll'!$S$11),-'Rent Roll'!$U$11*'Rent Roll'!$F$11*'Rent Roll'!$X$11,0) -> 0 | E78: =IF(E$4=EOMONTH(CloseDate,'Rent Roll'!$O$11+'Rent Roll'!$S$11),-'Rent Roll'!$U$11*'Rent Roll'!$F$11*'Rent Roll'!$X$11,0) -> 0 | F78: =IF(F$4=EOMONTH(CloseDate,'Rent Roll'!$O$11+'Rent Roll'!$S$11),-'Rent Roll'!$U$11*'Rent Roll'!$F$11*'Rent Roll'!$X$11,0) -> 0 | G78: =IF(G$4=EOMONTH(CloseDate,'Rent Roll'!$O$11+'Rent Roll'!$S$11),-'Rent Roll'!$U$11*'Rent Roll'!$F$11*'Rent Roll'!$X$11,0) -> 0 | H78: =IF(H$4=EOMONTH(CloseDate,'Rent Roll'!$O$11+'Rent Roll'!$S$11),-'Rent Roll'!$U$11*'Rent Roll'!$F$11*'Rent Roll'!$X$11,0) -> 0 | I78: =IF(I$4=EOMONTH(CloseDate,'Rent Roll'!$O$11+'Rent Roll'!$S$11),-'Rent Roll'!$U$11*'Rent Roll'!$F$11*'Rent Roll'!$X$11,0) -> 0 | J78: =IF(J$4=EOMONTH(CloseDate,'Rent Roll'!$O$11+'Rent Roll'!$S$11),-'Rent Roll'!$U$11*'Rent Roll'!$F$11*'Rent Roll'!$X$11,0) -> 0 | K78: =IF(K$4=EOMONTH(CloseDate,'Rent Roll'!$O$11+'Rent Roll'!$S$11),-'Rent Roll'!$U$11*'Rent Roll'!$F$11*'Rent Roll'!$X$11,0) -> 0 | ... BX78: =IF(BX$4=EOMONTH(CloseDate,'Rent Roll'!$O$11+'Rent Roll'!$S$11),-'Rent Roll'!$U$11*'Rent Roll'!$F$11*'Rent Roll'!$X$11,0) -> 0
A79: ='Rent Roll'!C12 -> Queen City Accounting | B79: =INDEX('Rent Roll'!$F$5:$F$46,MATCH('Rent Roll Calc'!A79,'Rent Roll'!$C$5:$C$46,0)) -> 8500
B80: Occupancy Flag | D80: =IF(AND('Rent Roll'!$N$12<>"Ghost",D$4<='Rent Roll'!$L$12),1,0) -> 1 | E80: =IF(AND('Rent Roll'!$N$12<>"Ghost",E$4<='Rent Roll'!$L$12),1,0) -> 1 | F80: =IF(AND('Rent Roll'!$N$12<>"Ghost",F$4<='Rent Roll'!$L$12),1,0) -> 1 | G80: =IF(AND('Rent Roll'!$N$12<>"Ghost",G$4<='Rent Roll'!$L$12),1,0) -> 1 | H80: =IF(AND('Rent Roll'!$N$12<>"Ghost",H$4<='Rent Roll'!$L$12),1,0) -> 1 | I80: =IF(AND('Rent Roll'!$N$12<>"Ghost",I$4<='Rent Roll'!$L$12),1,0) -> 1 | J80: =IF(AND('Rent Roll'!$N$12<>"Ghost",J$4<='Rent Roll'!$L$12),1,0) -> 1 | K80: =IF(AND('Rent Roll'!$N$12<>"Ghost",K$4<='Rent Roll'!$L$12),1,0) -> 1 | ... BX80: =IF(AND('Rent Roll'!$N$12<>"Ghost",BX$4<='Rent Roll'!$L$12),1,0) -> 0
B81: In-Place Rent | D81: =IF(D80=1,'Rent Roll'!$H$12/12*(1+'Rent Roll'!$I$12)^IF(D$4<'Rent Roll'!$Y$12,0,YEAR(D$4)-YEAR('Rent Roll'!$Y$12)+1),0) -> 13989.583 | E81: =IF(E80=1,'Rent Roll'!$H$12/12*(1+'Rent Roll'!$I$12)^IF(E$4<'Rent Roll'!$Y$12,0,YEAR(E$4)-YEAR('Rent Roll'!$Y$12)+1),0) -> 13989.583 | F81: =IF(F80=1,'Rent Roll'!$H$12/12*(1+'Rent Roll'!$I$12)^IF(F$4<'Rent Roll'!$Y$12,0,YEAR(F$4)-YEAR('Rent Roll'!$Y$12)+1),0) -> 13989.583 | G81: =IF(G80=1,'Rent Roll'!$H$12/12*(1+'Rent Roll'!$I$12)^IF(G$4<'Rent Roll'!$Y$12,0,YEAR(G$4)-YEAR('Rent Roll'!$Y$12)+1),0) -> 13989.583 | H81: =IF(H80=1,'Rent Roll'!$H$12/12*(1+'Rent Roll'!$I$12)^IF(H$4<'Rent Roll'!$Y$12,0,YEAR(H$4)-YEAR('Rent Roll'!$Y$12)+1),0) -> 13989.583 | I81: =IF(I80=1,'Rent Roll'!$H$12/12*(1+'Rent Roll'!$I$12)^IF(I$4<'Rent Roll'!$Y$12,0,YEAR(I$4)-YEAR('Rent Roll'!$Y$12)+1),0) -> 13989.583 | J81: =IF(J80=1,'Rent Roll'!$H$12/12*(1+'Rent Roll'!$I$12)^IF(J$4<'Rent Roll'!$Y$12,0,YEAR(J$4)-YEAR('Rent Roll'!$Y$12)+1),0) -> 14339.323 | K81: =IF(K80=1,'Rent Roll'!$H$12/12*(1+'Rent Roll'!$I$12)^IF(K$4<'Rent Roll'!$Y$12,0,YEAR(K$4)-YEAR('Rent Roll'!$Y$12)+1),0) -> 14339.323 | ... BX81: =IF(BX80=1,'Rent Roll'!$H$12/12*(1+'Rent Roll'!$I$12)^IF(BX$4<'Rent Roll'!$Y$12,0,YEAR(BX$4)-YEAR('Rent Roll'!$Y$12)+1),0) -> 0
B82: Re-Let Flag | D82: =IF(D$4>EOMONTH(CloseDate,'Rent Roll'!$O$12+'Rent Roll'!$S$12-1),1,0) -> 0 | E82: =IF(E$4>EOMONTH(CloseDate,'Rent Roll'!$O$12+'Rent Roll'!$S$12-1),1,0) -> 0 | F82: =IF(F$4>EOMONTH(CloseDate,'Rent Roll'!$O$12+'Rent Roll'!$S$12-1),1,0) -> 0 | G82: =IF(G$4>EOMONTH(CloseDate,'Rent Roll'!$O$12+'Rent Roll'!$S$12-1),1,0) -> 0 | H82: =IF(H$4>EOMONTH(CloseDate,'Rent Roll'!$O$12+'Rent Roll'!$S$12-1),1,0) -> 0 | I82: =IF(I$4>EOMONTH(CloseDate,'Rent Roll'!$O$12+'Rent Roll'!$S$12-1),1,0) -> 0 | J82: =IF(J$4>EOMONTH(CloseDate,'Rent Roll'!$O$12+'Rent Roll'!$S$12-1),1,0) -> 0 | K82: =IF(K$4>EOMONTH(CloseDate,'Rent Roll'!$O$12+'Rent Roll'!$S$12-1),1,0) -> 0 | ... BX82: =IF(BX$4>EOMONTH(CloseDate,'Rent Roll'!$O$12+'Rent Roll'!$S$12-1),1,0) -> 1
B83: Re-Let Rent (gross) | D83: =IF(D82=1,'Rent Roll'!$F$12*'Rent Roll'!$X$12/12*D$6,0) -> 0 | E83: =IF(E82=1,'Rent Roll'!$F$12*'Rent Roll'!$X$12/12*E$6,0) -> 0 | F83: =IF(F82=1,'Rent Roll'!$F$12*'Rent Roll'!$X$12/12*F$6,0) -> 0 | G83: =IF(G82=1,'Rent Roll'!$F$12*'Rent Roll'!$X$12/12*G$6,0) -> 0 | H83: =IF(H82=1,'Rent Roll'!$F$12*'Rent Roll'!$X$12/12*H$6,0) -> 0 | I83: =IF(I82=1,'Rent Roll'!$F$12*'Rent Roll'!$X$12/12*I$6,0) -> 0 | J83: =IF(J82=1,'Rent Roll'!$F$12*'Rent Roll'!$X$12/12*J$6,0) -> 0 | K83: =IF(K82=1,'Rent Roll'!$F$12*'Rent Roll'!$X$12/12*K$6,0) -> 0 | ... BX83: =IF(BX82=1,'Rent Roll'!$F$12*'Rent Roll'!$X$12/12*BX$6,0) -> 20504.609
B84: Free Rent Adj | D84: =IF(AND(D$4>EOMONTH(CloseDate,'Rent Roll'!$O$12+'Rent Roll'!$S$12-1),D$4<=EOMONTH(CloseDate,'Rent Roll'!$O$12+'Rent Roll'!$S$12-1+'Rent Roll'!$V$12)),-D83,0) -> 0 | E84: =IF(AND(E$4>EOMONTH(CloseDate,'Rent Roll'!$O$12+'Rent Roll'!$S$12-1),E$4<=EOMONTH(CloseDate,'Rent Roll'!$O$12+'Rent Roll'!$S$12-1+'Rent Roll'!$V$12)),-E83,0) -> 0 | F84: =IF(AND(F$4>EOMONTH(CloseDate,'Rent Roll'!$O$12+'Rent Roll'!$S$12-1),F$4<=EOMONTH(CloseDate,'Rent Roll'!$O$12+'Rent Roll'!$S$12-1+'Rent Roll'!$V$12)),-F83,0) -> 0 | G84: =IF(AND(G$4>EOMONTH(CloseDate,'Rent Roll'!$O$12+'Rent Roll'!$S$12-1),G$4<=EOMONTH(CloseDate,'Rent Roll'!$O$12+'Rent Roll'!$S$12-1+'Rent Roll'!$V$12)),-G83,0) -> 0 | H84: =IF(AND(H$4>EOMONTH(CloseDate,'Rent Roll'!$O$12+'Rent Roll'!$S$12-1),H$4<=EOMONTH(CloseDate,'Rent Roll'!$O$12+'Rent Roll'!$S$12-1+'Rent Roll'!$V$12)),-H83,0) -> 0 | I84: =IF(AND(I$4>EOMONTH(CloseDate,'Rent Roll'!$O$12+'Rent Roll'!$S$12-1),I$4<=EOMONTH(CloseDate,'Rent Roll'!$O$12+'Rent Roll'!$S$12-1+'Rent Roll'!$V$12)),-I83,0) -> 0 | J84: =IF(AND(J$4>EOMONTH(CloseDate,'Rent Roll'!$O$12+'Rent Roll'!$S$12-1),J$4<=EOMONTH(CloseDate,'Rent Roll'!$O$12+'Rent Roll'!$S$12-1+'Rent Roll'!$V$12)),-J83,0) -> 0 | K84: =IF(AND(K$4>EOMONTH(CloseDate,'Rent Roll'!$O$12+'Rent Roll'!$S$12-1),K$4<=EOMONTH(CloseDate,'Rent Roll'!$O$12+'Rent Roll'!$S$12-1+'Rent Roll'!$V$12)),-K83,0) -> 0 | ... BX84: =IF(AND(BX$4>EOMONTH(CloseDate,'Rent Roll'!$O$12+'Rent Roll'!$S$12-1),BX$4<=EOMONTH(CloseDate,'Rent Roll'!$O$12+'Rent Roll'!$S$12-1+'Rent Roll'!$V$12)),-BX83,0) -> 0
B85: Net Base Rent | D85: =D81+D83+D84 -> 13989.583 | E85: =E81+E83+E84 -> 13989.583 | F85: =F81+F83+F84 -> 13989.583 | G85: =G81+G83+G84 -> 13989.583 | H85: =H81+H83+H84 -> 13989.583 | I85: =I81+I83+I84 -> 13989.583 | J85: =J81+J83+J84 -> 14339.323 | K85: =K81+K83+K84 -> 14339.323 | ... BX85: =BX81+BX83+BX84 -> 20504.609
B86: Opex Recovery (NNN) | D86: =IF(OR(D80=1,D82=1),'Rent Roll'!$F$12/BldgSF*ReimbPool/12*D$7,0) -> 7416.25 | E86: =IF(OR(E80=1,E82=1),'Rent Roll'!$F$12/BldgSF*ReimbPool/12*E$7,0) -> 7416.25 | F86: =IF(OR(F80=1,F82=1),'Rent Roll'!$F$12/BldgSF*ReimbPool/12*F$7,0) -> 7416.25 | G86: =IF(OR(G80=1,G82=1),'Rent Roll'!$F$12/BldgSF*ReimbPool/12*G$7,0) -> 7416.25 | H86: =IF(OR(H80=1,H82=1),'Rent Roll'!$F$12/BldgSF*ReimbPool/12*H$7,0) -> 7416.25 | I86: =IF(OR(I80=1,I82=1),'Rent Roll'!$F$12/BldgSF*ReimbPool/12*I$7,0) -> 7616.4887 | J86: =IF(OR(J80=1,J82=1),'Rent Roll'!$F$12/BldgSF*ReimbPool/12*J$7,0) -> 7616.4887 | K86: =IF(OR(K80=1,K82=1),'Rent Roll'!$F$12/BldgSF*ReimbPool/12*K$7,0) -> 7616.4887 | ... BX86: =IF(OR(BX80=1,BX82=1),'Rent Roll'!$F$12/BldgSF*ReimbPool/12*BX$7,0) -> 8701.7584
B87: TI (capital) | D87: =IF(D$4=EOMONTH(CloseDate,'Rent Roll'!$O$12+'Rent Roll'!$S$12),-'Rent Roll'!$F$12*'Rent Roll'!$T$12,0) -> 0 | E87: =IF(E$4=EOMONTH(CloseDate,'Rent Roll'!$O$12+'Rent Roll'!$S$12),-'Rent Roll'!$F$12*'Rent Roll'!$T$12,0) -> 0 | F87: =IF(F$4=EOMONTH(CloseDate,'Rent Roll'!$O$12+'Rent Roll'!$S$12),-'Rent Roll'!$F$12*'Rent Roll'!$T$12,0) -> 0 | G87: =IF(G$4=EOMONTH(CloseDate,'Rent Roll'!$O$12+'Rent Roll'!$S$12),-'Rent Roll'!$F$12*'Rent Roll'!$T$12,0) -> 0 | H87: =IF(H$4=EOMONTH(CloseDate,'Rent Roll'!$O$12+'Rent Roll'!$S$12),-'Rent Roll'!$F$12*'Rent Roll'!$T$12,0) -> 0 | I87: =IF(I$4=EOMONTH(CloseDate,'Rent Roll'!$O$12+'Rent Roll'!$S$12),-'Rent Roll'!$F$12*'Rent Roll'!$T$12,0) -> 0 | J87: =IF(J$4=EOMONTH(CloseDate,'Rent Roll'!$O$12+'Rent Roll'!$S$12),-'Rent Roll'!$F$12*'Rent Roll'!$T$12,0) -> 0 | K87: =IF(K$4=EOMONTH(CloseDate,'Rent Roll'!$O$12+'Rent Roll'!$S$12),-'Rent Roll'!$F$12*'Rent Roll'!$T$12,0) -> 0 | ... BX87: =IF(BX$4=EOMONTH(CloseDate,'Rent Roll'!$O$12+'Rent Roll'!$S$12),-'Rent Roll'!$F$12*'Rent Roll'!$T$12,0) -> 0
B88: LC (capital) | D88: =IF(D$4=EOMONTH(CloseDate,'Rent Roll'!$O$12+'Rent Roll'!$S$12),-'Rent Roll'!$U$12*'Rent Roll'!$F$12*'Rent Roll'!$X$12,0) -> 0 | E88: =IF(E$4=EOMONTH(CloseDate,'Rent Roll'!$O$12+'Rent Roll'!$S$12),-'Rent Roll'!$U$12*'Rent Roll'!$F$12*'Rent Roll'!$X$12,0) -> 0 | F88: =IF(F$4=EOMONTH(CloseDate,'Rent Roll'!$O$12+'Rent Roll'!$S$12),-'Rent Roll'!$U$12*'Rent Roll'!$F$12*'Rent Roll'!$X$12,0) -> 0 | G88: =IF(G$4=EOMONTH(CloseDate,'Rent Roll'!$O$12+'Rent Roll'!$S$12),-'Rent Roll'!$U$12*'Rent Roll'!$F$12*'Rent Roll'!$X$12,0) -> 0 | H88: =IF(H$4=EOMONTH(CloseDate,'Rent Roll'!$O$12+'Rent Roll'!$S$12),-'Rent Roll'!$U$12*'Rent Roll'!$F$12*'Rent Roll'!$X$12,0) -> 0 | I88: =IF(I$4=EOMONTH(CloseDate,'Rent Roll'!$O$12+'Rent Roll'!$S$12),-'Rent Roll'!$U$12*'Rent Roll'!$F$12*'Rent Roll'!$X$12,0) -> 0 | J88: =IF(J$4=EOMONTH(CloseDate,'Rent Roll'!$O$12+'Rent Roll'!$S$12),-'Rent Roll'!$U$12*'Rent Roll'!$F$12*'Rent Roll'!$X$12,0) -> 0 | K88: =IF(K$4=EOMONTH(CloseDate,'Rent Roll'!$O$12+'Rent Roll'!$S$12),-'Rent Roll'!$U$12*'Rent Roll'!$F$12*'Rent Roll'!$X$12,0) -> 0 | ... BX88: =IF(BX$4=EOMONTH(CloseDate,'Rent Roll'!$O$12+'Rent Roll'!$S$12),-'Rent Roll'!$U$12*'Rent Roll'!$F$12*'Rent Roll'!$X$12,0) -> 0
A89: ='Rent Roll'!C13 -> Monarch Marketing Group | B89: =INDEX('Rent Roll'!$F$5:$F$46,MATCH('Rent Roll Calc'!A89,'Rent Roll'!$C$5:$C$46,0)) -> 7800
B90: Occupancy Flag | D90: =IF(AND('Rent Roll'!$N$13<>"Ghost",D$4<='Rent Roll'!$L$13),1,0) -> 1 | E90: =IF(AND('Rent Roll'!$N$13<>"Ghost",E$4<='Rent Roll'!$L$13),1,0) -> 1 | F90: =IF(AND('Rent Roll'!$N$13<>"Ghost",F$4<='Rent Roll'!$L$13),1,0) -> 1 | G90: =IF(AND('Rent Roll'!$N$13<>"Ghost",G$4<='Rent Roll'!$L$13),1,0) -> 1 | H90: =IF(AND('Rent Roll'!$N$13<>"Ghost",H$4<='Rent Roll'!$L$13),1,0) -> 1 | I90: =IF(AND('Rent Roll'!$N$13<>"Ghost",I$4<='Rent Roll'!$L$13),1,0) -> 1 | J90: =IF(AND('Rent Roll'!$N$13<>"Ghost",J$4<='Rent Roll'!$L$13),1,0) -> 1 | K90: =IF(AND('Rent Roll'!$N$13<>"Ghost",K$4<='Rent Roll'!$L$13),1,0) -> 1 | ... BX90: =IF(AND('Rent Roll'!$N$13<>"Ghost",BX$4<='Rent Roll'!$L$13),1,0) -> 0
B91: In-Place Rent | D91: =IF(D90=1,'Rent Roll'!$H$13/12*(1+'Rent Roll'!$I$13)^IF(D$4<'Rent Roll'!$Y$13,0,YEAR(D$4)-YEAR('Rent Roll'!$Y$13)+1),0) -> 13650 | E91: =IF(E90=1,'Rent Roll'!$H$13/12*(1+'Rent Roll'!$I$13)^IF(E$4<'Rent Roll'!$Y$13,0,YEAR(E$4)-YEAR('Rent Roll'!$Y$13)+1),0) -> 13650 | F91: =IF(F90=1,'Rent Roll'!$H$13/12*(1+'Rent Roll'!$I$13)^IF(F$4<'Rent Roll'!$Y$13,0,YEAR(F$4)-YEAR('Rent Roll'!$Y$13)+1),0) -> 13650 | G91: =IF(G90=1,'Rent Roll'!$H$13/12*(1+'Rent Roll'!$I$13)^IF(G$4<'Rent Roll'!$Y$13,0,YEAR(G$4)-YEAR('Rent Roll'!$Y$13)+1),0) -> 13650 | H91: =IF(H90=1,'Rent Roll'!$H$13/12*(1+'Rent Roll'!$I$13)^IF(H$4<'Rent Roll'!$Y$13,0,YEAR(H$4)-YEAR('Rent Roll'!$Y$13)+1),0) -> 13650 | I91: =IF(I90=1,'Rent Roll'!$H$13/12*(1+'Rent Roll'!$I$13)^IF(I$4<'Rent Roll'!$Y$13,0,YEAR(I$4)-YEAR('Rent Roll'!$Y$13)+1),0) -> 13650 | J91: =IF(J90=1,'Rent Roll'!$H$13/12*(1+'Rent Roll'!$I$13)^IF(J$4<'Rent Roll'!$Y$13,0,YEAR(J$4)-YEAR('Rent Roll'!$Y$13)+1),0) -> 13650 | K91: =IF(K90=1,'Rent Roll'!$H$13/12*(1+'Rent Roll'!$I$13)^IF(K$4<'Rent Roll'!$Y$13,0,YEAR(K$4)-YEAR('Rent Roll'!$Y$13)+1),0) -> 13650 | ... BX91: =IF(BX90=1,'Rent Roll'!$H$13/12*(1+'Rent Roll'!$I$13)^IF(BX$4<'Rent Roll'!$Y$13,0,YEAR(BX$4)-YEAR('Rent Roll'!$Y$13)+1),0) -> 0
B92: Re-Let Flag | D92: =IF(D$4>EOMONTH(CloseDate,'Rent Roll'!$O$13+'Rent Roll'!$S$13-1),1,0) -> 0 | E92: =IF(E$4>EOMONTH(CloseDate,'Rent Roll'!$O$13+'Rent Roll'!$S$13-1),1,0) -> 0 | F92: =IF(F$4>EOMONTH(CloseDate,'Rent Roll'!$O$13+'Rent Roll'!$S$13-1),1,0) -> 0 | G92: =IF(G$4>EOMONTH(CloseDate,'Rent Roll'!$O$13+'Rent Roll'!$S$13-1),1,0) -> 0 | H92: =IF(H$4>EOMONTH(CloseDate,'Rent Roll'!$O$13+'Rent Roll'!$S$13-1),1,0) -> 0 | I92: =IF(I$4>EOMONTH(CloseDate,'Rent Roll'!$O$13+'Rent Roll'!$S$13-1),1,0) -> 0 | J92: =IF(J$4>EOMONTH(CloseDate,'Rent Roll'!$O$13+'Rent Roll'!$S$13-1),1,0) -> 0 | K92: =IF(K$4>EOMONTH(CloseDate,'Rent Roll'!$O$13+'Rent Roll'!$S$13-1),1,0) -> 0 | ... BX92: =IF(BX$4>EOMONTH(CloseDate,'Rent Roll'!$O$13+'Rent Roll'!$S$13-1),1,0) -> 1
B93: Re-Let Rent (gross) | D93: =IF(D92=1,'Rent Roll'!$F$13*'Rent Roll'!$X$13/12*D$6,0) -> 0 | E93: =IF(E92=1,'Rent Roll'!$F$13*'Rent Roll'!$X$13/12*E$6,0) -> 0 | F93: =IF(F92=1,'Rent Roll'!$F$13*'Rent Roll'!$X$13/12*F$6,0) -> 0 | G93: =IF(G92=1,'Rent Roll'!$F$13*'Rent Roll'!$X$13/12*G$6,0) -> 0 | H93: =IF(H92=1,'Rent Roll'!$F$13*'Rent Roll'!$X$13/12*H$6,0) -> 0 | I93: =IF(I92=1,'Rent Roll'!$F$13*'Rent Roll'!$X$13/12*I$6,0) -> 0 | J93: =IF(J92=1,'Rent Roll'!$F$13*'Rent Roll'!$X$13/12*J$6,0) -> 0 | K93: =IF(K92=1,'Rent Roll'!$F$13*'Rent Roll'!$X$13/12*K$6,0) -> 0 | ... BX93: =IF(BX92=1,'Rent Roll'!$F$13*'Rent Roll'!$X$13/12*BX$6,0) -> 18815.994
B94: Free Rent Adj | D94: =IF(AND(D$4>EOMONTH(CloseDate,'Rent Roll'!$O$13+'Rent Roll'!$S$13-1),D$4<=EOMONTH(CloseDate,'Rent Roll'!$O$13+'Rent Roll'!$S$13-1+'Rent Roll'!$V$13)),-D93,0) -> 0 | E94: =IF(AND(E$4>EOMONTH(CloseDate,'Rent Roll'!$O$13+'Rent Roll'!$S$13-1),E$4<=EOMONTH(CloseDate,'Rent Roll'!$O$13+'Rent Roll'!$S$13-1+'Rent Roll'!$V$13)),-E93,0) -> 0 | F94: =IF(AND(F$4>EOMONTH(CloseDate,'Rent Roll'!$O$13+'Rent Roll'!$S$13-1),F$4<=EOMONTH(CloseDate,'Rent Roll'!$O$13+'Rent Roll'!$S$13-1+'Rent Roll'!$V$13)),-F93,0) -> 0 | G94: =IF(AND(G$4>EOMONTH(CloseDate,'Rent Roll'!$O$13+'Rent Roll'!$S$13-1),G$4<=EOMONTH(CloseDate,'Rent Roll'!$O$13+'Rent Roll'!$S$13-1+'Rent Roll'!$V$13)),-G93,0) -> 0 | H94: =IF(AND(H$4>EOMONTH(CloseDate,'Rent Roll'!$O$13+'Rent Roll'!$S$13-1),H$4<=EOMONTH(CloseDate,'Rent Roll'!$O$13+'Rent Roll'!$S$13-1+'Rent Roll'!$V$13)),-H93,0) -> 0 | I94: =IF(AND(I$4>EOMONTH(CloseDate,'Rent Roll'!$O$13+'Rent Roll'!$S$13-1),I$4<=EOMONTH(CloseDate,'Rent Roll'!$O$13+'Rent Roll'!$S$13-1+'Rent Roll'!$V$13)),-I93,0) -> 0 | J94: =IF(AND(J$4>EOMONTH(CloseDate,'Rent Roll'!$O$13+'Rent Roll'!$S$13-1),J$4<=EOMONTH(CloseDate,'Rent Roll'!$O$13+'Rent Roll'!$S$13-1+'Rent Roll'!$V$13)),-J93,0) -> 0 | K94: =IF(AND(K$4>EOMONTH(CloseDate,'Rent Roll'!$O$13+'Rent Roll'!$S$13-1),K$4<=EOMONTH(CloseDate,'Rent Roll'!$O$13+'Rent Roll'!$S$13-1+'Rent Roll'!$V$13)),-K93,0) -> 0 | ... BX94: =IF(AND(BX$4>EOMONTH(CloseDate,'Rent Roll'!$O$13+'Rent Roll'!$S$13-1),BX$4<=EOMONTH(CloseDate,'Rent Roll'!$O$13+'Rent Roll'!$S$13-1+'Rent Roll'!$V$13)),-BX93,0) -> 0
B95: Net Base Rent | D95: =D91+D93+D94 -> 13650 | E95: =E91+E93+E94 -> 13650 | F95: =F91+F93+F94 -> 13650 | G95: =G91+G93+G94 -> 13650 | H95: =H91+H93+H94 -> 13650 | I95: =I91+I93+I94 -> 13650 | J95: =J91+J93+J94 -> 13650 | K95: =K91+K93+K94 -> 13650 | ... BX95: =BX91+BX93+BX94 -> 18815.994
B96: Opex Recovery (NNN) | D96: =IF(OR(D90=1,D92=1),'Rent Roll'!$F$13/BldgSF*ReimbPool/12*D$7,0) -> 6805.5 | E96: =IF(OR(E90=1,E92=1),'Rent Roll'!$F$13/BldgSF*ReimbPool/12*E$7,0) -> 6805.5 | F96: =IF(OR(F90=1,F92=1),'Rent Roll'!$F$13/BldgSF*ReimbPool/12*F$7,0) -> 6805.5 | G96: =IF(OR(G90=1,G92=1),'Rent Roll'!$F$13/BldgSF*ReimbPool/12*G$7,0) -> 6805.5 | H96: =IF(OR(H90=1,H92=1),'Rent Roll'!$F$13/BldgSF*ReimbPool/12*H$7,0) -> 6805.5 | I96: =IF(OR(I90=1,I92=1),'Rent Roll'!$F$13/BldgSF*ReimbPool/12*I$7,0) -> 6989.2485 | J96: =IF(OR(J90=1,J92=1),'Rent Roll'!$F$13/BldgSF*ReimbPool/12*J$7,0) -> 6989.2485 | K96: =IF(OR(K90=1,K92=1),'Rent Roll'!$F$13/BldgSF*ReimbPool/12*K$7,0) -> 6989.2485 | ... BX96: =IF(OR(BX90=1,BX92=1),'Rent Roll'!$F$13/BldgSF*ReimbPool/12*BX$7,0) -> 7985.143
B97: TI (capital) | D97: =IF(D$4=EOMONTH(CloseDate,'Rent Roll'!$O$13+'Rent Roll'!$S$13),-'Rent Roll'!$F$13*'Rent Roll'!$T$13,0) -> 0 | E97: =IF(E$4=EOMONTH(CloseDate,'Rent Roll'!$O$13+'Rent Roll'!$S$13),-'Rent Roll'!$F$13*'Rent Roll'!$T$13,0) -> 0 | F97: =IF(F$4=EOMONTH(CloseDate,'Rent Roll'!$O$13+'Rent Roll'!$S$13),-'Rent Roll'!$F$13*'Rent Roll'!$T$13,0) -> 0 | G97: =IF(G$4=EOMONTH(CloseDate,'Rent Roll'!$O$13+'Rent Roll'!$S$13),-'Rent Roll'!$F$13*'Rent Roll'!$T$13,0) -> 0 | H97: =IF(H$4=EOMONTH(CloseDate,'Rent Roll'!$O$13+'Rent Roll'!$S$13),-'Rent Roll'!$F$13*'Rent Roll'!$T$13,0) -> 0 | I97: =IF(I$4=EOMONTH(CloseDate,'Rent Roll'!$O$13+'Rent Roll'!$S$13),-'Rent Roll'!$F$13*'Rent Roll'!$T$13,0) -> 0 | J97: =IF(J$4=EOMONTH(CloseDate,'Rent Roll'!$O$13+'Rent Roll'!$S$13),-'Rent Roll'!$F$13*'Rent Roll'!$T$13,0) -> 0 | K97: =IF(K$4=EOMONTH(CloseDate,'Rent Roll'!$O$13+'Rent Roll'!$S$13),-'Rent Roll'!$F$13*'Rent Roll'!$T$13,0) -> 0 | ... BX97: =IF(BX$4=EOMONTH(CloseDate,'Rent Roll'!$O$13+'Rent Roll'!$S$13),-'Rent Roll'!$F$13*'Rent Roll'!$T$13,0) -> 0
B98: LC (capital) | D98: =IF(D$4=EOMONTH(CloseDate,'Rent Roll'!$O$13+'Rent Roll'!$S$13),-'Rent Roll'!$U$13*'Rent Roll'!$F$13*'Rent Roll'!$X$13,0) -> 0 | E98: =IF(E$4=EOMONTH(CloseDate,'Rent Roll'!$O$13+'Rent Roll'!$S$13),-'Rent Roll'!$U$13*'Rent Roll'!$F$13*'Rent Roll'!$X$13,0) -> 0 | F98: =IF(F$4=EOMONTH(CloseDate,'Rent Roll'!$O$13+'Rent Roll'!$S$13),-'Rent Roll'!$U$13*'Rent Roll'!$F$13*'Rent Roll'!$X$13,0) -> 0 | G98: =IF(G$4=EOMONTH(CloseDate,'Rent Roll'!$O$13+'Rent Roll'!$S$13),-'Rent Roll'!$U$13*'Rent Roll'!$F$13*'Rent Roll'!$X$13,0) -> 0 | H98: =IF(H$4=EOMONTH(CloseDate,'Rent Roll'!$O$13+'Rent Roll'!$S$13),-'Rent Roll'!$U$13*'Rent Roll'!$F$13*'Rent Roll'!$X$13,0) -> 0 | I98: =IF(I$4=EOMONTH(CloseDate,'Rent Roll'!$O$13+'Rent Roll'!$S$13),-'Rent Roll'!$U$13*'Rent Roll'!$F$13*'Rent Roll'!$X$13,0) -> 0 | J98: =IF(J$4=EOMONTH(CloseDate,'Rent Roll'!$O$13+'Rent Roll'!$S$13),-'Rent Roll'!$U$13*'Rent Roll'!$F$13*'Rent Roll'!$X$13,0) -> 0 | K98: =IF(K$4=EOMONTH(CloseDate,'Rent Roll'!$O$13+'Rent Roll'!$S$13),-'Rent Roll'!$U$13*'Rent Roll'!$F$13*'Rent Roll'!$X$13,0) -> 0 | ... BX98: =IF(BX$4=EOMONTH(CloseDate,'Rent Roll'!$O$13+'Rent Roll'!$S$13),-'Rent Roll'!$U$13*'Rent Roll'!$F$13*'Rent Roll'!$X$13,0) -> 0
A99: ='Rent Roll'!C14 -> Davidson & Reed Architects | B99: =INDEX('Rent Roll'!$F$5:$F$46,MATCH('Rent Roll Calc'!A99,'Rent Roll'!$C$5:$C$46,0)) -> 7200
B100: Occupancy Flag | D100: =IF(AND('Rent Roll'!$N$14<>"Ghost",D$4<='Rent Roll'!$L$14),1,0) -> 1 | E100: =IF(AND('Rent Roll'!$N$14<>"Ghost",E$4<='Rent Roll'!$L$14),1,0) -> 1 | F100: =IF(AND('Rent Roll'!$N$14<>"Ghost",F$4<='Rent Roll'!$L$14),1,0) -> 1 | G100: =IF(AND('Rent Roll'!$N$14<>"Ghost",G$4<='Rent Roll'!$L$14),1,0) -> 1 | H100: =IF(AND('Rent Roll'!$N$14<>"Ghost",H$4<='Rent Roll'!$L$14),1,0) -> 1 | I100: =IF(AND('Rent Roll'!$N$14<>"Ghost",I$4<='Rent Roll'!$L$14),1,0) -> 1 | J100: =IF(AND('Rent Roll'!$N$14<>"Ghost",J$4<='Rent Roll'!$L$14),1,0) -> 1 | K100: =IF(AND('Rent Roll'!$N$14<>"Ghost",K$4<='Rent Roll'!$L$14),1,0) -> 1 | ... BX100: =IF(AND('Rent Roll'!$N$14<>"Ghost",BX$4<='Rent Roll'!$L$14),1,0) -> 0
B101: In-Place Rent | D101: =IF(D100=1,'Rent Roll'!$H$14/12*(1+'Rent Roll'!$I$14)^IF(D$4<'Rent Roll'!$Y$14,0,YEAR(D$4)-YEAR('Rent Roll'!$Y$14)+1),0) -> 12450 | E101: =IF(E100=1,'Rent Roll'!$H$14/12*(1+'Rent Roll'!$I$14)^IF(E$4<'Rent Roll'!$Y$14,0,YEAR(E$4)-YEAR('Rent Roll'!$Y$14)+1),0) -> 12450 | F101: =IF(F100=1,'Rent Roll'!$H$14/12*(1+'Rent Roll'!$I$14)^IF(F$4<'Rent Roll'!$Y$14,0,YEAR(F$4)-YEAR('Rent Roll'!$Y$14)+1),0) -> 12450 | G101: =IF(G100=1,'Rent Roll'!$H$14/12*(1+'Rent Roll'!$I$14)^IF(G$4<'Rent Roll'!$Y$14,0,YEAR(G$4)-YEAR('Rent Roll'!$Y$14)+1),0) -> 12450 | H101: =IF(H100=1,'Rent Roll'!$H$14/12*(1+'Rent Roll'!$I$14)^IF(H$4<'Rent Roll'!$Y$14,0,YEAR(H$4)-YEAR('Rent Roll'!$Y$14)+1),0) -> 12699 | I101: =IF(I100=1,'Rent Roll'!$H$14/12*(1+'Rent Roll'!$I$14)^IF(I$4<'Rent Roll'!$Y$14,0,YEAR(I$4)-YEAR('Rent Roll'!$Y$14)+1),0) -> 12952.98 | J101: =IF(J100=1,'Rent Roll'!$H$14/12*(1+'Rent Roll'!$I$14)^IF(J$4<'Rent Roll'!$Y$14,0,YEAR(J$4)-YEAR('Rent Roll'!$Y$14)+1),0) -> 12952.98 | K101: =IF(K100=1,'Rent Roll'!$H$14/12*(1+'Rent Roll'!$I$14)^IF(K$4<'Rent Roll'!$Y$14,0,YEAR(K$4)-YEAR('Rent Roll'!$Y$14)+1),0) -> 12952.98 | ... BX101: =IF(BX100=1,'Rent Roll'!$H$14/12*(1+'Rent Roll'!$I$14)^IF(BX$4<'Rent Roll'!$Y$14,0,YEAR(BX$4)-YEAR('Rent Roll'!$Y$14)+1),0) -> 0
B102: Re-Let Flag | D102: =IF(D$4>EOMONTH(CloseDate,'Rent Roll'!$O$14+'Rent Roll'!$S$14-1),1,0) -> 0 | E102: =IF(E$4>EOMONTH(CloseDate,'Rent Roll'!$O$14+'Rent Roll'!$S$14-1),1,0) -> 0 | F102: =IF(F$4>EOMONTH(CloseDate,'Rent Roll'!$O$14+'Rent Roll'!$S$14-1),1,0) -> 0 | G102: =IF(G$4>EOMONTH(CloseDate,'Rent Roll'!$O$14+'Rent Roll'!$S$14-1),1,0) -> 0 | H102: =IF(H$4>EOMONTH(CloseDate,'Rent Roll'!$O$14+'Rent Roll'!$S$14-1),1,0) -> 0 | I102: =IF(I$4>EOMONTH(CloseDate,'Rent Roll'!$O$14+'Rent Roll'!$S$14-1),1,0) -> 0 | J102: =IF(J$4>EOMONTH(CloseDate,'Rent Roll'!$O$14+'Rent Roll'!$S$14-1),1,0) -> 0 | K102: =IF(K$4>EOMONTH(CloseDate,'Rent Roll'!$O$14+'Rent Roll'!$S$14-1),1,0) -> 0 | ... BX102: =IF(BX$4>EOMONTH(CloseDate,'Rent Roll'!$O$14+'Rent Roll'!$S$14-1),1,0) -> 1
...

Sheet IC Summary
A1: INVESTMENT COMMITTEE SUMMARY
A3: DEAL OVERVIEW
A4: Property Name | D4: =Assumptions!A1 -> SouthPark Centre
A5: Address | D5: =Assumptions!A2 -> 4800 Sharon Road, Charlotte, NC 2821
A6: Submarket | D6: ='Rental Comp Analysis'!C3 -> SouthPark
A7: Total SF | D7: =BldgSF -> 280000
A8: Stories | D8: 8 | E8: from OM
A9: Year Built | D9: 2014 | E9: from OM
A10: Purchase Price | D10: =PurchasePrice -> 50000000
A11: Price / SF | D11: =D10/D7 -> 178.57143
A12: Going-In Cap Rate (Reconciled) | D12: ='Sales Comp Analysis'!I29 -> 0.05743247
A13: Physical Occupancy (Corrected) | D13: ='Property Cash Flow'!L6 -> 0.77357143
A14: Number of Tenants (Actual) | D14: =COUNTIF('Rent Roll'!N5:N32,"Occupied") -> 18
A15: WALT (Years) | D15: =('Rent Roll'!L34-CloseDate)/365.4 -> 1.8160562
A16: Largest Tenant | D16: ='Rent Roll'!C5 -> Meridian Financial Group
A17: Near-Term Rollover Exposure (SF) | D17: ='Rent Roll'!F5 -> 76000
A19: MARKET CONTEXT
A20: Submarket Vacancy | D20: ='SouthPark Submarket'!B11 -> 14.8%
A21: Class B+ Asking Rent (NNN) | D21: ='SouthPark Submarket'!B20 -> $24.00 - $27.00/SF
A22: 12-Month Rent Growth | D22: =+'SouthPark Submarket'!B40 -> 2.8%
A23: TTM Net Absorption | D23: =+'SouthPark Submarket'!B27 -> 185,000 SF
A24: Supply Pipeline | D24: ='SouthPark Submarket'!B33 -> 320,000 SF
A26: TENANCY SUMMARY
A27: WALT | D27: =D15 -> 1.8160562
A28: Top 5 Tenant Concentration (% of SF) | D28: =SUMIFS('Rent Roll'!$F$5:$F$32,'Rent Roll'!$A$5:$A$32,"<=5")/D7 -> 0.47678571
A29: Near-Term Rollover (SF / % of Bldg) | D29: =D17 -> 76000
A30: Avg Mark-to-Market Spread | D30: ='Rent Roll'!X34-'Rent Roll'!G34 -> 8.773008 | E30: incl. vacancy
A31: Weighted Avg In-Place Rent | D31: ='Rent Roll'!G34 -> 15.903036
A33: FINANCIAL SUMMARY
A34: Broker's Stated NOI | D34: 3880000
A35: Reconciled NOI | D35: ='Property Cash Flow'!M19*12 -> 3761085.4
A36: Year 1 Proforma NOI | D36: ='Property Cash Flow'!E19 -> 2957772.2
A37: Stabilized NOI | D37: ='Property Cash Flow'!H19 -> 6027050.5
A38: Exit Year NOI | D38: ='Exit Analysis'!B5 -> 6545315.3
A39: Unlevered IRR | D39: ='Property Cash Flow'!B35 -> 0.11468807
A41: DEBT TERMS
A42: Selected Lender | D42: ='Leverage Options'!B4 -> First Southeast Bank
A43: Loan Type | D43: ='Leverage Options'!B5 -> Construction-to-Permanent
A44: Rate | D44: ='Leverage Options'!B9 -> 7.10%
A45: Loan Amount | D45: =MAX('Leverage Options'!B26,MIN('Leverage Options'!B27:B28)) -> 57936597
A46: LTC | D46: ='Leverage Options'!B10 -> 75%
A47: LTV at Stabilization | D47: ='Leverage Options'!B11 -> 70%
A48: DSCR at Conversion | D48: ='Leverage Options'!B12 -> 1.25
A49: IO Period | D49: ='Leverage Options'!B13 -> 36
A50: Amortization | D50: ='Leverage Options'!B16 -> 30
A51: Term | D51: ='Leverage Options'!B17 -> 5
A52: Lender Selection Rationale | D52: Max Returns
A54: RENOVATION PROGRAM
A55: Selected Contractor | D55: Pinnacle Builders
A56: Total Budget | D56: =RenoBudget -> 7500000
A57: Timeline | D57: 18 months
A58: Selection Rationale | D58: Closest in pricing to Headof Development
A60: JV STRUCTURE & RETURNS
A61: GP / LP Equity Split | D61: =Assumptions!C67 -> Contributions called 90/10 LP/GP
A62: Preferred Return | D62: =Assumptions!B69 -> 0.08
A63: Promote Structure | D63: =Waterfall!A2 -> GP 10% / LP 90% · 8% pref (effective annual, monthly compounding) · 50/50 catch-up to 20% GP profit share · 80/20 LP/GP residual
A64: GP IRR | D64: =Waterfall!B72 -> 0.30356701
A65: LP IRR | D65: =Waterfall!B71 -> 0.19814531
A66: GP Equity Multiple | D66: =Waterfall!B75 -> 3.222145
A67: LP Equity Multiple | D67: =Waterfall!B74 -> 1.98762
A68: Total Project IRR | D68: =Waterfall!B73 -> 0.21210951
A70: RECOMMENDATION
A71: Go / No-Go | D71: =IF(AND(D68>0.15,'Property Cash Flow'!B75>1.8),"GO","PASS") -> GO | E71: Reference from fund return targets
A72: Rationale | D72: Returns
A73: Key Return Metric vs Fund Threshold | D73: IRR & MOIC

Sheet LOI
A1: LETTER OF INTENT
A3: HARBORVIEW CAPITAL PARTNERS
A5: PROPERTY DETAILS
A6: Property Name: | B6: =Assumptions!A1 -> SouthPark Centre
A7: Address: | B7: =Assumptions!A2 -> 4800 Sharon Road, Charlotte, NC 2821
A8: Total SF: | B8: =BldgSF -> 280000
A10: TRANSACTION TERMS
A11: Buyer: | B11: =A3 -> HARBORVIEW CAPITAL PARTNERS | C11: e.g. Harborview Capital Partners or its designee
A12: Purchase Price: | B12: =PurchasePrice -> 50000000 | C12: Link to model
A13: Deposit: | B13: =B12*1% -> 500000 | C13: Typically 1% of purchase price | D13: From email 4
A14: Due Diligence Period: | B14: 45 | C14: Calendar days from execution | D14: From email 4
A15: Financing Contingency: | B15: 30 | C15: Calendar days from DD expiration | D15: From email 4
A16: Target Close Date: | B16: =CloseDate -> 46265
A18: CONDITIONS
A19: Access: | B19: Full access to property and all books/records during DD | C19: Property access during DD period | D19: From email 4
A20: Exclusivity: | B20: 60 days | C20: Period of exclusivity from execution | D20: From email 4
A21: Existing Contracts: | B21: Assignable at close, subject to review during diligence | C21: Assignment of service contracts | D21: From email 4
A22: Tenant Estoppels: | B22: At least 75% of tenants by occupied SF | C22: Required from what % of tenants | D22: From email 4
A23: Title & Survey: | B23: Standard title commitment and ALTA survey | C23: Clean title, ALTA survey | D23: From email 4
A24: Environmental: | B24: Phase I at seller's cost, Phase II if flagged | C24: Phase I/II requirements | D24: From email 4
A26: EXPIRATION
A27: This LOI expires: | B27: 10 | C27: Business days from date of issuance | D27: From email 4

Sheet Property Cash Flow
A1: SouthPark Centre — Cash Flow Summary
A2: in $'000s
A3: Year # | D3: 0 | E3: =D3+1 -> 1 | F3: =E3+1 -> 2 | G3: =F3+1 -> 3 | H3: =G3+1 -> 4 | I3: =H3+1 -> 5 | J3: =I3+1 -> 6 | L3: =INT((L4-1)/12)+1 -> 0 | M3: =INT((M4-1)/12)+1 -> 1 | N3: =INT((N4-1)/12)+1 -> 1 | O3: =INT((O4-1)/12)+1 -> 1 | P3: =INT((P4-1)/12)+1 -> 1 | Q3: =INT((Q4-1)/12)+1 -> 1 | R3: =INT((R4-1)/12)+1 -> 1 | S3: =INT((S4-1)/12)+1 -> 1 | ... CF3: =INT((CF4-1)/12)+1 -> 6
A4: Month # | D4: 0 | E4: =D4+12 -> 12 | F4: =E4+12 -> 24 | G4: =F4+12 -> 36 | H4: =G4+12 -> 48 | I4: =H4+12 -> 60 | J4: =I4+12 -> 72 | L4: ='Rent Roll Calc'!D3 -> 0 | M4: ='Rent Roll Calc'!E3 -> 1 | N4: ='Rent Roll Calc'!F3 -> 2 | O4: ='Rent Roll Calc'!G3 -> 3 | P4: ='Rent Roll Calc'!H3 -> 4 | Q4: ='Rent Roll Calc'!I3 -> 5 | R4: ='Rent Roll Calc'!J3 -> 6 | S4: ='Rent Roll Calc'!K3 -> 7 | ... CF4: ='Rent Roll Calc'!BX3 -> 72
A5: Period End | D5: =+EOMONTH(CloseDate,0) -> 46265 | E5: =EOMONTH(D5,12) -> 46630 | F5: =EOMONTH(E5,12) -> 46996 | G5: =EOMONTH(F5,12) -> 47361 | H5: =EOMONTH(G5,12) -> 47726 | I5: =EOMONTH(H5,12) -> 48091 | J5: =EOMONTH(I5,12) -> 48457 | L5: ='Rent Roll Calc'!D4 -> 46265 | M5: ='Rent Roll Calc'!E4 -> 46295 | N5: ='Rent Roll Calc'!F4 -> 46326 | O5: ='Rent Roll Calc'!G4 -> 46356 | P5: ='Rent Roll Calc'!H4 -> 46387 | Q5: ='Rent Roll Calc'!I4 -> 46418 | R5: ='Rent Roll Calc'!J4 -> 46446 | S5: ='Rent Roll Calc'!K4 -> 46477 | ... CF5: ='Rent Roll Calc'!BX4 -> 48457
A6: Occupancy % | D6: =AVERAGEIFS($L6:$CF6,$L$3:$CF$3,D$3) -> 0.77357143 | E6: =AVERAGEIFS($L6:$CF6,$L$3:$CF$3,E$3) -> 0.68791667 | F6: =AVERAGEIFS($L6:$CF6,$L$3:$CF$3,F$3) -> 0.94074405 | G6: =AVERAGEIFS($L6:$CF6,$L$3:$CF$3,G$3) -> 0.90452381 | H6: =AVERAGEIFS($L6:$CF6,$L$3:$CF$3,H$3) -> 0.96104167 | I6: =AVERAGEIFS($L6:$CF6,$L$3:$CF$3,I$3) -> 0.97738095 | J6: =AVERAGEIFS($L6:$CF6,$L$3:$CF$3,J$3) -> 0.97818452 | L6: ='Rent Roll Calc'!D359/BldgSF -> 0.77357143 | M6: ='Rent Roll Calc'!E359/BldgSF -> 0.77357143 | N6: ='Rent Roll Calc'!F359/BldgSF -> 0.80392857 | O6: ='Rent Roll Calc'!G359/BldgSF -> 0.55535714 | P6: ='Rent Roll Calc'!H359/BldgSF -> 0.57607143 | Q6: ='Rent Roll Calc'!I359/BldgSF -> 0.60892857 | R6: ='Rent Roll Calc'!J359/BldgSF -> 0.63571429 | S6: ='Rent Roll Calc'!K359/BldgSF -> 0.63571429 | ... CF6: ='Rent Roll Calc'!BX359/BldgSF -> 0.99357143
A8: Gross Rental Income | D8: =SUMIFS($L8:$CF8,$L$3:$CF$3,D$3) -> 0 | E8: =SUMIFS($L8:$CF8,$L$3:$CF$3,E$3) -> 4242046.3 | F8: =SUMIFS($L8:$CF8,$L$3:$CF$3,F$3) -> 6442836.2 | G8: =SUMIFS($L8:$CF8,$L$3:$CF$3,G$3) -> 6521652.5 | H8: =SUMIFS($L8:$CF8,$L$3:$CF$3,H$3) -> 7297171.5 | I8: =SUMIFS($L8:$CF8,$L$3:$CF$3,I$3) -> 7679584.1 | J8: =SUMIFS($L8:$CF8,$L$3:$CF$3,J$3) -> 7953389.9 | M8: ='Rent Roll Calc'!E352+'Rent Roll Calc'!E353 -> 368853.75 | N8: ='Rent Roll Calc'!F352+'Rent Roll Calc'!F353 -> 386879.22 | O8: ='Rent Roll Calc'!G352+'Rent Roll Calc'!G353 -> 276827.47 | P8: ='Rent Roll Calc'!H352+'Rent Roll Calc'!H353 -> 289186.84 | Q8: ='Rent Roll Calc'!I352+'Rent Roll Calc'!I353 -> 312147.59 | R8: ='Rent Roll Calc'!J352+'Rent Roll Calc'!J353 -> 328333.19 | S8: ='Rent Roll Calc'!K352+'Rent Roll Calc'!K353 -> 328751.78 | T8: ='Rent Roll Calc'!L352+'Rent Roll Calc'!L353 -> 348769.52 | ... CF8: ='Rent Roll Calc'!BX352+'Rent Roll Calc'!BX353 -> 678889.91
A9: Free Rent | D9: =SUMIFS($L9:$CF9,$L$3:$CF$3,D$3) -> 0 | E9: =SUMIFS($L9:$CF9,$L$3:$CF$3,E$3) -> -378313.2 | F9: =SUMIFS($L9:$CF9,$L$3:$CF$3,F$3) -> -332829.86 | G9: =SUMIFS($L9:$CF9,$L$3:$CF$3,G$3) -> -214452.09 | H9: =SUMIFS($L9:$CF9,$L$3:$CF$3,H$3) -> -156624.11 | I9: =SUMIFS($L9:$CF9,$L$3:$CF$3,I$3) -> -76390.288 | J9: =SUMIFS($L9:$CF9,$L$3:$CF$3,J$3) -> -65277.575 | M9: ='Rent Roll Calc'!E354 -> 0 | N9: ='Rent Roll Calc'!F354 -> -17475.469 | O9: ='Rent Roll Calc'!G354 -> -30633.469 | P9: ='Rent Roll Calc'!H354 -> -25082.437 | Q9: ='Rent Roll Calc'!I354 -> -31671.717 | R9: ='Rent Roll Calc'!J354 -> -35261.178 | S9: ='Rent Roll Calc'!K354 -> -15835.859 | T9: ='Rent Roll Calc'!L354 -> -18580.741 | ... CF9: ='Rent Roll Calc'!BX354 -> 0
A10: Net Rental Income | D10: =SUMIFS($L10:$CF10,$L$3:$CF$3,D$3) -> 0 | E10: =SUMIFS($L10:$CF10,$L$3:$CF$3,E$3) -> 3863733.1 | F10: =SUMIFS($L10:$CF10,$L$3:$CF$3,F$3) -> 6110006.3 | G10: =SUMIFS($L10:$CF10,$L$3:$CF$3,G$3) -> 6307200.4 | H10: =SUMIFS($L10:$CF10,$L$3:$CF$3,H$3) -> 7140547.3 | I10: =SUMIFS($L10:$CF10,$L$3:$CF$3,I$3) -> 7603193.8 | J10: =SUMIFS($L10:$CF10,$L$3:$CF$3,J$3) -> 7888112.4 | M10: =SUM(M8:M9) -> 368853.75 | N10: =SUM(N8:N9) -> 369403.75 | O10: =SUM(O8:O9) -> 246194 | P10: =SUM(P8:P9) -> 264104.41 | Q10: =SUM(Q8:Q9) -> 280475.87 | R10: =SUM(R8:R9) -> 293072.01 | S10: =SUM(S8:S9) -> 312915.92 | T10: =SUM(T8:T9) -> 330188.78 | ... CF10: =SUM(CF8:CF9) -> 678889.91
A12: Expense Recovery (NNN) | D12: =SUMIFS($L12:$CF12,$L$3:$CF$3,D$3) -> 0 | E12: =SUMIFS($L12:$CF12,$L$3:$CF$3,E$3) -> 2053278.9 | F12: =SUMIFS($L12:$CF12,$L$3:$CF$3,F$3) -> 2884395.7 | G12: =SUMIFS($L12:$CF12,$L$3:$CF$3,G$3) -> 2845516.7 | H12: =SUMIFS($L12:$CF12,$L$3:$CF$3,H$3) -> 3106601.8 | I12: =SUMIFS($L12:$CF12,$L$3:$CF$3,I$3) -> 3245276.3 | J12: =SUMIFS($L12:$CF12,$L$3:$CF$3,J$3) -> 3335899.7 | M12: ='Rent Roll Calc'!E356 -> 188983.5 | N12: ='Rent Roll Calc'!F356 -> 196399.75 | O12: ='Rent Roll Calc'!G356 -> 135673.75 | P12: ='Rent Roll Calc'!H356 -> 140734.25 | Q12: ='Rent Roll Calc'!I356 -> 152777.8 | R12: ='Rent Roll Calc'!J356 -> 159498.23 | S12: ='Rent Roll Calc'!K356 -> 159498.23 | T12: ='Rent Roll Calc'!L356 -> 167383.54 | ... CF12: ='Rent Roll Calc'!BX356 -> 284803.43
A13: Other Income | D13: =SUMIFS($L13:$CF13,$L$3:$CF$3,D$3) -> 0 | E13: =SUMIFS($L13:$CF13,$L$3:$CF$3,E$3) -> 282000 | F13: =SUMIFS($L13:$CF13,$L$3:$CF$3,F$3) -> 288390 | G13: =SUMIFS($L13:$CF13,$L$3:$CF$3,G$3) -> 294936.55 | H13: =SUMIFS($L13:$CF13,$L$3:$CF$3,H$3) -> 301643.5 | I13: =SUMIFS($L13:$CF13,$L$3:$CF$3,I$3) -> 308514.79 | J13: =SUMIFS($L13:$CF13,$L$3:$CF$3,J$3) -> 315554.47 | M13: =(Assumptions!$B$45*(1+ParkGrowth)^('Rent Roll Calc'!E$5-1)+Assumptions!$B$46*(1+AntennaGrowth)^('Rent Roll Calc'!E$5-1)+Assumptions!$B$47)/12 -> 23500 | N13: =(Assumptions!$B$45*(1+ParkGrowth)^('Rent Roll Calc'!F$5-1)+Assumptions!$B$46*(1+AntennaGrowth)^('Rent Roll Calc'!F$5-1)+Assumptions!$B$47)/12 -> 23500 | O13: =(Assumptions!$B$45*(1+ParkGrowth)^('Rent Roll Calc'!G$5-1)+Assumptions!$B$46*(1+AntennaGrowth)^('Rent Roll Calc'!G$5-1)+Assumptions!$B$47)/12 -> 23500 | P13: =(Assumptions!$B$45*(1+ParkGrowth)^('Rent Roll Calc'!H$5-1)+Assumptions!$B$46*(1+AntennaGrowth)^('Rent Roll Calc'!H$5-1)+Assumptions!$B$47)/12 -> 23500 | Q13: =(Assumptions!$B$45*(1+ParkGrowth)^('Rent Roll Calc'!I$5-1)+Assumptions!$B$46*(1+AntennaGrowth)^('Rent Roll Calc'!I$5-1)+Assumptions!$B$47)/12 -> 23500 | R13: =(Assumptions!$B$45*(1+ParkGrowth)^('Rent Roll Calc'!J$5-1)+Assumptions!$B$46*(1+AntennaGrowth)^('Rent Roll Calc'!J$5-1)+Assumptions!$B$47)/12 -> 23500 | S13: =(Assumptions!$B$45*(1+ParkGrowth)^('Rent Roll Calc'!K$5-1)+Assumptions!$B$46*(1+AntennaGrowth)^('Rent Roll Calc'!K$5-1)+Assumptions!$B$47)/12 -> 23500 | T13: =(Assumptions!$B$45*(1+ParkGrowth)^('Rent Roll Calc'!L$5-1)+Assumptions!$B$46*(1+AntennaGrowth)^('Rent Roll Calc'!L$5-1)+Assumptions!$B$47)/12 -> 23500 | ... CF13: =(Assumptions!$B$45*(1+ParkGrowth)^('Rent Roll Calc'!BX$5-1)+Assumptions!$B$46*(1+AntennaGrowth)^('Rent Roll Calc'!BX$5-1)+Assumptions!$B$47)/12 -> 26296.206
A14: Effective Gross Income | D14: =D10+D12+D13 -> 0 | E14: =E10+E12+E13 -> 6199012 | F14: =F10+F12+F13 -> 9282792.1 | G14: =G10+G12+G13 -> 9447653.7 | H14: =H10+H12+H13 -> 10548793 | I14: =I10+I12+I13 -> 11156985 | J14: =J10+J12+J13 -> 11539567 | M14: =M10+M12+M13 -> 581337.25 | N14: =N10+N12+N13 -> 589303.5 | O14: =O10+O12+O13 -> 405367.75 | P14: =P10+P12+P13 -> 428338.66 | Q14: =Q10+Q12+Q13 -> 456753.68 | R14: =R10+R12+R13 -> 476070.24 | S14: =S10+S12+S13 -> 495914.16 | T14: =T10+T12+T13 -> 521072.32 | ... CF14: =CF10+CF12+CF13 -> 989989.55
A16: General Vacancy Adjustment | D16: =SUMIFS($L16:$CF16,$L$3:$CF$3,D$3) -> 0 | E16: =SUMIFS($L16:$CF16,$L$3:$CF$3,E$3) -> 0 | F16: =SUMIFS($L16:$CF16,$L$3:$CF$3,F$3) -> -633124.25 | G16: =SUMIFS($L16:$CF16,$L$3:$CF$3,G$3) -> -364160.33 | H16: =SUMIFS($L16:$CF16,$L$3:$CF$3,H$3) -> -876620.16 | I16: =SUMIFS($L16:$CF16,$L$3:$CF$3,I$3) -> -1089696.2 | J16: =SUMIFS($L16:$CF16,$L$3:$CF$3,J$3) -> -1135164.7 | M16: =(SUM(M8,M12)/M6)*-(MAX('Property Cash Flow'!M6-Assumptions!$B$22,0)) -> 0 | N16: =(SUM(N8,N12)/N6)*-(MAX('Property Cash Flow'!N6-Assumptions!$B$22,0)) -> 0 | O16: =(SUM(O8,O12)/O6)*-(MAX('Property Cash Flow'!O6-Assumptions!$B$22,0)) -> 0 | P16: =(SUM(P8,P12)/P6)*-(MAX('Property Cash Flow'!P6-Assumptions!$B$22,0)) -> 0 | Q16: =(SUM(Q8,Q12)/Q6)*-(MAX('Property Cash Flow'!Q6-Assumptions!$B$22,0)) -> 0 | R16: =(SUM(R8,R12)/R6)*-(MAX('Property Cash Flow'!R6-Assumptions!$B$22,0)) -> 0 | S16: =(SUM(S8,S12)/S6)*-(MAX('Property Cash Flow'!S6-Assumptions!$B$22,0)) -> 0 | T16: =(SUM(T8,T12)/T6)*-(MAX('Property Cash Flow'!T6-Assumptions!$B$22,0)) -> 0 | ... CF16: =(SUM(CF8,CF12)/CF6)*-(MAX('Property Cash Flow'!CF6-Assumptions!$B$22,0)) -> -110156.18
A17: Operating Expenses | D17: =SUMIFS($L17:$CF17,$L$3:$CF$3,D$3) -> 0 | E17: =SUMIFS($L17:$CF17,$L$3:$CF$3,E$3) -> -3024274.4 | F17: =SUMIFS($L17:$CF17,$L$3:$CF$3,F$3) -> -3105929.8 | G17: =SUMIFS($L17:$CF17,$L$3:$CF$3,G$3) -> -3189789.9 | H17: =SUMIFS($L17:$CF17,$L$3:$CF$3,H$3) -> -3275914.2 | I17: =SUMIFS($L17:$CF17,$L$3:$CF$3,I$3) -> -3364363.9 | J17: =SUMIFS($L17:$CF17,$L$3:$CF$3,J$3) -> -3455201.8 | M17: =-Assumptions!$B$39/12*'Rent Roll Calc'!E$7 -> -247566.67 | N17: =-Assumptions!$B$39/12*'Rent Roll Calc'!F$7 -> -247566.67 | O17: =-Assumptions!$B$39/12*'Rent Roll Calc'!G$7 -> -247566.67 | P17: =-Assumptions!$B$39/12*'Rent Roll Calc'!H$7 -> -247566.67 | Q17: =-Assumptions!$B$39/12*'Rent Roll Calc'!I$7 -> -254250.97 | R17: =-Assumptions!$B$39/12*'Rent Roll Calc'!J$7 -> -254250.97 | S17: =-Assumptions!$B$39/12*'Rent Roll Calc'!K$7 -> -254250.97 | T17: =-Assumptions!$B$39/12*'Rent Roll Calc'!L$7 -> -254250.97 | ... CF17: =-Assumptions!$B$39/12*'Rent Roll Calc'!BX$7 -> -290479.06
A18: Management Fee | D18: =SUMIFS($L18:$CF18,$L$3:$CF$3,D$3) -> 0 | E18: =SUMIFS($L18:$CF18,$L$3:$CF$3,E$3) -> -216965.42 | F18: =SUMIFS($L18:$CF18,$L$3:$CF$3,F$3) -> -324897.72 | G18: =SUMIFS($L18:$CF18,$L$3:$CF$3,G$3) -> -330667.88 | H18: =SUMIFS($L18:$CF18,$L$3:$CF$3,H$3) -> -369207.74 | I18: =SUMIFS($L18:$CF18,$L$3:$CF$3,I$3) -> -390494.47 | J18: =SUMIFS($L18:$CF18,$L$3:$CF$3,J$3) -> -403884.83 | M18: =-MgmtFeePct*M14 -> -20346.804 | N18: =-MgmtFeePct*N14 -> -20625.623 | O18: =-MgmtFeePct*O14 -> -14187.871 | P18: =-MgmtFeePct*P14 -> -14991.853 | Q18: =-MgmtFeePct*Q14 -> -15986.379 | R18: =-MgmtFeePct*R14 -> -16662.459 | S18: =-MgmtFeePct*S14 -> -17356.995 | T18: =-MgmtFeePct*T14 -> -18237.531 | ... CF18: =-MgmtFeePct*CF14 -> -34649.634
A19: Net Operating Income | D19: =D14+D17+D18+D16 -> 0 | E19: =E14+E17+E18+E16 -> 2957772.2 | F19: =F14+F17+F18+F16 -> 5218840.3 | G19: =G14+G17+G18+G16 -> 5563035.6 | H19: =H14+H17+H18+H16 -> 6027050.5 | I19: =I14+I17+I18+I16 -> 6312430.3 | J19: =J14+J17+J18+J16 -> 6545315.3 | M19: =M14+M17+M18+M16 -> 313423.78 | N19: =N14+N17+N18+N16 -> 321111.21 | O19: =O14+O17+O18+O16 -> 143613.21 | P19: =P14+P17+P18+P16 -> 165780.14 | Q19: =Q14+Q17+Q18+Q16 -> 186516.33 | R19: =R14+R17+R18+R16 -> 205156.82 | S19: =S14+S17+S18+S16 -> 224306.19 | T19: =T14+T17+T18+T16 -> 248583.82 | ... CF19: =CF14+CF17+CF18+CF16 -> 554704.68
A21: Renovation CapEx | D21: =SUMIFS($L21:$CF21,$L$3:$CF$3,D$3) -> 0 | E21: =SUMIFS($L21:$CF21,$L$3:$CF$3,E$3) -> -5990083.3 | F21: =SUMIFS($L21:$CF21,$L$3:$CF$3,F$3) -> -1509916.7 | G21: =SUMIFS($L21:$CF21,$L$3:$CF$3,G$3) -> 0 | H21: =SUMIFS($L21:$CF21,$L$3:$CF$3,H$3) -> 0 | I21: =SUMIFS($L21:$CF21,$L$3:$CF$3,I$3) -> 0 | J21: =SUMIFS($L21:$CF21,$L$3:$CF$3,J$3) -> 0 | M21: =-SUMIFS('CapEx Schedule'!$E$39:$V$39,'CapEx Schedule'!$E$6:$V$6,'Property Cash Flow'!M$4)*(M$4<=HoldMonths) -> -75354.167 | N21: =-SUMIFS('CapEx Schedule'!$E$39:$V$39,'CapEx Schedule'!$E$6:$V$6,'Property Cash Flow'!N$4)*(N$4<=HoldMonths) -> -157854.17 | O21: =-SUMIFS('CapEx Schedule'!$E$39:$V$39,'CapEx Schedule'!$E$6:$V$6,'Property Cash Flow'!O$4)*(O$4<=HoldMonths) -> -167304.17 | P21: =-SUMIFS('CapEx Schedule'!$E$39:$V$39,'CapEx Schedule'!$E$6:$V$6,'Property Cash Flow'!P$4)*(P$4<=HoldMonths) -> -198454.17 | Q21: =-SUMIFS('CapEx Schedule'!$E$39:$V$39,'CapEx Schedule'!$E$6:$V$6,'Property Cash Flow'!Q$4)*(Q$4<=HoldMonths) -> -221020.83 | R21: =-SUMIFS('CapEx Schedule'!$E$39:$V$39,'CapEx Schedule'!$E$6:$V$6,'Property Cash Flow'!R$4)*(R$4<=HoldMonths) -> -488820.83 | S21: =-SUMIFS('CapEx Schedule'!$E$39:$V$39,'CapEx Schedule'!$E$6:$V$6,'Property Cash Flow'!S$4)*(S$4<=HoldMonths) -> -509737.5 | T21: =-SUMIFS('CapEx Schedule'!$E$39:$V$39,'CapEx Schedule'!$E$6:$V$6,'Property Cash Flow'!T$4)*(T$4<=HoldMonths) -> -725454.17 | ... CF21: =-SUMIFS('CapEx Schedule'!$E$39:$V$39,'CapEx Schedule'!$E$6:$V$6,'Property Cash Flow'!CF$4)*(CF$4<=HoldMonths) -> 0
A22: Building Reserves | D22: =SUMIFS($L22:$CF22,$L$3:$CF$3,D$3) -> 0 | E22: =SUMIFS($L22:$CF22,$L$3:$CF$3,E$3) -> -140000 | F22: =SUMIFS($L22:$CF22,$L$3:$CF$3,F$3) -> -143500 | G22: =SUMIFS($L22:$CF22,$L$3:$CF$3,G$3) -> -147087.5 | H22: =SUMIFS($L22:$CF22,$L$3:$CF$3,H$3) -> -150764.69 | I22: =SUMIFS($L22:$CF22,$L$3:$CF$3,I$3) -> -154533.8 | J22: =SUMIFS($L22:$CF22,$L$3:$CF$3,J$3) -> 0 | M22: =(-ReservesPSF/12*BldgSF*(1+ReservesGrowth)^('Rent Roll Calc'!E$5-1))*(M$4<=HoldMonths) -> -11666.667 | N22: =(-ReservesPSF/12*BldgSF*(1+ReservesGrowth)^('Rent Roll Calc'!F$5-1))*(N$4<=HoldMonths) -> -11666.667 | O22: =(-ReservesPSF/12*BldgSF*(1+ReservesGrowth)^('Rent Roll Calc'!G$5-1))*(O$4<=HoldMonths) -> -11666.667 | P22: =(-ReservesPSF/12*BldgSF*(1+ReservesGrowth)^('Rent Roll Calc'!H$5-1))*(P$4<=HoldMonths) -> -11666.667 | Q22: =(-ReservesPSF/12*BldgSF*(1+ReservesGrowth)^('Rent Roll Calc'!I$5-1))*(Q$4<=HoldMonths) -> -11666.667 | R22: =(-ReservesPSF/12*BldgSF*(1+ReservesGrowth)^('Rent Roll Calc'!J$5-1))*(R$4<=HoldMonths) -> -11666.667 | S22: =(-ReservesPSF/12*BldgSF*(1+ReservesGrowth)^('Rent Roll Calc'!K$5-1))*(S$4<=HoldMonths) -> -11666.667 | T22: =(-ReservesPSF/12*BldgSF*(1+ReservesGrowth)^('Rent Roll Calc'!L$5-1))*(T$4<=HoldMonths) -> -11666.667 | ... CF22: =(-ReservesPSF/12*BldgSF*(1+ReservesGrowth)^('Rent Roll Calc'!BX$5-1))*(CF$4<=HoldMonths) -> 0
A23: Tenant Improvements | D23: =SUMIFS($L23:$CF23,$L$3:$CF$3,D$3) -> 0 | E23: =SUMIFS($L23:$CF23,$L$3:$CF$3,E$3) -> -4610933.3 | F23: =SUMIFS($L23:$CF23,$L$3:$CF$3,F$3) -> -1618266.7 | G23: =SUMIFS($L23:$CF23,$L$3:$CF$3,G$3) -> -2215600 | H23: =SUMIFS($L23:$CF23,$L$3:$CF$3,H$3) -> -817600 | I23: =SUMIFS($L23:$CF23,$L$3:$CF$3,I$3) -> -601200 | J23: =SUMIFS($L23:$CF23,$L$3:$CF$3,J$3) -> 0 | M23: ='Rent Roll Calc'!E357*(M$4<=HoldMonths) -> 0 | N23: ='Rent Roll Calc'!F357*(N$4<=HoldMonths) -> -306000 | O23: ='Rent Roll Calc'!G357*(O$4<=HoldMonths) -> -230400 | P23: ='Rent Roll Calc'!H357*(P$4<=HoldMonths) -> -208800 | Q23: ='Rent Roll Calc'!I357*(Q$4<=HoldMonths) -> -331200 | R23: ='Rent Roll Calc'!J357*(R$4<=HoldMonths) -> -450000 | S23: ='Rent Roll Calc'!K357*(S$4<=HoldMonths) -> -180000 | T23: ='Rent Roll Calc'!L357*(T$4<=HoldMonths) -> -663466.67 | ... CF23: ='Rent Roll Calc'!BX357*(CF$4<=HoldMonths) -> 0
A24: Leasing Commissions | D24: =SUMIFS($L24:$CF24,$L$3:$CF$3,D$3) -> 0 | E24: =SUMIFS($L24:$CF24,$L$3:$CF$3,E$3) -> -111087.45 | F24: =SUMIFS($L24:$CF24,$L$3:$CF$3,F$3) -> -99636.906 | G24: =SUMIFS($L24:$CF24,$L$3:$CF$3,G$3) -> -67500.469 | H24: =SUMIFS($L24:$CF24,$L$3:$CF$3,H$3) -> -29283.45 | I24: =SUMIFS($L24:$CF24,$L$3:$CF$3,I$3) -> -20600.494 | J24: =SUMIFS($L24:$CF24,$L$3:$CF$3,J$3) -> 0 | M24: ='Rent Roll Calc'!E358*(M$4<=HoldMonths) -> 0 | N24: ='Rent Roll Calc'!F358*(N$4<=HoldMonths) -> -10485.281 | O24: ='Rent Roll Calc'!G358*(O$4<=HoldMonths) -> -7894.8 | P24: ='Rent Roll Calc'!H358*(P$4<=HoldMonths) -> -7154.6625 | Q24: ='Rent Roll Calc'!I358*(Q$4<=HoldMonths) -> -11348.775 | R24: ='Rent Roll Calc'!J358*(R$4<=HoldMonths) -> -9251.7187 | S24: ='Rent Roll Calc'!K358*(S$4<=HoldMonths) -> 0 | T24: ='Rent Roll Calc'!L358*(T$4<=HoldMonths) -> -10855.35 | ... CF24: ='Rent Roll Calc'!BX358*(CF$4<=HoldMonths) -> 0
A25: Total Capital Expenditure | D25: =SUM(D21:D24) -> 0 | E25: =SUM(E21:E24) -> -10852104 | F25: =SUM(F21:F24) -> -3371320.2 | G25: =SUM(G21:G24) -> -2430188 | H25: =SUM(H21:H24) -> -997648.14 | I25: =SUM(I21:I24) -> -776334.3 | J25: =SUM(J21:J24) -> 0 | M25: =SUM(M21:M24) -> -87020.833 | N25: =SUM(N21:N24) -> -486006.11 | O25: =SUM(O21:O24) -> -417265.63 | P25: =SUM(P21:P24) -> -426075.5 | Q25: =SUM(Q21:Q24) -> -575236.28 | R25: =SUM(R21:R24) -> -959739.22 | S25: =SUM(S21:S24) -> -701404.17 | T25: =SUM(T21:T24) -> -1411442.9 | ... CF25: =SUM(CF21:CF24) -> 0
A27: Unlevered Operating Cash Flow | D27: =SUMIFS($L27:$CF27,$L$3:$CF$3,D$3) -> 0 | E27: =SUMIFS($L27:$CF27,$L$3:$CF$3,E$3) -> -7894331.9 | F27: =SUMIFS($L27:$CF27,$L$3:$CF$3,F$3) -> 1847520 | G27: =SUMIFS($L27:$CF27,$L$3:$CF$3,G$3) -> 3132847.6 | H27: =SUMIFS($L27:$CF27,$L$3:$CF$3,H$3) -> 5029402.3 | I27: =SUMIFS($L27:$CF27,$L$3:$CF$3,I$3) -> 5536096 | J27: =SUMIFS($L27:$CF27,$L$3:$CF$3,J$3) -> 0 | L27: =(L19+L25)*(L$4<=HoldMonths) -> 0 | M27: =(M19+M25)*(M$4<=HoldMonths) -> 226402.95 | N27: =(N19+N25)*(N$4<=HoldMonths) -> -164894.9 | O27: =(O19+O25)*(O$4<=HoldMonths) -> -273652.42 | P27: =(P19+P25)*(P$4<=HoldMonths) -> -260295.36 | Q27: =(Q19+Q25)*(Q$4<=HoldMonths) -> -388719.95 | R27: =(R19+R25)*(R$4<=HoldMonths) -> -754582.4 | S27: =(S19+S25)*(S$4<=HoldMonths) -> -477097.97 | ... CF27: =(CF19+CF25)*(CF$4<=HoldMonths) -> 0
A29: Acquisition Price | D29: =SUMIFS($L29:$CF29,$L$3:$CF$3,D$3) -> -50000000 | E29: =SUMIFS($L29:$CF29,$L$3:$CF$3,E$3) -> 0 | F29: =SUMIFS($L29:$CF29,$L$3:$CF$3,F$3) -> 0 | G29: =SUMIFS($L29:$CF29,$L$3:$CF$3,G$3) -> 0 | H29: =SUMIFS($L29:$CF29,$L$3:$CF$3,H$3) -> 0 | I29: =SUMIFS($L29:$CF29,$L$3:$CF$3,I$3) -> 0 | J29: =SUMIFS($L29:$CF29,$L$3:$CF$3,J$3) -> 0 | L29: =-PurchasePrice -> -50000000
A30: Acquisition Costs | D30: =SUMIFS($L30:$CF30,$L$3:$CF$3,D$3) -> -1500000 | E30: =SUMIFS($L30:$CF30,$L$3:$CF$3,E$3) -> 0 | F30: =SUMIFS($L30:$CF30,$L$3:$CF$3,F$3) -> 0 | G30: =SUMIFS($L30:$CF30,$L$3:$CF$3,G$3) -> 0 | H30: =SUMIFS($L30:$CF30,$L$3:$CF$3,H$3) -> 0 | I30: =SUMIFS($L30:$CF30,$L$3:$CF$3,I$3) -> 0 | J30: =SUMIFS($L30:$CF30,$L$3:$CF$3,J$3) -> 0 | L30: =L29*Assumptions!B7 -> -1500000
A31: Disposition Price | D31: =SUMIFS($L31:$CF31,$L$3:$CF$3,D$3) -> 0 | E31: =SUMIFS($L31:$CF31,$L$3:$CF$3,E$3) -> 0 | F31: =SUMIFS($L31:$CF31,$L$3:$CF$3,F$3) -> 0 | G31: =SUMIFS($L31:$CF31,$L$3:$CF$3,G$3) -> 0 | H31: =SUMIFS($L31:$CF31,$L$3:$CF$3,H$3) -> 0 | I31: =SUMIFS($L31:$CF31,$L$3:$CF$3,I$3) -> 84455681 | J31: =SUMIFS($L31:$CF31,$L$3:$CF$3,J$3) -> 0 | L31: =(L$4=HoldMonths)*SUM(OFFSET('Property Cash Flow'!M$19,0,0,1,12))/ExitCap -> 0 | M31: =(M$4=HoldMonths)*SUM(OFFSET('Property Cash Flow'!N$19,0,0,1,12))/ExitCap -> 0 | N31: =(N$4=HoldMonths)*SUM(OFFSET('Property Cash Flow'!O$19,0,0,1,12))/ExitCap -> 0 | O31: =(O$4=HoldMonths)*SUM(OFFSET('Property Cash Flow'!P$19,0,0,1,12))/ExitCap -> 0 | P31: =(P$4=HoldMonths)*SUM(OFFSET('Property Cash Flow'!Q$19,0,0,1,12))/ExitCap -> 0 | Q31: =(Q$4=HoldMonths)*SUM(OFFSET('Property Cash Flow'!R$19,0,0,1,12))/ExitCap -> 0 | R31: =(R$4=HoldMonths)*SUM(OFFSET('Property Cash Flow'!S$19,0,0,1,12))/ExitCap -> 0 | S31: =(S$4=HoldMonths)*SUM(OFFSET('Property Cash Flow'!T$19,0,0,1,12))/ExitCap -> 0 | ... CF31: =(CF$4=HoldMonths)*SUM(OFFSET('Property Cash Flow'!CG$19,0,0,1,12))/ExitCap -> 0
A32: Exit Costs | D32: =SUMIFS($L32:$CF32,$L$3:$CF$3,D$3) -> 0 | E32: =SUMIFS($L32:$CF32,$L$3:$CF$3,E$3) -> 0 | F32: =SUMIFS($L32:$CF32,$L$3:$CF$3,F$3) -> 0 | G32: =SUMIFS($L32:$CF32,$L$3:$CF$3,G$3) -> 0 | H32: =SUMIFS($L32:$CF32,$L$3:$CF$3,H$3) -> 0 | I32: =SUMIFS($L32:$CF32,$L$3:$CF$3,I$3) -> -1689113.6 | J32: =SUMIFS($L32:$CF32,$L$3:$CF$3,J$3) -> 0 | L32: =L31*-DispCost -> 0 | M32: =M31*-DispCost -> 0 | N32: =N31*-DispCost -> 0 | O32: =O31*-DispCost -> 0 | P32: =P31*-DispCost -> 0 | Q32: =Q31*-DispCost -> 0 | R32: =R31*-DispCost -> 0 | S32: =S31*-DispCost -> 0 | ... CF32: =CF31*-DispCost -> 0
A34: Total Unlevered Cash Flow | D34: =SUM(D27,D29:D32) -> -51500000 | E34: =SUM(E27,E29:E32) -> -7894331.9 | F34: =SUM(F27,F29:F32) -> 1847520 | G34: =SUM(G27,G29:G32) -> 3132847.6 | H34: =SUM(H27,H29:H32) -> 5029402.3 | I34: =SUM(I27,I29:I32) -> 88302663 | J34: =SUM(J27,J29:J32) -> 0 | L34: =SUM(L27,L29:L32) -> -51500000 | M34: =SUM(M27,M29:M32) -> 226402.95 | N34: =SUM(N27,N29:N32) -> -164894.9 | O34: =SUM(O27,O29:O32) -> -273652.42 | P34: =SUM(P27,P29:P32) -> -260295.36 | Q34: =SUM(Q27,Q29:Q32) -> -388719.95 | R34: =SUM(R27,R29:R32) -> -754582.4 | S34: =SUM(S27,S29:S32) -> -477097.97 | ... CF34: =SUM(CF27,CF29:CF32) -> 0
A35: IRR | B35: =XIRR(L34:CF34,$L$5:$CF$5) -> 0.11468807
A36: Required Capital | B36: =-SUMIF(L34:CF34,"<0") -> 61528582
A37: Profit | B37: =SUM(L34:CF34) -> 38918102
A38: MoIC | B38: =B37/B36+1 -> 1.6325207
A41: Financing Cash Flow
A42: Acquisition / Dev Loan
A43: BoP Balance | D43: 0 | E43: =D48 -> 38625000 | F43: =E48 -> 47665744 | G43: =F48 -> 52075651 | H43: =G48 -> 0 | I43: =H48 -> 0 | J43: =I48 -> 0 | L43: 0 | M43: =L48 -> 38625000 | N43: =M48 -> 38853531 | O43: =N48 -> 39207086 | P43: =O48 -> 39644300 | Q43: =P48 -> 40074084 | R43: =Q48 -> 40602729 | S43: =R48 -> 41392883 | T43: =S48 -> 42003778 | ... CF43: =CE48 -> 0
A44: Drawdown | B44: ='Leverage Options'!B10 -> 75% | D44: =SUMIFS($L44:$CF44,$L$3:$CF$3,D$3) -> 38625000 | E44: =SUMIFS($L44:$CF44,$L$3:$CF$3,E$3) -> 6090551.1 | F44: =SUMIFS($L44:$CF44,$L$3:$CF$3,F$3) -> 862668.93 | G44: =SUMIFS($L44:$CF44,$L$3:$CF$3,G$3) -> 456174.01 | H44: =SUMIFS($L44:$CF44,$L$3:$CF$3,H$3) -> 0 | I44: =SUMIFS($L44:$CF44,$L$3:$CF$3,I$3) -> 0 | J44: =SUMIFS($L44:$CF44,$L$3:$CF$3,J$3) -> 0 | L44: =MIN(L34,0)*-$B44*(L$4<=$B47) -> 38625000 | M44: =MIN(M34,0)*-$B44*(M$4<=$B47) -> 0 | N44: =MIN(N34,0)*-$B44*(N$4<=$B47) -> 123671.18 | O44: =MIN(O34,0)*-$B44*(O$4<=$B47) -> 205239.32 | P44: =MIN(P34,0)*-$B44*(P$4<=$B47) -> 195221.52 | Q44: =MIN(Q34,0)*-$B44*(Q$4<=$B47) -> 291539.96 | R44: =MIN(R34,0)*-$B44*(R$4<=$B47) -> 565936.8 | S44: =MIN(S34,0)*-$B44*(S$4<=$B47) -> 357823.48 | ... CF44: =MIN(CF34,0)*-$B44*(CF$4<=$B47) -> 0
A45: PIK Interest | B45: ='Leverage Options'!B9 -> 7.10% | D45: =SUMIFS($L45:$CF45,$L$3:$CF$3,D$3) -> 0 | E45: =SUMIFS($L45:$CF45,$L$3:$CF$3,E$3) -> 2950192.8 | F45: =SUMIFS($L45:$CF45,$L$3:$CF$3,F$3) -> 3547237.8 | G45: =SUMIFS($L45:$CF45,$L$3:$CF$3,G$3) -> 3810017 | H45: =SUMIFS($L45:$CF45,$L$3:$CF$3,H$3) -> 0 | I45: =SUMIFS($L45:$CF45,$L$3:$CF$3,I$3) -> 0 | J45: =SUMIFS($L45:$CF45,$L$3:$CF$3,J$3) -> 0 | L45: =$B45*L43*YEARFRAC(K5,L5,0) -> 0 | M45: =$B45*M43*YEARFRAC(L5,M5,0) -> 228531.25 | N45: =$B45*N43*YEARFRAC(M5,N5,0) -> 229883.39 | O45: =$B45*O43*YEARFRAC(N5,O5,0) -> 231975.26 | P45: =$B45*P43*YEARFRAC(O5,P5,0) -> 234562.11 | Q45: =$B45*Q43*YEARFRAC(P5,Q5,0) -> 237105 | R45: =$B45*R43*YEARFRAC(Q5,R5,0) -> 224217.29 | S45: =$B45*S43*YEARFRAC(R5,S5,0) -> 253071.49 | ... CF45: =$B45*CF43*YEARFRAC(CE5,CF5,0) -> 0
A46: Scheduled Amortization | B46: n/a | D46: =SUMIFS($L46:$CF46,$L$3:$CF$3,D$3) -> 0 | E46: =SUMIFS($L46:$CF46,$L$3:$CF$3,E$3) -> 0 | F46: =SUMIFS($L46:$CF46,$L$3:$CF$3,F$3) -> 0 | G46: =SUMIFS($L46:$CF46,$L$3:$CF$3,G$3) -> 0 | H46: =SUMIFS($L46:$CF46,$L$3:$CF$3,H$3) -> 0 | I46: =SUMIFS($L46:$CF46,$L$3:$CF$3,I$3) -> 0 | J46: =SUMIFS($L46:$CF46,$L$3:$CF$3,J$3) -> 0 | L46: =IFERROR(PPMT((1+$B50)^(1/12)-1,L$4-$B$47,$B46*12,SUM(L44:L45),0,0),0) -> 0 | M46: =IFERROR(PPMT((1+$B50)^(1/12)-1,M$4-$B$47,$B46*12,SUM(M44:M45),0,0),0) -> 0 | N46: =IFERROR(PPMT((1+$B50)^(1/12)-1,N$4-$B$47,$B46*12,SUM(N44:N45),0,0),0) -> 0 | O46: =IFERROR(PPMT((1+$B50)^(1/12)-1,O$4-$B$47,$B46*12,SUM(O44:O45),0,0),0) -> 0 | P46: =IFERROR(PPMT((1+$B50)^(1/12)-1,P$4-$B$47,$B46*12,SUM(P44:P45),0,0),0) -> 0 | Q46: =IFERROR(PPMT((1+$B50)^(1/12)-1,Q$4-$B$47,$B46*12,SUM(Q44:Q45),0,0),0) -> 0 | R46: =IFERROR(PPMT((1+$B50)^(1/12)-1,R$4-$B$47,$B46*12,SUM(R44:R45),0,0),0) -> 0 | S46: =IFERROR(PPMT((1+$B50)^(1/12)-1,S$4-$B$47,$B46*12,SUM(S44:S45),0,0),0) -> 0 | ... CF46: =IFERROR(PPMT((1+$B50)^(1/12)-1,CF$4-$B$47,$B46*12,SUM(CF44:CF45),0,0),0) -> 0
A47: Repayment | B47: ='Leverage Options'!B13 -> 36 | D47: =SUMIFS($L47:$CF47,$L$3:$CF$3,D$3) -> 0 | E47: =SUMIFS($L47:$CF47,$L$3:$CF$3,E$3) -> 0 | F47: =SUMIFS($L47:$CF47,$L$3:$CF$3,F$3) -> 0 | G47: =SUMIFS($L47:$CF47,$L$3:$CF$3,G$3) -> -56341842 | H47: =SUMIFS($L47:$CF47,$L$3:$CF$3,H$3) -> 0 | I47: =SUMIFS($L47:$CF47,$L$3:$CF$3,I$3) -> 0 | J47: =SUMIFS($L47:$CF47,$L$3:$CF$3,J$3) -> 0 | L47: =-SUM(L43:L46)*(L4=$B47) -> 0 | M47: =-SUM(M43:M46)*(M4=$B47) -> 0 | N47: =-SUM(N43:N46)*(N4=$B47) -> 0 | O47: =-SUM(O43:O46)*(O4=$B47) -> 0 | P47: =-SUM(P43:P46)*(P4=$B47) -> 0 | Q47: =-SUM(Q43:Q46)*(Q4=$B47) -> 0 | R47: =-SUM(R43:R46)*(R4=$B47) -> 0 | S47: =-SUM(S43:S46)*(S4=$B47) -> 0 | ... CF47: =-SUM(CF43:CF46)*(CF4=$B47) -> 0
A48: EoP Balance | D48: =SUM(D43:D47) -> 38625000 | E48: =SUM(E43:E47) -> 47665744 | F48: =SUM(F43:F47) -> 52075651 | G48: =SUM(G43:G47) -> 0 | H48: =SUM(H43:H47) -> 0 | I48: =SUM(I43:I47) -> 0 | J48: =SUM(J43:J47) -> 0 | L48: =SUM(L43:L47) -> 38625000 | M48: =SUM(M43:M47) -> 38853531 | N48: =SUM(N43:N47) -> 39207086 | O48: =SUM(O43:O47) -> 39644300 | P48: =SUM(P43:P47) -> 40074084 | Q48: =SUM(Q43:Q47) -> 40602729 | R48: =SUM(R43:R47) -> 41392883 | S48: =SUM(S43:S47) -> 42003778 | ... CF48: =SUM(CF43:CF47) -> 0
A50: Cash Interest | B50: n/a | D50: =SUMIFS($L50:$CF50,$L$3:$CF$3,D$3) -> 0 | E50: =SUMIFS($L50:$CF50,$L$3:$CF$3,E$3) -> 0 | F50: =SUMIFS($L50:$CF50,$L$3:$CF$3,F$3) -> 0 | G50: =SUMIFS($L50:$CF50,$L$3:$CF$3,G$3) -> 0 | H50: =SUMIFS($L50:$CF50,$L$3:$CF$3,H$3) -> 0 | I50: =SUMIFS($L50:$CF50,$L$3:$CF$3,I$3) -> 0 | J50: =SUMIFS($L50:$CF50,$L$3:$CF$3,J$3) -> 0 | L50: =IFERROR(-$B50*L43*YEARFRAC(K5,L5,0),0) -> 0 | M50: =IFERROR(-$B50*M43*YEARFRAC(L5,M5,0),0) -> 0 | N50: =IFERROR(-$B50*N43*YEARFRAC(M5,N5,0),0) -> 0 | O50: =IFERROR(-$B50*O43*YEARFRAC(N5,O5,0),0) -> 0 | P50: =IFERROR(-$B50*P43*YEARFRAC(O5,P5,0),0) -> 0 | Q50: =IFERROR(-$B50*Q43*YEARFRAC(P5,Q5,0),0) -> 0 | R50: =IFERROR(-$B50*R43*YEARFRAC(Q5,R5,0),0) -> 0 | S50: =IFERROR(-$B50*S43*YEARFRAC(R5,S5,0),0) -> 0 | ... CF50: =IFERROR(-$B50*CF43*YEARFRAC(CE5,CF5,0),0) -> 0
A51: Loan Closing Costs | B51: ='Leverage Options'!B14 -> 0.015 | D51: =SUMIFS($L51:$CF51,$L$3:$CF$3,D$3) -> -690515.91 | E51: =SUMIFS($L51:$CF51,$L$3:$CF$3,E$3) -> 0 | F51: =SUMIFS($L51:$CF51,$L$3:$CF$3,F$3) -> 0 | G51: =SUMIFS($L51:$CF51,$L$3:$CF$3,G$3) -> 0 | H51: =SUMIFS($L51:$CF51,$L$3:$CF$3,H$3) -> 0 | I51: =SUMIFS($L51:$CF51,$L$3:$CF$3,I$3) -> 0 | J51: =SUMIFS($L51:$CF51,$L$3:$CF$3,J$3) -> 0 | L51: =SUM($L$44:$CF$44)*(L$4=0)*-$B51 -> -690515.91 | M51: =SUM($L$44:$CF$44)*(M$4=0)*-$B51 -> 0 | N51: =SUM($L$44:$CF$44)*(N$4=0)*-$B51 -> 0 | O51: =SUM($L$44:$CF$44)*(O$4=0)*-$B51 -> 0 | P51: =SUM($L$44:$CF$44)*(P$4=0)*-$B51 -> 0 | Q51: =SUM($L$44:$CF$44)*(Q$4=0)*-$B51 -> 0 | R51: =SUM($L$44:$CF$44)*(R$4=0)*-$B51 -> 0 | S51: =SUM($L$44:$CF$44)*(S$4=0)*-$B51 -> 0 | ... CF51: =SUM($L$44:$CF$44)*(CF$4=0)*-$B51 -> 0
A52: Origination Fee | B52: ='Leverage Options'!$B$20 -> 1.00% | D52: =SUMIFS($L52:$CF52,$L$3:$CF$3,D$3) -> -460343.94 | E52: =SUMIFS($L52:$CF52,$L$3:$CF$3,E$3) -> 0 | F52: =SUMIFS($L52:$CF52,$L$3:$CF$3,F$3) -> 0 | G52: =SUMIFS($L52:$CF52,$L$3:$CF$3,G$3) -> 0 | H52: =SUMIFS($L52:$CF52,$L$3:$CF$3,H$3) -> 0 | I52: =SUMIFS($L52:$CF52,$L$3:$CF$3,I$3) -> 0 | J52: =SUMIFS($L52:$CF52,$L$3:$CF$3,J$3) -> 0 | L52: =SUM($L$44:$CF$44)*(L$4=0)*-$B52 -> -460343.94 | M52: =SUM($L$44:$CF$44)*(M$4=0)*-$B52 -> 0 | N52: =SUM($L$44:$CF$44)*(N$4=0)*-$B52 -> 0 | O52: =SUM($L$44:$CF$44)*(O$4=0)*-$B52 -> 0 | P52: =SUM($L$44:$CF$44)*(P$4=0)*-$B52 -> 0 | Q52: =SUM($L$44:$CF$44)*(Q$4=0)*-$B52 -> 0 | R52: =SUM($L$44:$CF$44)*(R$4=0)*-$B52 -> 0 | S52: =SUM($L$44:$CF$44)*(S$4=0)*-$B52 -> 0 | ... CF52: =SUM($L$44:$CF$44)*(CF$4=0)*-$B52 -> 0
A54: Acquisition / Dev Loan Cash Flow | D54: =SUMIFS($L54:$CF54,$L$3:$CF$3,D$3) -> 37474140 | E54: =SUMIFS($L54:$CF54,$L$3:$CF$3,E$3) -> 6090551.1 | F54: =SUMIFS($L54:$CF54,$L$3:$CF$3,F$3) -> 862668.93 | G54: =SUMIFS($L54:$CF54,$L$3:$CF$3,G$3) -> -55885668 | H54: =SUMIFS($L54:$CF54,$L$3:$CF$3,H$3) -> 0 | I54: =SUMIFS($L54:$CF54,$L$3:$CF$3,I$3) -> 0 | J54: =SUMIFS($L54:$CF54,$L$3:$CF$3,J$3) -> 0 | L54: =SUM(L44,L50,L46,L47,L51,L52) -> 37474140 | M54: =SUM(M44,M50,M46,M47,M51,M52) -> 0 | N54: =SUM(N44,N50,N46,N47,N51,N52) -> 123671.18 | O54: =SUM(O44,O50,O46,O47,O51,O52) -> 205239.32 | P54: =SUM(P44,P50,P46,P47,P51,P52) -> 195221.52 | Q54: =SUM(Q44,Q50,Q46,Q47,Q51,Q52) -> 291539.96 | R54: =SUM(R44,R50,R46,R47,R51,R52) -> 565936.8 | S54: =SUM(S44,S50,S46,S47,S51,S52) -> 357823.48 | ... CF54: =SUM(CF44,CF50,CF46,CF47,CF51,CF52) -> 0
A58: Permanent Loan
A59: BoP Balance | D59: 0 | E59: =D63 -> 0 | F59: =E63 -> 0 | G59: =F63 -> 0 | H59: =G63 -> 57936597 | I59: =H63 -> 57337067 | J59: =I63 -> 0 | L59: 0 | M59: =L63 -> 0 | N59: =M63 -> 0 | O59: =N63 -> 0 | P59: =O63 -> 0 | Q59: =P63 -> 0 | R59: =Q63 -> 0 | S59: =R63 -> 0 | T59: =S63 -> 0 | ... CF59: =CE63 -> 0
A60: Drawdown | B60: =MIN('Leverage Options'!B27,'Leverage Options'!B28) -> 57936597 | D60: =SUMIFS($L60:$CF60,$L$3:$CF$3,D$3) -> 0 | E60: =SUMIFS($L60:$CF60,$L$3:$CF$3,E$3) -> 0 | F60: =SUMIFS($L60:$CF60,$L$3:$CF$3,F$3) -> 0 | G60: =SUMIFS($L60:$CF60,$L$3:$CF$3,G$3) -> 57936597 | H60: =SUMIFS($L60:$CF60,$L$3:$CF$3,H$3) -> 0 | I60: =SUMIFS($L60:$CF60,$L$3:$CF$3,I$3) -> 0 | J60: =SUMIFS($L60:$CF60,$L$3:$CF$3,J$3) -> 0 | L60: =$B60*(L$4=$B$47) -> 0 | M60: =$B60*(M$4=$B$47) -> 0 | N60: =$B60*(N$4=$B$47) -> 0 | O60: =$B60*(O$4=$B$47) -> 0 | P60: =$B60*(P$4=$B$47) -> 0 | Q60: =$B60*(Q$4=$B$47) -> 0 | R60: =$B60*(R$4=$B$47) -> 0 | S60: =$B60*(S$4=$B$47) -> 0 | ... CF60: =$B60*(CF$4=$B$47) -> 0
A61: Scheduled Amortization | B61: ='Leverage Options'!B16 -> 30 | D61: =SUMIFS($L61:$CF61,$L$3:$CF$3,D$3) -> 0 | E61: =SUMIFS($L61:$CF61,$L$3:$CF$3,E$3) -> 0 | F61: =SUMIFS($L61:$CF61,$L$3:$CF$3,F$3) -> 0 | G61: =SUMIFS($L61:$CF61,$L$3:$CF$3,G$3) -> 0 | H61: =SUMIFS($L61:$CF61,$L$3:$CF$3,H$3) -> -599530.29 | I61: =SUMIFS($L61:$CF61,$L$3:$CF$3,I$3) -> -635237.75 | J61: =SUMIFS($L61:$CF61,$L$3:$CF$3,J$3) -> 0 | L61: =IFERROR(PPMT((1+$B65)^(1/12)-1,L$4-$B$47,$B61*12,SUM(L59:L60),0,0),0) -> 0 | M61: =IFERROR(PPMT((1+$B65)^(1/12)-1,M$4-$B$47,$B61*12,SUM(M59:M60),0,0),0) -> 0 | N61: =IFERROR(PPMT((1+$B65)^(1/12)-1,N$4-$B$47,$B61*12,SUM(N59:N60),0,0),0) -> 0 | O61: =IFERROR(PPMT((1+$B65)^(1/12)-1,O$4-$B$47,$B61*12,SUM(O59:O60),0,0),0) -> 0 | P61: =IFERROR(PPMT((1+$B65)^(1/12)-1,P$4-$B$47,$B61*12,SUM(P59:P60),0,0),0) -> 0 | Q61: =IFERROR(PPMT((1+$B65)^(1/12)-1,Q$4-$B$47,$B61*12,SUM(Q59:Q60),0,0),0) -> 0 | R61: =IFERROR(PPMT((1+$B65)^(1/12)-1,R$4-$B$47,$B61*12,SUM(R59:R60),0,0),0) -> 0 | S61: =IFERROR(PPMT((1+$B65)^(1/12)-1,S$4-$B$47,$B61*12,SUM(S59:S60),0,0),0) -> 0 | ... CF61: =IFERROR(PPMT((1+$B65)^(1/12)-1,CF$4-$B$47,$B61*12,SUM(CF59:CF60),0,0),0) -> 0
A62: Repayment | B62: =MIN(B47+'Leverage Options'!B17*12,HoldMonths) -> 60 | D62: =SUMIFS($L62:$CF62,$L$3:$CF$3,D$3) -> 0 | E62: =SUMIFS($L62:$CF62,$L$3:$CF$3,E$3) -> 0 | F62: =SUMIFS($L62:$CF62,$L$3:$CF$3,F$3) -> 0 | G62: =SUMIFS($L62:$CF62,$L$3:$CF$3,G$3) -> 0 | H62: =SUMIFS($L62:$CF62,$L$3:$CF$3,H$3) -> 0 | I62: =SUMIFS($L62:$CF62,$L$3:$CF$3,I$3) -> -56701829 | J62: =SUMIFS($L62:$CF62,$L$3:$CF$3,J$3) -> 0 | L62: =-SUM(L59:L61)*(L$4=$B62) -> 0 | M62: =-SUM(M59:M61)*(M$4=$B62) -> 0 | N62: =-SUM(N59:N61)*(N$4=$B62) -> 0 | O62: =-SUM(O59:O61)*(O$4=$B62) -> 0 | P62: =-SUM(P59:P61)*(P$4=$B62) -> 0 | Q62: =-SUM(Q59:Q61)*(Q$4=$B62) -> 0 | R62: =-SUM(R59:R61)*(R$4=$B62) -> 0 | S62: =-SUM(S59:S61)*(S$4=$B62) -> 0 | ... CF62: =-SUM(CF59:CF61)*(CF$4=$B62) -> 0
A63: EoP Balance | D63: =SUM(D59:D62) -> 0 | E63: =SUM(E59:E62) -> 0 | F63: =SUM(F59:F62) -> 0 | G63: =SUM(G59:G62) -> 57936597 | H63: =SUM(H59:H62) -> 57337067 | I63: =SUM(I59:I62) -> 0 | J63: =SUM(J59:J62) -> 0 | L63: =SUM(L59:L62) -> 0 | M63: =SUM(M59:M62) -> 0 | N63: =SUM(N59:N62) -> 0 | O63: =SUM(O59:O62) -> 0 | P63: =SUM(P59:P62) -> 0 | Q63: =SUM(Q59:Q62) -> 0 | R63: =SUM(R59:R62) -> 0 | S63: =SUM(S59:S62) -> 0 | ... CF63: =SUM(CF59:CF62) -> 0
A65: Cash Interest | B65: ='Leverage Options'!B9 -> 7.10% | D65: =SUMIFS($L65:$CF65,$L$3:$CF$3,D$3) -> 0 | E65: =SUMIFS($L65:$CF65,$L$3:$CF$3,E$3) -> 0 | F65: =SUMIFS($L65:$CF65,$L$3:$CF$3,F$3) -> 0 | G65: =SUMIFS($L65:$CF65,$L$3:$CF$3,G$3) -> 0 | H65: =SUMIFS($L65:$CF65,$L$3:$CF$3,H$3) -> -4082806 | I65: =SUMIFS($L65:$CF65,$L$3:$CF$3,I$3) -> -4039207.4 | J65: =SUMIFS($L65:$CF65,$L$3:$CF$3,J$3) -> 0 | L65: =-$B65*L59*YEARFRAC(K5,L5,0) -> 0 | M65: =-$B65*M59*YEARFRAC(L5,M5,0) -> 0 | N65: =-$B65*N59*YEARFRAC(M5,N5,0) -> 0 | O65: =-$B65*O59*YEARFRAC(N5,O5,0) -> 0 | P65: =-$B65*P59*YEARFRAC(O5,P5,0) -> 0 | Q65: =-$B65*Q59*YEARFRAC(P5,Q5,0) -> 0 | R65: =-$B65*R59*YEARFRAC(Q5,R5,0) -> 0 | S65: =-$B65*S59*YEARFRAC(R5,S5,0) -> 0 | ... CF65: =-$B65*CF59*YEARFRAC(CE5,CF5,0) -> 0
A67: Permanent Loan Cash Flow | D67: =SUMIFS($L67:$CF67,$L$3:$CF$3,D$3) -> 0 | E67: =SUMIFS($L67:$CF67,$L$3:$CF$3,E$3) -> 0 | F67: =SUMIFS($L67:$CF67,$L$3:$CF$3,F$3) -> 0 | G67: =SUMIFS($L67:$CF67,$L$3:$CF$3,G$3) -> 57936597 | H67: =SUMIFS($L67:$CF67,$L$3:$CF$3,H$3) -> -4682336.3 | I67: =SUMIFS($L67:$CF67,$L$3:$CF$3,I$3) -> -61376274 | J67: =SUMIFS($L67:$CF67,$L$3:$CF$3,J$3) -> 0 | L67: =SUM(L60:L62,L65) -> 0 | M67: =SUM(M60:M62,M65) -> 0 | N67: =SUM(N60:N62,N65) -> 0 | O67: =SUM(O60:O62,O65) -> 0 | P67: =SUM(P60:P62,P65) -> 0 | Q67: =SUM(Q60:Q62,Q65) -> 0 | R67: =SUM(R60:R62,R65) -> 0 | S67: =SUM(S60:S62,S65) -> 0 | ... CF67: =SUM(CF60:CF62,CF65) -> 0
A69: Total CF from Financing | D69: =SUMIFS($L69:$CF69,$L$3:$CF$3,D$3) -> 37474140 | E69: =SUMIFS($L69:$CF69,$L$3:$CF$3,E$3) -> 6090551.1 | F69: =SUMIFS($L69:$CF69,$L$3:$CF$3,F$3) -> 862668.93 | G69: =SUMIFS($L69:$CF69,$L$3:$CF$3,G$3) -> 2050929.6 | H69: =SUMIFS($L69:$CF69,$L$3:$CF$3,H$3) -> -4682336.3 | I69: =SUMIFS($L69:$CF69,$L$3:$CF$3,I$3) -> -61376274 | J69: =SUMIFS($L69:$CF69,$L$3:$CF$3,J$3) -> 0 | L69: =L67+L54 -> 37474140 | M69: =M67+M54 -> 0 | N69: =N67+N54 -> 123671.18 | O69: =O67+O54 -> 205239.32 | P69: =P67+P54 -> 195221.52 | Q69: =Q67+Q54 -> 291539.96 | R69: =R67+R54 -> 565936.8 | S69: =S67+S54 -> 357823.48 | ... CF69: =CF67+CF54 -> 0
A71: Total Levered Cash Flow | D71: =SUMIFS($L71:$CF71,$L$3:$CF$3,D$3) -> -14025860 | E71: =SUMIFS($L71:$CF71,$L$3:$CF$3,E$3) -> -1803780.8 | F71: =SUMIFS($L71:$CF71,$L$3:$CF$3,F$3) -> 2710189 | G71: =SUMIFS($L71:$CF71,$L$3:$CF$3,G$3) -> 5183777.2 | H71: =SUMIFS($L71:$CF71,$L$3:$CF$3,H$3) -> 347066.07 | I71: =SUMIFS($L71:$CF71,$L$3:$CF$3,I$3) -> 26926389 | J71: =SUMIFS($L71:$CF71,$L$3:$CF$3,J$3) -> 0 | L71: =L34+L69 -> -14025860 | M71: =M34+M69 -> 226402.95 | N71: =N34+N69 -> -41223.726 | O71: =O34+O69 -> -68413.105 | P71: =P34+P69 -> -65073.84 | Q71: =Q34+Q69 -> -97179.986 | R71: =R34+R69 -> -188645.6 | S71: =S34+S69 -> -119274.49 | ... CF71: =CF34+CF69 -> 0
A72: IRR | B72: =XIRR(L71:CF71,$L$5:$CF$5) -> 0.21210951
A73: Required Capital | B73: =-SUMIF(L71:CF71,"<0") -> 17404608
A74: Profit | B74: =SUM(L71:CF71) -> 19337781
A75: MoIC | B75: =B74/B73+1 -> 2.1110725

Sheet CapEx Schedule
A1: RENOVATION TIMELINE - SOUTHPARK CENTRE
A2: Prepared by: Pinnacle Builders Inc.
A3: Date: May 28, 2026 | Revision: 0 | Contract Value: $7,500,000
A4: Assumes close August 1, 2026. Months numbered from close.
A6: Work Item | B6: Budget | C6: Start Month | D6: Duration | E6: 1 | F6: 2 | G6: 3 | H6: 4 | I6: 5 | J6: 6 | K6: 7 | L6: 8 | M6: 9 | N6: 10 | O6: 11 | P6: 12 | Q6: 13 | R6: 14 | S6: 15 | T6: 16 | U6: 17 | V6: 18
A7: COMMON AREA RENOVATION
A8: General Conditions & Mobilization | B8: 365000 | C8: 1 | D8: 18 | E8: =$B8/$D8*(AND(E$6>=$C8,E$6<=$C8+$D8-1)) -> 20277.778 | F8: =$B8/$D8*(AND(F$6>=$C8,F$6<=$C8+$D8-1)) -> 20277.778 | G8: =$B8/$D8*(AND(G$6>=$C8,G$6<=$C8+$D8-1)) -> 20277.778 | H8: =$B8/$D8*(AND(H$6>=$C8,H$6<=$C8+$D8-1)) -> 20277.778 | I8: =$B8/$D8*(AND(I$6>=$C8,I$6<=$C8+$D8-1)) -> 20277.778 | J8: =$B8/$D8*(AND(J$6>=$C8,J$6<=$C8+$D8-1)) -> 20277.778 | K8: =$B8/$D8*(AND(K$6>=$C8,K$6<=$C8+$D8-1)) -> 20277.778 | L8: =$B8/$D8*(AND(L$6>=$C8,L$6<=$C8+$D8-1)) -> 20277.778 | ... V8: =$B8/$D8*(AND(V$6>=$C8,V$6<=$C8+$D8-1)) -> 20277.778 | X8: =IF(SUM(E8:V8)=B8,"OK","ERROR") -> OK
A9: Lobby Demolition | B9: 82500 | C9: 2 | D9: 1 | E9: =$B9/$D9*(AND(E$6>=$C9,E$6<=$C9+$D9-1)) -> 0 | F9: =$B9/$D9*(AND(F$6>=$C9,F$6<=$C9+$D9-1)) -> 82500 | G9: =$B9/$D9*(AND(G$6>=$C9,G$6<=$C9+$D9-1)) -> 0 | H9: =$B9/$D9*(AND(H$6>=$C9,H$6<=$C9+$D9-1)) -> 0 | I9: =$B9/$D9*(AND(I$6>=$C9,I$6<=$C9+$D9-1)) -> 0 | J9: =$B9/$D9*(AND(J$6>=$C9,J$6<=$C9+$D9-1)) -> 0 | K9: =$B9/$D9*(AND(K$6>=$C9,K$6<=$C9+$D9-1)) -> 0 | L9: =$B9/$D9*(AND(L$6>=$C9,L$6<=$C9+$D9-1)) -> 0 | ... V9: =$B9/$D9*(AND(V$6>=$C9,V$6<=$C9+$D9-1)) -> 0 | X9: =IF(SUM(E9:V9)=B9,"OK","ERROR") -> OK
A10: Lobby Renovation (Entrance + Reception) | B10: 300000 | C10: 3 | D10: 8 | E10: =$B10/$D10*(AND(E$6>=$C10,E$6<=$C10+$D10-1)) -> 0 | F10: =$B10/$D10*(AND(F$6>=$C10,F$6<=$C10+$D10-1)) -> 0 | G10: =$B10/$D10*(AND(G$6>=$C10,G$6<=$C10+$D10-1)) -> 37500 | H10: =$B10/$D10*(AND(H$6>=$C10,H$6<=$C10+$D10-1)) -> 37500 | I10: =$B10/$D10*(AND(I$6>=$C10,I$6<=$C10+$D10-1)) -> 37500 | J10: =$B10/$D10*(AND(J$6>=$C10,J$6<=$C10+$D10-1)) -> 37500 | K10: =$B10/$D10*(AND(K$6>=$C10,K$6<=$C10+$D10-1)) -> 37500 | L10: =$B10/$D10*(AND(L$6>=$C10,L$6<=$C10+$D10-1)) -> 37500 | ... V10: =$B10/$D10*(AND(V$6>=$C10,V$6<=$C10+$D10-1)) -> 0 | X10: =IF(SUM(E10:V10)=B10,"OK","ERROR") -> OK
A11: Corridor Refresh - Floor 1 | B11: 60900 | C11: 3 | D11: 2 | E11: =$B11/$D11*(AND(E$6>=$C11,E$6<=$C11+$D11-1)) -> 0 | F11: =$B11/$D11*(AND(F$6>=$C11,F$6<=$C11+$D11-1)) -> 0 | G11: =$B11/$D11*(AND(G$6>=$C11,G$6<=$C11+$D11-1)) -> 30450 | H11: =$B11/$D11*(AND(H$6>=$C11,H$6<=$C11+$D11-1)) -> 30450 | I11: =$B11/$D11*(AND(I$6>=$C11,I$6<=$C11+$D11-1)) -> 0 | J11: =$B11/$D11*(AND(J$6>=$C11,J$6<=$C11+$D11-1)) -> 0 | K11: =$B11/$D11*(AND(K$6>=$C11,K$6<=$C11+$D11-1)) -> 0 | L11: =$B11/$D11*(AND(L$6>=$C11,L$6<=$C11+$D11-1)) -> 0 | ... V11: =$B11/$D11*(AND(V$6>=$C11,V$6<=$C11+$D11-1)) -> 0 | X11: =IF(SUM(E11:V11)=B11,"OK","ERROR") -> OK
A12: Corridor Refresh - Floor 2 | B12: 62300 | C12: 4 | D12: 2 | E12: =$B12/$D12*(AND(E$6>=$C12,E$6<=$C12+$D12-1)) -> 0 | F12: =$B12/$D12*(AND(F$6>=$C12,F$6<=$C12+$D12-1)) -> 0 | G12: =$B12/$D12*(AND(G$6>=$C12,G$6<=$C12+$D12-1)) -> 0 | H12: =$B12/$D12*(AND(H$6>=$C12,H$6<=$C12+$D12-1)) -> 31150 | I12: =$B12/$D12*(AND(I$6>=$C12,I$6<=$C12+$D12-1)) -> 31150 | J12: =$B12/$D12*(AND(J$6>=$C12,J$6<=$C12+$D12-1)) -> 0 | K12: =$B12/$D12*(AND(K$6>=$C12,K$6<=$C12+$D12-1)) -> 0 | L12: =$B12/$D12*(AND(L$6>=$C12,L$6<=$C12+$D12-1)) -> 0 | ... V12: =$B12/$D12*(AND(V$6>=$C12,V$6<=$C12+$D12-1)) -> 0 | X12: =IF(SUM(E12:V12)=B12,"OK","ERROR") -> OK
A13: Corridor Refresh - Floor 3 | B13: 56700 | C13: 5 | D13: 2 | E13: =$B13/$D13*(AND(E$6>=$C13,E$6<=$C13+$D13-1)) -> 0 | F13: =$B13/$D13*(AND(F$6>=$C13,F$6<=$C13+$D13-1)) -> 0 | G13: =$B13/$D13*(AND(G$6>=$C13,G$6<=$C13+$D13-1)) -> 0 | H13: =$B13/$D13*(AND(H$6>=$C13,H$6<=$C13+$D13-1)) -> 0 | I13: =$B13/$D13*(AND(I$6>=$C13,I$6<=$C13+$D13-1)) -> 28350 | J13: =$B13/$D13*(AND(J$6>=$C13,J$6<=$C13+$D13-1)) -> 28350 | K13: =$B13/$D13*(AND(K$6>=$C13,K$6<=$C13+$D13-1)) -> 0 | L13: =$B13/$D13*(AND(L$6>=$C13,L$6<=$C13+$D13-1)) -> 0 | ... V13: =$B13/$D13*(AND(V$6>=$C13,V$6<=$C13+$D13-1)) -> 0 | X13: =IF(SUM(E13:V13)=B13,"OK","ERROR") -> OK
A14: Corridor Refresh - Floor 4 | B14: 60900 | C14: 6 | D14: 2 | E14: =$B14/$D14*(AND(E$6>=$C14,E$6<=$C14+$D14-1)) -> 0 | F14: =$B14/$D14*(AND(F$6>=$C14,F$6<=$C14+$D14-1)) -> 0 | G14: =$B14/$D14*(AND(G$6>=$C14,G$6<=$C14+$D14-1)) -> 0 | H14: =$B14/$D14*(AND(H$6>=$C14,H$6<=$C14+$D14-1)) -> 0 | I14: =$B14/$D14*(AND(I$6>=$C14,I$6<=$C14+$D14-1)) -> 0 | J14: =$B14/$D14*(AND(J$6>=$C14,J$6<=$C14+$D14-1)) -> 30450 | K14: =$B14/$D14*(AND(K$6>=$C14,K$6<=$C14+$D14-1)) -> 30450 | L14: =$B14/$D14*(AND(L$6>=$C14,L$6<=$C14+$D14-1)) -> 0 | ... V14: =$B14/$D14*(AND(V$6>=$C14,V$6<=$C14+$D14-1)) -> 0 | X14: =IF(SUM(E14:V14)=B14,"OK","ERROR") -> OK
A15: Corridor Refresh - Floor 5 | B15: 53200 | C15: 7 | D15: 2 | E15: =$B15/$D15*(AND(E$6>=$C15,E$6<=$C15+$D15-1)) -> 0 | F15: =$B15/$D15*(AND(F$6>=$C15,F$6<=$C15+$D15-1)) -> 0 | G15: =$B15/$D15*(AND(G$6>=$C15,G$6<=$C15+$D15-1)) -> 0 | H15: =$B15/$D15*(AND(H$6>=$C15,H$6<=$C15+$D15-1)) -> 0 | I15: =$B15/$D15*(AND(I$6>=$C15,I$6<=$C15+$D15-1)) -> 0 | J15: =$B15/$D15*(AND(J$6>=$C15,J$6<=$C15+$D15-1)) -> 0 | K15: =$B15/$D15*(AND(K$6>=$C15,K$6<=$C15+$D15-1)) -> 26600 | L15: =$B15/$D15*(AND(L$6>=$C15,L$6<=$C15+$D15-1)) -> 26600 | ... V15: =$B15/$D15*(AND(V$6>=$C15,V$6<=$C15+$D15-1)) -> 0 | X15: =IF(SUM(E15:V15)=B15,"OK","ERROR") -> OK
A16: Restroom Renovation - Floor 1 | B16: 72000 | C16: 3 | D16: 3 | E16: =$B16/$D16*(AND(E$6>=$C16,E$6<=$C16+$D16-1)) -> 0 | F16: =$B16/$D16*(AND(F$6>=$C16,F$6<=$C16+$D16-1)) -> 0 | G16: =$B16/$D16*(AND(G$6>=$C16,G$6<=$C16+$D16-1)) -> 24000 | H16: =$B16/$D16*(AND(H$6>=$C16,H$6<=$C16+$D16-1)) -> 24000 | I16: =$B16/$D16*(AND(I$6>=$C16,I$6<=$C16+$D16-1)) -> 24000 | J16: =$B16/$D16*(AND(J$6>=$C16,J$6<=$C16+$D16-1)) -> 0 | K16: =$B16/$D16*(AND(K$6>=$C16,K$6<=$C16+$D16-1)) -> 0 | L16: =$B16/$D16*(AND(L$6>=$C16,L$6<=$C16+$D16-1)) -> 0 | ... V16: =$B16/$D16*(AND(V$6>=$C16,V$6<=$C16+$D16-1)) -> 0 | X16: =IF(SUM(E16:V16)=B16,"OK","ERROR") -> OK
A17: Restroom Renovation - Floor 2 | B17: 74000 | C17: 5 | D17: 3 | E17: =$B17/$D17*(AND(E$6>=$C17,E$6<=$C17+$D17-1)) -> 0 | F17: =$B17/$D17*(AND(F$6>=$C17,F$6<=$C17+$D17-1)) -> 0 | G17: =$B17/$D17*(AND(G$6>=$C17,G$6<=$C17+$D17-1)) -> 0 | H17: =$B17/$D17*(AND(H$6>=$C17,H$6<=$C17+$D17-1)) -> 0 | I17: =$B17/$D17*(AND(I$6>=$C17,I$6<=$C17+$D17-1)) -> 24666.667 | J17: =$B17/$D17*(AND(J$6>=$C17,J$6<=$C17+$D17-1)) -> 24666.667 | K17: =$B17/$D17*(AND(K$6>=$C17,K$6<=$C17+$D17-1)) -> 24666.667 | L17: =$B17/$D17*(AND(L$6>=$C17,L$6<=$C17+$D17-1)) -> 0 | ... V17: =$B17/$D17*(AND(V$6>=$C17,V$6<=$C17+$D17-1)) -> 0 | X17: =IF(SUM(E17:V17)=B17,"OK","ERROR") -> OK
A18: Restroom Renovation - Floor 3 | B18: 68000 | C18: 7 | D18: 3 | E18: =$B18/$D18*(AND(E$6>=$C18,E$6<=$C18+$D18-1)) -> 0 | F18: =$B18/$D18*(AND(F$6>=$C18,F$6<=$C18+$D18-1)) -> 0 | G18: =$B18/$D18*(AND(G$6>=$C18,G$6<=$C18+$D18-1)) -> 0 | H18: =$B18/$D18*(AND(H$6>=$C18,H$6<=$C18+$D18-1)) -> 0 | I18: =$B18/$D18*(AND(I$6>=$C18,I$6<=$C18+$D18-1)) -> 0 | J18: =$B18/$D18*(AND(J$6>=$C18,J$6<=$C18+$D18-1)) -> 0 | K18: =$B18/$D18*(AND(K$6>=$C18,K$6<=$C18+$D18-1)) -> 22666.667 | L18: =$B18/$D18*(AND(L$6>=$C18,L$6<=$C18+$D18-1)) -> 22666.667 | ... V18: =$B18/$D18*(AND(V$6>=$C18,V$6<=$C18+$D18-1)) -> 0 | X18: =IF(SUM(E18:V18)=B18,"OK","ERROR") -> OK
A19: Restroom Renovation - Floor 4 | B19: 72000 | C19: 9 | D19: 3 | E19: =$B19/$D19*(AND(E$6>=$C19,E$6<=$C19+$D19-1)) -> 0 | F19: =$B19/$D19*(AND(F$6>=$C19,F$6<=$C19+$D19-1)) -> 0 | G19: =$B19/$D19*(AND(G$6>=$C19,G$6<=$C19+$D19-1)) -> 0 | H19: =$B19/$D19*(AND(H$6>=$C19,H$6<=$C19+$D19-1)) -> 0 | I19: =$B19/$D19*(AND(I$6>=$C19,I$6<=$C19+$D19-1)) -> 0 | J19: =$B19/$D19*(AND(J$6>=$C19,J$6<=$C19+$D19-1)) -> 0 | K19: =$B19/$D19*(AND(K$6>=$C19,K$6<=$C19+$D19-1)) -> 0 | L19: =$B19/$D19*(AND(L$6>=$C19,L$6<=$C19+$D19-1)) -> 0 | ... V19: =$B19/$D19*(AND(V$6>=$C19,V$6<=$C19+$D19-1)) -> 0 | X19: =IF(SUM(E19:V19)=B19,"OK","ERROR") -> OK
... A23: Punch List & Closeout - Common Areas | B23: 0 | C23: 14 | D23: 2 | E23: =$B23/$D23*(AND(E$6>=$C23,E$6<=$C23+$D23-1)) -> 0 | F23: =$B23/$D23*(AND(F$6>=$C23,F$6<=$C23+$D23-1)) -> 0 | G23: =$B23/$D23*(AND(G$6>=$C23,G$6<=$C23+$D23-1)) -> 0 | H23: =$B23/$D23*(AND(H$6>=$C23,H$6<=$C23+$D23-1)) -> 0 | I23: =$B23/$D23*(AND(I$6>=$C23,I$6<=$C23+$D23-1)) -> 0 | J23: =$B23/$D23*(AND(J$6>=$C23,J$6<=$C23+$D23-1)) -> 0 | K23: =$B23/$D23*(AND(K$6>=$C23,K$6<=$C23+$D23-1)) -> 0 | L23: =$B23/$D23*(AND(L$6>=$C23,L$6<=$C23+$D23-1)) -> 0 | ... V23: =$B23/$D23*(AND(V$6>=$C23,V$6<=$C23+$D23-1)) -> 0 | X23: =IF(SUM(E23:V23)=B23,"OK","ERROR") -> OK
A25: SPEC SUITE BUILDOUT (MERIDIAN FLOORS)
A26: Suite 610 (14,000 SF) - Floor 6 | B26: 910000 | C26: 6 | D26: 6 | E26: =$B26/$D26*(AND(E$6>=$C26,E$6<=$C26+$D26-1)) -> 0 | F26: =$B26/$D26*(AND(F$6>=$C26,F$6<=$C26+$D26-1)) -> 0 | G26: =$B26/$D26*(AND(G$6>=$C26,G$6<=$C26+$D26-1)) -> 0 | H26: =$B26/$D26*(AND(H$6>=$C26,H$6<=$C26+$D26-1)) -> 0 | I26: =$B26/$D26*(AND(I$6>=$C26,I$6<=$C26+$D26-1)) -> 0 | J26: =$B26/$D26*(AND(J$6>=$C26,J$6<=$C26+$D26-1)) -> 151666.67 | K26: =$B26/$D26*(AND(K$6>=$C26,K$6<=$C26+$D26-1)) -> 151666.67 | L26: =$B26/$D26*(AND(L$6>=$C26,L$6<=$C26+$D26-1)) -> 151666.67 | ... V26: =$B26/$D26*(AND(V$6>=$C26,V$6<=$C26+$D26-1)) -> 0 | X26: =IF(SUM(E26:V26)=B26,"OK","ERROR") -> OK
A27: Suite 620 (13,000 SF) - Floor 6 | B27: 845000 | C27: 6 | D27: 6 | E27: =$B27/$D27*(AND(E$6>=$C27,E$6<=$C27+$D27-1)) -> 0 | F27: =$B27/$D27*(AND(F$6>=$C27,F$6<=$C27+$D27-1)) -> 0 | G27: =$B27/$D27*(AND(G$6>=$C27,G$6<=$C27+$D27-1)) -> 0 | H27: =$B27/$D27*(AND(H$6>=$C27,H$6<=$C27+$D27-1)) -> 0 | I27: =$B27/$D27*(AND(I$6>=$C27,I$6<=$C27+$D27-1)) -> 0 | J27: =$B27/$D27*(AND(J$6>=$C27,J$6<=$C27+$D27-1)) -> 140833.33 | K27: =$B27/$D27*(AND(K$6>=$C27,K$6<=$C27+$D27-1)) -> 140833.33 | L27: =$B27/$D27*(AND(L$6>=$C27,L$6<=$C27+$D27-1)) -> 140833.33 | ... V27: =$B27/$D27*(AND(V$6>=$C27,V$6<=$C27+$D27-1)) -> 0 | X27: =IF(SUM(E27:V27)=B27,"OK","ERROR") -> OK
A28: Suite 710 (13,000 SF) - Floor 7 | B28: 845000 | C28: 8 | D28: 6 | E28: =$B28/$D28*(AND(E$6>=$C28,E$6<=$C28+$D28-1)) -> 0 | F28: =$B28/$D28*(AND(F$6>=$C28,F$6<=$C28+$D28-1)) -> 0 | G28: =$B28/$D28*(AND(G$6>=$C28,G$6<=$C28+$D28-1)) -> 0 | H28: =$B28/$D28*(AND(H$6>=$C28,H$6<=$C28+$D28-1)) -> 0 | I28: =$B28/$D28*(AND(I$6>=$C28,I$6<=$C28+$D28-1)) -> 0 | J28: =$B28/$D28*(AND(J$6>=$C28,J$6<=$C28+$D28-1)) -> 0 | K28: =$B28/$D28*(AND(K$6>=$C28,K$6<=$C28+$D28-1)) -> 0 | L28: =$B28/$D28*(AND(L$6>=$C28,L$6<=$C28+$D28-1)) -> 140833.33 | ... V28: =$B28/$D28*(AND(V$6>=$C28,V$6<=$C28+$D28-1)) -> 0 | X28: =IF(SUM(E28:V28)=B28,"OK","ERROR") -> OK
A29: Suite 720 (12,000 SF) - Floor 7 | B29: 780000 | C29: 8 | D29: 6 | E29: =$B29/$D29*(AND(E$6>=$C29,E$6<=$C29+$D29-1)) -> 0 | F29: =$B29/$D29*(AND(F$6>=$C29,F$6<=$C29+$D29-1)) -> 0 | G29: =$B29/$D29*(AND(G$6>=$C29,G$6<=$C29+$D29-1)) -> 0 | H29: =$B29/$D29*(AND(H$6>=$C29,H$6<=$C29+$D29-1)) -> 0 | I29: =$B29/$D29*(AND(I$6>=$C29,I$6<=$C29+$D29-1)) -> 0 | J29: =$B29/$D29*(AND(J$6>=$C29,J$6<=$C29+$D29-1)) -> 0 | K29: =$B29/$D29*(AND(K$6>=$C29,K$6<=$C29+$D29-1)) -> 0 | L29: =$B29/$D29*(AND(L$6>=$C29,L$6<=$C29+$D29-1)) -> 130000 | ... V29: =$B29/$D29*(AND(V$6>=$C29,V$6<=$C29+$D29-1)) -> 0 | X29: =IF(SUM(E29:V29)=B29,"OK","ERROR") -> OK
A30: Suite 810 (12,500 SF) - Floor 8 | B30: 812500 | C30: 10 | D30: 6 | E30: =$B30/$D30*(AND(E$6>=$C30,E$6<=$C30+$D30-1)) -> 0 | F30: =$B30/$D30*(AND(F$6>=$C30,F$6<=$C30+$D30-1)) -> 0 | G30: =$B30/$D30*(AND(G$6>=$C30,G$6<=$C30+$D30-1)) -> 0 | H30: =$B30/$D30*(AND(H$6>=$C30,H$6<=$C30+$D30-1)) -> 0 | I30: =$B30/$D30*(AND(I$6>=$C30,I$6<=$C30+$D30-1)) -> 0 | J30: =$B30/$D30*(AND(J$6>=$C30,J$6<=$C30+$D30-1)) -> 0 | K30: =$B30/$D30*(AND(K$6>=$C30,K$6<=$C30+$D30-1)) -> 0 | L30: =$B30/$D30*(AND(L$6>=$C30,L$6<=$C30+$D30-1)) -> 0 | ... V30: =$B30/$D30*(AND(V$6>=$C30,V$6<=$C30+$D30-1)) -> 0 | X30: =IF(SUM(E30:V30)=B30,"OK","ERROR") -> OK
A31: Suite 820 (11,500 SF) - Floor 8 | B31: 747500 | C31: 10 | D31: 6 | E31: =$B31/$D31*(AND(E$6>=$C31,E$6<=$C31+$D31-1)) -> 0 | F31: =$B31/$D31*(AND(F$6>=$C31,F$6<=$C31+$D31-1)) -> 0 | G31: =$B31/$D31*(AND(G$6>=$C31,G$6<=$C31+$D31-1)) -> 0 | H31: =$B31/$D31*(AND(H$6>=$C31,H$6<=$C31+$D31-1)) -> 0 | I31: =$B31/$D31*(AND(I$6>=$C31,I$6<=$C31+$D31-1)) -> 0 | J31: =$B31/$D31*(AND(J$6>=$C31,J$6<=$C31+$D31-1)) -> 0 | K31: =$B31/$D31*(AND(K$6>=$C31,K$6<=$C31+$D31-1)) -> 0 | L31: =$B31/$D31*(AND(L$6>=$C31,L$6<=$C31+$D31-1)) -> 0 | ... V31: =$B31/$D31*(AND(V$6>=$C31,V$6<=$C31+$D31-1)) -> 0 | X31: =IF(SUM(E31:V31)=B31,"OK","ERROR") -> OK
A32: Punch List & Closeout - Spec Suites | B32: 0 | C32: 11 | D32: 1 | E32: =$B32/$D32*(AND(E$6>=$C32,E$6<=$C32+$D32-1)) -> 0 | F32: =$B32/$D32*(AND(F$6>=$C32,F$6<=$C32+$D32-1)) -> 0 | G32: =$B32/$D32*(AND(G$6>=$C32,G$6<=$C32+$D32-1)) -> 0 | H32: =$B32/$D32*(AND(H$6>=$C32,H$6<=$C32+$D32-1)) -> 0 | I32: =$B32/$D32*(AND(I$6>=$C32,I$6<=$C32+$D32-1)) -> 0 | J32: =$B32/$D32*(AND(J$6>=$C32,J$6<=$C32+$D32-1)) -> 0 | K32: =$B32/$D32*(AND(K$6>=$C32,K$6<=$C32+$D32-1)) -> 0 | L32: =$B32/$D32*(AND(L$6>=$C32,L$6<=$C32+$D32-1)) -> 0 | ... V32: =$B32/$D32*(AND(V$6>=$C32,V$6<=$C32+$D32-1)) -> 0 | X32: =IF(SUM(E32:V32)=B32,"OK","ERROR") -> OK
A34: INDIRECT COSTS
A35: Soft Costs (A&E, Permits, CM Fee) | B35: 495000 | C35: 1 | D35: 16 | E35: =$B35/$D35*(AND(E$6>=$C35,E$6<=$C35+$D35-1)) -> 30937.5 | F35: =$B35/$D35*(AND(F$6>=$C35,F$6<=$C35+$D35-1)) -> 30937.5 | G35: =$B35/$D35*(AND(G$6>=$C35,G$6<=$C35+$D35-1)) -> 30937.5 | H35: =$B35/$D35*(AND(H$6>=$C35,H$6<=$C35+$D35-1)) -> 30937.5 | I35: =$B35/$D35*(AND(I$6>=$C35,I$6<=$C35+$D35-1)) -> 30937.5 | J35: =$B35/$D35*(AND(J$6>=$C35,J$6<=$C35+$D35-1)) -> 30937.5 | K35: =$B35/$D35*(AND(K$6>=$C35,K$6<=$C35+$D35-1)) -> 30937.5 | L35: =$B35/$D35*(AND(L$6>=$C35,L$6<=$C35+$D35-1)) -> 30937.5 | ... V35: =$B35/$D35*(AND(V$6>=$C35,V$6<=$C35+$D35-1)) -> 0 | X35: =IF(SUM(E35:V35)=B35,"OK","ERROR") -> OK
A36: Contingency (~7% of hard costs) | B36: 434500 | C36: 1 | D36: 18 | E36: =$B36/$D36*(AND(E$6>=$C36,E$6<=$C36+$D36-1)) -> 24138.889 | F36: =$B36/$D36*(AND(F$6>=$C36,F$6<=$C36+$D36-1)) -> 24138.889 | G36: =$B36/$D36*(AND(G$6>=$C36,G$6<=$C36+$D36-1)) -> 24138.889 | H36: =$B36/$D36*(AND(H$6>=$C36,H$6<=$C36+$D36-1)) -> 24138.889 | I36: =$B36/$D36*(AND(I$6>=$C36,I$6<=$C36+$D36-1)) -> 24138.889 | J36: =$B36/$D36*(AND(J$6>=$C36,J$6<=$C36+$D36-1)) -> 24138.889 | K36: =$B36/$D36*(AND(K$6>=$C36,K$6<=$C36+$D36-1)) -> 24138.889 | L36: =$B36/$D36*(AND(L$6>=$C36,L$6<=$C36+$D36-1)) -> 24138.889 | ... V36: =$B36/$D36*(AND(V$6>=$C36,V$6<=$C36+$D36-1)) -> 24138.889 | X36: =IF(SUM(E36:V36)=B36,"OK","ERROR") -> OK
A38: CapEx Sensitivity | B38: =RenoDuration -> 0 | E38: =SUM(E8:E23,E26:E32,E35:E36)*$B38 -> 0 | F38: =SUM(F8:F23,F26:F32,F35:F36)*$B38 -> 0 | G38: =SUM(G8:G23,G26:G32,G35:G36)*$B38 -> 0 | H38: =SUM(H8:H23,H26:H32,H35:H36)*$B38 -> 0 | I38: =SUM(I8:I23,I26:I32,I35:I36)*$B38 -> 0 | J38: =SUM(J8:J23,J26:J32,J35:J36)*$B38 -> 0 | K38: =SUM(K8:K23,K26:K32,K35:K36)*$B38 -> 0 | L38: =SUM(L8:L23,L26:L32,L35:L36)*$B38 -> 0 | ... V38: =SUM(V8:V23,V26:V32,V35:V36)*$B38 -> 0
A39: Total CapEx | B39: =SUM(E39:V39) -> 7500000 | E39: =SUM(E8:E23,E26:E38) -> 75354.167 | F39: =SUM(F8:F23,F26:F38) -> 157854.17 | G39: =SUM(G8:G23,G26:G38) -> 167304.17 | H39: =SUM(H8:H23,H26:H38) -> 198454.17 | I39: =SUM(I8:I23,I26:I38) -> 221020.83 | J39: =SUM(J8:J23,J26:J38) -> 488820.83 | K39: =SUM(K8:K23,K26:K38) -> 509737.5 | L39: =SUM(L8:L23,L26:L38) -> 725454.17 | ... V39: =SUM(V8:V23,V26:V38) -> 44416.667 | X39: =IF(SUM(E39:V39)=B39,"OK","ERROR") -> OK
A42: NOTES
A43: 1. Spec suite buildout at $65/SF per James Whitfield's site assessment (Email 5, May 31).
A44: 2. Floor 6 spec suites assume access beginning Month 4 (Meridian lease expires Oct 31, 2026).
A45: 3. Floors 7 and 8 phased at 2-month intervals to manage subcontractor scheduling.
A46: 4. Common area renovation and spec suites run in parallel where possible.
A47: 5. TI allowance for spec suites not included herein
A48: 6. Budget excludes ongoing tenant TI/LC for existing tenant rollovers (separate line in operating budget).
A49: 7. Contingency of 5% included in line items. No separate contingency line.

Sheet Waterfall
A1: SouthPark Centre — JV Equity Waterfall
A2: GP 10% / LP 90% · 8% pref (effective annual, monthly compounding) · 50/50 catch-up to 20% GP profit share · 80/20 LP/GP residual
A3: Year # | D3: ='Property Cash Flow'!L3 -> 0 | E3: ='Property Cash Flow'!M3 -> 1 | F3: ='Property Cash Flow'!N3 -> 1 | G3: ='Property Cash Flow'!O3 -> 1 | H3: ='Property Cash Flow'!P3 -> 1 | I3: ='Property Cash Flow'!Q3 -> 1 | J3: ='Property Cash Flow'!R3 -> 1 | K3: ='Property Cash Flow'!S3 -> 1 | ... BL3: ='Property Cash Flow'!BT3 -> 5
A4: Month # | D4: ='Property Cash Flow'!L4 -> 0 | E4: ='Property Cash Flow'!M4 -> 1 | F4: ='Property Cash Flow'!N4 -> 2 | G4: ='Property Cash Flow'!O4 -> 3 | H4: ='Property Cash Flow'!P4 -> 4 | I4: ='Property Cash Flow'!Q4 -> 5 | J4: ='Property Cash Flow'!R4 -> 6 | K4: ='Property Cash Flow'!S4 -> 7 | ... BL4: ='Property Cash Flow'!BT4 -> 60
A5: Period End | D5: ='Property Cash Flow'!L5 -> 46265 | E5: ='Property Cash Flow'!M5 -> 46295 | F5: ='Property Cash Flow'!N5 -> 46326 | G5: ='Property Cash Flow'!O5 -> 46356 | H5: ='Property Cash Flow'!P5 -> 46387 | I5: ='Property Cash Flow'!Q5 -> 46418 | J5: ='Property Cash Flow'!R5 -> 46446 | K5: ='Property Cash Flow'!S5 -> 46477 | ... BL5: ='Property Cash Flow'!BT5 -> 48091
A7: DEAL CASH FLOW
A8: Levered Cash Flow (Property CF) | D8: ='Property Cash Flow'!L71 -> -14025860 | E8: ='Property Cash Flow'!M71 -> 226402.95 | F8: ='Property Cash Flow'!N71 -> -41223.726 | G8: ='Property Cash Flow'!O71 -> -68413.105 | H8: ='Property Cash Flow'!P71 -> -65073.84 | I8: ='Property Cash Flow'!Q71 -> -97179.986 | J8: ='Property Cash Flow'!R71 -> -188645.6 | K8: ='Property Cash Flow'!S71 -> -119274.49 | ... BL8: ='Property Cash Flow'!BT71 -> 26199165
A9: Capital Call — Total Equity | D9: =MAX(0,-D8) -> 14025860 | E9: =MAX(0,-E8) -> 0 | F9: =MAX(0,-F8) -> 41223.726 | G9: =MAX(0,-G8) -> 68413.105 | H9: =MAX(0,-H8) -> 65073.84 | I9: =MAX(0,-I8) -> 97179.986 | J9: =MAX(0,-J8) -> 188645.6 | K9: =MAX(0,-K8) -> 119274.49 | ... BL9: =MAX(0,-BL8) -> 0
A10: Available for Distribution | D10: =MAX(0,D8) -> 0 | E10: =MAX(0,E8) -> 226402.95 | F10: =MAX(0,F8) -> 0 | G10: =MAX(0,G8) -> 0 | H10: =MAX(0,H8) -> 0 | I10: =MAX(0,I8) -> 0 | J10: =MAX(0,J8) -> 0 | K10: =MAX(0,K8) -> 0 | ... BL10: =MAX(0,BL8) -> 26199165
A12: CAPITAL CONTRIBUTIONS
A13: LP Contribution | D13: =D9*LPShare -> 12623274 | E13: =E9*LPShare -> 0 | F13: =F9*LPShare -> 37101.353 | G13: =G9*LPShare -> 61571.795 | H13: =H9*LPShare -> 58566.456 | I13: =I9*LPShare -> 87461.988 | J13: =J9*LPShare -> 169781.04 | K13: =K9*LPShare -> 107347.04 | ... BL13: =BL9*LPShare -> 0
A14: GP Contribution | D14: =D9*GPShare -> 1402586 | E14: =E9*GPShare -> 0 | F14: =F9*GPShare -> 4122.3726 | G14: =G9*GPShare -> 6841.3105 | H14: =H9*GPShare -> 6507.384 | I14: =I9*GPShare -> 9717.9986 | J14: =J9*GPShare -> 18864.56 | K14: =K9*GPShare -> 11927.449 | ... BL14: =BL9*GPShare -> 0
A15: Cumulative Called — Total | D15: =SUM($D$9:D9) -> 14025860 | E15: =SUM($D$9:E9) -> 14025860 | F15: =SUM($D$9:F9) -> 14067084 | G15: =SUM($D$9:G9) -> 14135497 | H15: =SUM($D$9:H9) -> 14200571 | I15: =SUM($D$9:I9) -> 14297751 | J15: =SUM($D$9:J9) -> 14486396 | K15: =SUM($D$9:K9) -> 14605671 | ... BL15: =SUM($D$9:BL9) -> 17404608
A16: Cumulative Called — LP | D16: =SUM($D$13:D13) -> 12623274 | E16: =SUM($D$13:E13) -> 12623274 | F16: =SUM($D$13:F13) -> 12660375 | G16: =SUM($D$13:G13) -> 12721947 | H16: =SUM($D$13:H13) -> 12780513 | I16: =SUM($D$13:I13) -> 12867975 | J16: =SUM($D$13:J13) -> 13037756 | K16: =SUM($D$13:K13) -> 13145104 | ... BL16: =SUM($D$13:BL13) -> 15664147
A17: Cumulative Called — GP | D17: =SUM($D$14:D14) -> 1402586 | E17: =SUM($D$14:E14) -> 1402586 | F17: =SUM($D$14:F14) -> 1406708.4 | G17: =SUM($D$14:G14) -> 1413549.7 | H17: =SUM($D$14:H14) -> 1420057.1 | I17: =SUM($D$14:I14) -> 1429775.1 | J17: =SUM($D$14:J14) -> 1448639.6 | K17: =SUM($D$14:K14) -> 1460567.1 | ... BL17: =SUM($D$14:BL14) -> 1740460.8
A19: LP LEDGER
A20: BoP Unreturned Capital | D20: =C23 -> 0 | E20: =D23 -> 12623274 | F20: =E23 -> 12487114 | G20: =F23 -> 12524215 | H20: =G23 -> 12585787 | I20: =H23 -> 12644353 | J20: =I23 -> 12731815 | K20: =J23 -> 12901596 | ... BL20: =BK23 -> 10425821
A21: (+) Contributions | D21: =D13 -> 12623274 | E21: =E13 -> 0 | F21: =F13 -> 37101.353 | G21: =G13 -> 61571.795 | H21: =H13 -> 58566.456 | I21: =I13 -> 87461.988 | J21: =J13 -> 169781.04 | K21: =K13 -> 107347.04 | ... BL21: =BL13 -> 0
A22: (−) Return of Capital | D22: =-D44 -> 0 | E22: =-E44 -> -136160.14 | F22: =-F44 -> 0 | G22: =-G44 -> 0 | H22: =-H44 -> 0 | I22: =-I44 -> 0 | J22: =-J44 -> 0 | K22: =-K44 -> 0 | ... BL22: =-BL44 -> -10425821
A23: EoP Unreturned Capital | D23: =SUM(D20:D22) -> 12623274 | E23: =SUM(E20:E22) -> 12487114 | F23: =SUM(F20:F22) -> 12524215 | G23: =SUM(G20:G22) -> 12585787 | H23: =SUM(H20:H22) -> 12644353 | I23: =SUM(I20:I22) -> 12731815 | J23: =SUM(J20:J22) -> 12901596 | K23: =SUM(K20:K22) -> 13008943 | ... BL23: =SUM(BL20:BL22) -> 0
A24: BoP Accrued Unpaid Pref | D24: =C27 -> 0 | E24: =D27 -> 0 | F24: =E27 -> 0 | G24: =F27 -> 80342.466 | H24: =G27 -> 161440.57 | I24: =H27 -> 243456.61 | J24: =I27 -> 326377.17 | K24: =J27 -> 410393.97 | ... BL24: =BK27 -> 0
A25: (+) Pref Accrual | D25: =(D20+D24)*PrefMo -> 0 | E25: =(E20+E24)*PrefMo -> 81218.524 | F25: =(F20+F24)*PrefMo -> 80342.466 | G25: =(G20+G24)*PrefMo -> 81098.103 | H25: =(H20+H24)*PrefMo -> 82016.045 | I25: =(I20+I24)*PrefMo -> 82920.557 | J25: =(J20+J24)*PrefMo -> 84016.804 | K25: =(K20+K24)*PrefMo -> 85649.747 | ... BL25: =(BL20+BL24)*PrefMo -> 67080.043
A26: (−) Pref Distributions | D26: =-D40 -> 0 | E26: =-E40 -> -81218.524 | F26: =-F40 -> 0 | G26: =-G40 -> 0 | H26: =-H40 -> 0 | I26: =-I40 -> 0 | J26: =-J40 -> 0 | K26: =-K40 -> 0 | ... BL26: =-BL40 -> -67080.043
A27: EoP Accrued Unpaid Pref | D27: =SUM(D24:D26) -> 0 | E27: =SUM(E24:E26) -> 0 | F27: =SUM(F24:F26) -> 80342.466 | G27: =SUM(G24:G26) -> 161440.57 | H27: =SUM(H24:H26) -> 243456.61 | I27: =SUM(I24:I26) -> 326377.17 | J27: =SUM(J24:J26) -> 410393.97 | K27: =SUM(K24:K26) -> 496043.72 | ... BL27: =SUM(BL24:BL26) -> 0
A29: GP LEDGER
A30: BoP Unreturned Capital | D30: =C33 -> 0 | E30: =D33 -> 1402586 | F30: =E33 -> 1402586 | G30: =F33 -> 1406708.4 | H30: =G33 -> 1413549.7 | I30: =H33 -> 1420057.1 | J30: =I33 -> 1429775.1 | K30: =J33 -> 1448639.6 | ... BL30: =BK33 -> 1740460.8
A31: (+) Contributions | D31: =D14 -> 1402586 | E31: =E14 -> 0 | F31: =F14 -> 4122.3726 | G31: =G14 -> 6841.3105 | H31: =H14 -> 6507.384 | I31: =I14 -> 9717.9986 | J31: =J14 -> 18864.56 | K31: =K14 -> 11927.449 | ... BL31: =BL14 -> 0
A32: (−) Return of Capital | D32: =-D46 -> 0 | E32: =-E46 -> 0 | F32: =-F46 -> 0 | G32: =-G46 -> 0 | H32: =-H46 -> 0 | I32: =-I46 -> 0 | J32: =-J46 -> 0 | K32: =-K46 -> 0 | ... BL32: =-BL46 -> -1740460.8
A33: EoP Unreturned Capital | D33: =SUM(D30:D32) -> 1402586 | E33: =SUM(E30:E32) -> 1402586 | F33: =SUM(F30:F32) -> 1406708.4 | G33: =SUM(G30:G32) -> 1413549.7 | H33: =SUM(H30:H32) -> 1420057.1 | I33: =SUM(I30:I32) -> 1429775.1 | J33: =SUM(J30:J32) -> 1448639.6 | K33: =SUM(K30:K32) -> 1460567.1 | ... BL33: =SUM(BL30:BL32) -> 0
A34: BoP Accrued Unpaid Pref | D34: =C37 -> 0 | E34: =D37 -> 0 | F34: =E37 -> 0 | G34: =F37 -> 9024.2805 | H34: =G37 -> 18133.147 | I34: =H37 -> 27344.637 | J34: =I37 -> 36657.263 | K34: =J37 -> 46092.333 | ... BL34: =BK37 -> 0
A35: (+) Pref Accrual | D35: =(D30+D34)*PrefMo -> 0 | E35: =(E30+E34)*PrefMo -> 9024.2805 | F35: =(F30+F34)*PrefMo -> 9024.2805 | G35: =(G30+G34)*PrefMo -> 9108.8664 | H35: =(H30+H34)*PrefMo -> 9211.4903 | I35: =(I30+I34)*PrefMo -> 9312.6261 | J35: =(J30+J34)*PrefMo -> 9435.0697 | K35: =(K30+K34)*PrefMo -> 9617.1503 | ... BL35: =(BL30+BL34)*PrefMo -> 11198.177
A36: (−) Pref Distributions | D36: =-D42 -> 0 | E36: =-E42 -> -9024.2805 | F36: =-F42 -> 0 | G36: =-G42 -> 0 | H36: =-H42 -> 0 | I36: =-I42 -> 0 | J36: =-J42 -> 0 | K36: =-K42 -> 0 | ... BL36: =-BL42 -> -11198.177
A37: EoP Accrued Unpaid Pref | D37: =SUM(D34:D36) -> 0 | E37: =SUM(E34:E36) -> 0 | F37: =SUM(F34:F36) -> 9024.2805 | G37: =SUM(G34:G36) -> 18133.147 | H37: =SUM(H34:H36) -> 27344.637 | I37: =SUM(I34:I36) -> 36657.263 | J37: =SUM(J34:J36) -> 46092.333 | K37: =SUM(K34:K36) -> 55709.483 | ... BL37: =SUM(BL34:BL36) -> 0
A39: DISTRIBUTION WATERFALL
A40: Tier 1 — LP Pref | D40: =MIN(D10,D24+D25) -> 0 | E40: =MIN(E10,E24+E25) -> 81218.524 | F40: =MIN(F10,F24+F25) -> 0 | G40: =MIN(G10,G24+G25) -> 0 | H40: =MIN(H10,H24+H25) -> 0 | I40: =MIN(I10,I24+I25) -> 0 | J40: =MIN(J10,J24+J25) -> 0 | K40: =MIN(K10,K24+K25) -> 0 | ... BL40: =MIN(BL10,BL24+BL25) -> 67080.043
A41: Remaining after Tier 1 | D41: =D10-D40 -> 0 | E41: =E10-E40 -> 145184.42 | F41: =F10-F40 -> 0 | G41: =G10-G40 -> 0 | H41: =H10-H40 -> 0 | I41: =I10-I40 -> 0 | J41: =J10-J40 -> 0 | K41: =K10-K40 -> 0 | ... BL41: =BL10-BL40 -> 26132085
A42: Tier 2 — GP Pref | D42: =MIN(D41,D34+D35) -> 0 | E42: =MIN(E41,E34+E35) -> 9024.2805 | F42: =MIN(F41,F34+F35) -> 0 | G42: =MIN(G41,G34+G35) -> 0 | H42: =MIN(H41,H34+H35) -> 0 | I42: =MIN(I41,I34+I35) -> 0 | J42: =MIN(J41,J34+J35) -> 0 | K42: =MIN(K41,K34+K35) -> 0 | ... BL42: =MIN(BL41,BL34+BL35) -> 11198.177
A43: Remaining after Tier 2 | D43: =D41-D42 -> 0 | E43: =E41-E42 -> 136160.14 | F43: =F41-F42 -> 0 | G43: =G41-G42 -> 0 | H43: =H41-H42 -> 0 | I43: =I41-I42 -> 0 | J43: =J41-J42 -> 0 | K43: =K41-K42 -> 0 | ... BL43: =BL41-BL42 -> 26120887
A44: Tier 3 — LP Return of Capital | D44: =MIN(D43,D20+D21) -> 0 | E44: =MIN(E43,E20+E21) -> 136160.14 | F44: =MIN(F43,F20+F21) -> 0 | G44: =MIN(G43,G20+G21) -> 0 | H44: =MIN(H43,H20+H21) -> 0 | I44: =MIN(I43,I20+I21) -> 0 | J44: =MIN(J43,J20+J21) -> 0 | K44: =MIN(K43,K20+K21) -> 0 | ... BL44: =MIN(BL43,BL20+BL21) -> 10425821
A45: Remaining after Tier 3 | D45: =D43-D44 -> 0 | E45: =E43-E44 -> 0 | F45: =F43-F44 -> 0 | G45: =G43-G44 -> 0 | H45: =H43-H44 -> 0 | I45: =I43-I44 -> 0 | J45: =J43-J44 -> 0 | K45: =K43-K44 -> 0 | ... BL45: =BL43-BL44 -> 15695066
A46: Tier 4 — GP Return of Capital | D46: =MIN(D45,D30+D31) -> 0 | E46: =MIN(E45,E30+E31) -> 0 | F46: =MIN(F45,F30+F31) -> 0 | G46: =MIN(G45,G30+G31) -> 0 | H46: =MIN(H45,H30+H31) -> 0 | I46: =MIN(I45,I30+I31) -> 0 | J46: =MIN(J45,J30+J31) -> 0 | K46: =MIN(K45,K30+K31) -> 0 | ... BL46: =MIN(BL45,BL30+BL31) -> 1740460.8
A47: Remaining after Tier 4 | D47: =D45-D46 -> 0 | E47: =E45-E46 -> 0 | F47: =F45-F46 -> 0 | G47: =G45-G46 -> 0 | H47: =H45-H46 -> 0 | I47: =I45-I46 -> 0 | J47: =J45-J46 -> 0 | K47: =K45-K46 -> 0 | ... BL47: =BL45-BL46 -> 13954605
A48: Cum LP Profit incl. this month's pref | D48: =C59+D40 -> 0 | E48: =D59+E40 -> 81218.524 | F48: =E59+F40 -> 81218.524 | G48: =F59+G40 -> 81218.524 | H48: =G59+H40 -> 81218.524 | I48: =H59+I40 -> 81218.524 | J48: =I59+J40 -> 81218.524 | K48: =J59+K40 -> 81218.524 | ... BL48: =BK59+BL40 -> 4741527.6
A49: Cum GP Profit incl. this month's pref | D49: =C60+D42 -> 0 | E49: =D60+E42 -> 9024.2805 | F49: =E60+F42 -> 9024.2805 | G49: =F60+G42 -> 9024.2805 | H49: =G60+H42 -> 9024.2805 | I49: =H60+I42 -> 9024.2805 | J49: =I60+J42 -> 9024.2805 | K49: =J60+K42 -> 9024.2805 | ... BL49: =BK60+BL42 -> 641647.76
A50: Required Catch-up | D50: =MAX(0,(GPTarget*D48-(1-GPTarget)*D49)/(CatchupGP-GPTarget)) -> 0 | E50: =MAX(0,(GPTarget*E48-(1-GPTarget)*E49)/(CatchupGP-GPTarget)) -> 30080.935 | F50: =MAX(0,(GPTarget*F48-(1-GPTarget)*F49)/(CatchupGP-GPTarget)) -> 30080.935 | G50: =MAX(0,(GPTarget*G48-(1-GPTarget)*G49)/(CatchupGP-GPTarget)) -> 30080.935 | H50: =MAX(0,(GPTarget*H48-(1-GPTarget)*H49)/(CatchupGP-GPTarget)) -> 30080.935 | I50: =MAX(0,(GPTarget*I48-(1-GPTarget)*I49)/(CatchupGP-GPTarget)) -> 30080.935 | J50: =MAX(0,(GPTarget*J48-(1-GPTarget)*J49)/(CatchupGP-GPTarget)) -> 30080.935 | K50: =MAX(0,(GPTarget*K48-(1-GPTarget)*K49)/(CatchupGP-GPTarget)) -> 30080.935 | ... BL50: =MAX(0,(GPTarget*BL48-(1-GPTarget)*BL49)/(CatchupGP-GPTarget)) -> 1449957.7
A51: Tier 5 — Catch-up Paid | D51: =MIN(D47,D50) -> 0 | E51: =MIN(E47,E50) -> 0 | F51: =MIN(F47,F50) -> 0 | G51: =MIN(G47,G50) -> 0 | H51: =MIN(H47,H50) -> 0 | I51: =MIN(I47,I50) -> 0 | J51: =MIN(J47,J50) -> 0 | K51: =MIN(K47,K50) -> 0 | ... BL51: =MIN(BL47,BL50) -> 1449957.7
A52: of which GP | D52: =D51*CatchupGP -> 0 | E52: =E51*CatchupGP -> 0 | F52: =F51*CatchupGP -> 0 | G52: =G51*CatchupGP -> 0 | H52: =H51*CatchupGP -> 0 | I52: =I51*CatchupGP -> 0 | J52: =J51*CatchupGP -> 0 | K52: =K51*CatchupGP -> 0 | ... BL52: =BL51*CatchupGP -> 724978.87
A53: of which LP | D53: =D51-D52 -> 0 | E53: =E51-E52 -> 0 | F53: =F51-F52 -> 0 | G53: =G51-G52 -> 0 | H53: =H51-H52 -> 0 | I53: =I51-I52 -> 0 | J53: =J51-J52 -> 0 | K53: =K51-K52 -> 0 | ... BL53: =BL51-BL52 -> 724978.87
A54: Remaining after Tier 5 | D54: =D47-D51 -> 0 | E54: =E47-E51 -> 0 | F54: =F47-F51 -> 0 | G54: =G47-G51 -> 0 | H54: =H47-H51 -> 0 | I54: =I47-I51 -> 0 | J54: =J47-J51 -> 0 | K54: =K47-K51 -> 0 | ... BL54: =BL47-BL51 -> 12504648
A55: Tier 6 — Residual to LP | D55: =D54*ResidLP -> 0 | E55: =E54*ResidLP -> 0 | F55: =F54*ResidLP -> 0 | G55: =G54*ResidLP -> 0 | H55: =H54*ResidLP -> 0 | I55: =I54*ResidLP -> 0 | J55: =J54*ResidLP -> 0 | K55: =K54*ResidLP -> 0 | ... BL55: =BL54*ResidLP -> 10003718
A56: Tier 6 — Residual to GP | D56: =D54-D55 -> 0 | E56: =E54-E55 -> 0 | F56: =F54-F55 -> 0 | G56: =G54-G55 -> 0 | H56: =H54-H55 -> 0 | I56: =I54-I55 -> 0 | J56: =J54-J55 -> 0 | K56: =K54-K55 -> 0 | ... BL56: =BL54-BL55 -> 2500929.5
A57: LP Profit (month) | D57: =D40+D53+D55 -> 0 | E57: =E40+E53+E55 -> 81218.524 | F57: =F40+F53+F55 -> 0 | G57: =G40+G53+G55 -> 0 | H57: =H40+H53+H55 -> 0 | I57: =I40+I53+I55 -> 0 | J57: =J40+J53+J55 -> 0 | K57: =K40+K53+K55 -> 0 | ... BL57: =BL40+BL53+BL55 -> 10795777
A58: GP Profit (month) | D58: =D42+D52+D56 -> 0 | E58: =E42+E52+E56 -> 9024.2805 | F58: =F42+F52+F56 -> 0 | G58: =G42+G52+G56 -> 0 | H58: =H42+H52+H56 -> 0 | I58: =I42+I52+I56 -> 0 | J58: =J42+J52+J56 -> 0 | K58: =K42+K52+K56 -> 0 | ... BL58: =BL42+BL52+BL56 -> 3237106.6
A59: Cumulative LP Profit | D59: =C59+D57 -> 0 | E59: =D59+E57 -> 81218.524 | F59: =E59+F57 -> 81218.524 | G59: =F59+G57 -> 81218.524 | H59: =G59+H57 -> 81218.524 | I59: =H59+I57 -> 81218.524 | J59: =I59+J57 -> 81218.524 | K59: =J59+K57 -> 81218.524 | ... BL59: =BK59+BL57 -> 15470225
A60: Cumulative GP Profit | D60: =C60+D58 -> 0 | E60: =D60+E58 -> 9024.2805 | F60: =E60+F58 -> 9024.2805 | G60: =F60+G58 -> 9024.2805 | H60: =G60+H58 -> 9024.2805 | I60: =H60+I58 -> 9024.2805 | J60: =I60+J58 -> 9024.2805 | K60: =J60+K58 -> 9024.2805 | ... BL60: =BK60+BL58 -> 3867556.2
A62: PARTNER CASH FLOWS
A63: LP Distributions | D63: =D40+D44+D53+D55 -> 0 | E63: =E40+E44+E53+E55 -> 217378.67 | F63: =F40+F44+F53+F55 -> 0 | G63: =G40+G44+G53+G55 -> 0 | H63: =H40+H44+H53+H55 -> 0 | I63: =I40+I44+I53+I55 -> 0 | J63: =J40+J44+J53+J55 -> 0 | K63: =K40+K44+K53+K55 -> 0 | ... BL63: =BL40+BL44+BL53+BL55 -> 21221598
A64: GP Distributions | D64: =D42+D46+D52+D56 -> 0 | E64: =E42+E46+E52+E56 -> 9024.2805 | F64: =F42+F46+F52+F56 -> 0 | G64: =G42+G46+G52+G56 -> 0 | H64: =H42+H46+H52+H56 -> 0 | I64: =I42+I46+I52+I56 -> 0 | J64: =J42+J46+J52+J56 -> 0 | K64: =K42+K46+K52+K56 -> 0 | ... BL64: =BL42+BL46+BL52+BL56 -> 4977567.3
A65: LP Net Cash Flow | D65: =D63-D13 -> -12623274 | E65: =E63-E13 -> 217378.67 | F65: =F63-F13 -> -37101.353 | G65: =G63-G13 -> -61571.795 | H65: =H63-H13 -> -58566.456 | I65: =I63-I13 -> -87461.988 | J65: =J63-J13 -> -169781.04 | K65: =K63-K13 -> -107347.04 | ... BL65: =BL63-BL13 -> 21221598
A66: GP Net Cash Flow | D66: =D64-D14 -> -1402586 | E66: =E64-E14 -> 9024.2805 | F66: =F64-F14 -> -4122.3726 | G66: =G64-G14 -> -6841.3105 | H66: =H64-H14 -> -6507.384 | I66: =I64-I14 -> -9717.9986 | J66: =J64-J14 -> -18864.56 | K66: =K64-K14 -> -11927.449 | ... BL66: =BL64-BL14 -> 4977567.3
A67: Total Equity Net CF | D67: =D65+D66 -> -14025860 | E67: =E65+E66 -> 226402.95 | F67: =F65+F66 -> -41223.726 | G67: =G65+G66 -> -68413.105 | H67: =H65+H66 -> -65073.84 | I67: =I65+I66 -> -97179.986 | J67: =J65+J66 -> -188645.6 | K67: =K65+K66 -> -119274.49 | ... BL67: =BL65+BL66 -> 26199165
A68: Total Unreturned Capital (EoP) | D68: =D23+D33 -> 14025860 | E68: =E23+E33 -> 13889700 | F68: =F23+F33 -> 13930923 | G68: =G23+G33 -> 13999337 | H68: =H23+H33 -> 14064410 | I68: =I23+I33 -> 14161590 | J68: =J23+J33 -> 14350236 | K68: =K23+K33 -> 14469510 | ... BL68: =BL23+BL33 -> 0
A70: RETURNS SUMMARY
A71: LP IRR | B71: =XIRR($D$65:$BL$65,$D$5:$BL$5) -> 0.19814531
A72: GP IRR | B72: =XIRR($D$66:$BL$66,$D$5:$BL$5) -> 0.30356701
A73: Deal IRR (Total Equity) | B73: =XIRR($D$67:$BL$67,$D$5:$BL$5) -> 0.21210951 | C73: =IF(ABS(B73)='Property Cash Flow'!B72,"OK","CHECK") -> OK
A74: LP Equity Multiple | B74: =SUM($D$63:$BL$63)/SUM($D$13:$BL$13) -> 1.98762
A75: GP Equity Multiple | B75: =SUM($D$64:$BL$64)/SUM($D$14:$BL$14) -> 3.222145
A76: Deal Equity Multiple | B76: =(SUM($D$63:$BL$63)+SUM($D$64:$BL$64))/SUM($D$9:$BL$9) -> 2.1110725
A77: Total Capital Called — Total | B77: =SUM($D$9:$BL$9) -> 17404608
A78: Total Capital Called — LP | B78: =SUM($D$13:$BL$13) -> 15664147
A79: Total Capital Called — GP | B79: =SUM($D$14:$BL$14) -> 1740460.8
A80: Peak Equity Outstanding — Total | B80: =MAX($D$68:$BL$68) -> 16207440
A81: Peak Equity Outstanding — LP | B81: =MAX($D$23:$BL$23) -> 14573080
A82: Peak Equity Outstanding — GP | B82: =MAX($D$33:$BL$33) -> 1740460.8
A83: GP Share of Total Profit | B83: =SUM($D$58:$BL$58)/(SUM($D$57:$BL$57)+SUM($D$58:$BL$58)) -> 0.2
A85: SENSE CHECKS
A86: Tier dists = Available, every month | B86: {=SUMPRODUCT(ABS($D$63:$BL$63+$D$64:$BL$64-$D$10:$BL$10))} -> 2.910383e-11 | C86: =IF(B86<0.01,"OK","CHECK") -> OK
A87: LP + GP Net CF = Levered CF, every month | B87: {=SUMPRODUCT(ABS($D$65:$BL$65+$D$66:$BL$66-$D$8:$BL$8))} -> 1.2369128e-10 | C87: =IF(B87<0.01,"OK","CHECK") -> OK
A88: Unreturned capital = 0 after exit | B88: =$BL$23+$BL$33 -> 0 | C88: =IF(ABS(B88)<0.01,"OK","CHECK") -> OK
A89: Accrued unpaid pref = 0 after exit | B89: =$BL$27+$BL$37 -> 0 | C89: =IF(ABS(B89)<0.01,"OK","CHECK") -> OK
A90: GP profit share ≥ target (catch-up complete) | B90: =B83-GPTarget -> 0 | C90: =IF(B90>=-0.001,"OK","CHECK") -> OK
A91: LP IRR < Deal IRR < GP IRR (promote intact) | C91: =IF(AND(B71<B73,B73<B72),"OK","CHECK") -> OK

Sheet Leverage Options
A1: Lender Quote Comparison — SouthPark Centre
B2: 2 | D2: 1 | E2: 2 | F2: 3
B3: Active Selection | D3: STALE QUOTE
A4: Term | B4: =OFFSET(C4,,$B$2) -> First Southeast Bank | D4: Atlantic Life Insurance | E4: First Southeast Bank | F4: Piedmont Capital
A5: Loan Type | B5: =OFFSET(C5,,$B$2) -> Construction-to-Permanent | D5: Construction-to-Permanent | E5: Construction-to-Permanent | F5: Construction-to-Permanent
A6: Rate Type | B6: =OFFSET(C6,,$B$2) -> Floating (swapped) | D6: Floating (swapped) | E6: Floating (swapped) | F6: Floating (swapped)
A7: Spread | B7: =OFFSET(C7,,$B$2) -> SOFR + 275 bps | D7: SOFR + 200 bps | E7: SOFR + 275 bps | F7: SOFR + 250 bps
A8: Current SOFR | B8: =OFFSET(C8,,$B$2) -> 4.35% | D8: 4.35% | E8: 4.35% | F8: 4.35%
A9: All-In Rate (indicative) | B9: =OFFSET(C9,,$B$2) -> 7.10% | D9: 6.35% | E9: 7.10% | F9: 6.85%
A10: Maximum LTC | B10: =OFFSET(C10,,$B$2) -> 75% | D10: 80% | E10: 75% | F10: 70%
A11: Maximum LTV (stabilized) | B11: =OFFSET(C11,,$B$2) -> 70% | D11: 75% | E11: 70% | F11: 65%
A12: Min DSCR at Conversion (NOI based) | B12: =OFFSET(C12,,$B$2) -> 1.25 | D12: 1.15 | E12: 1.25 | F12: 1.2
A13: Conversion Month | B13: =OFFSET(C13,,$B$2) -> 36 | D13: 36 | E13: 36 | F13: 36
A14: Closing Costs | B14: =OFFSET(C14,,$B$2) -> 0.015 | D14: 0.015 | E14: 0.015 | F14: 0.015
A15: Interest-Only Period | B15: =OFFSET(C15,,$B$2) -> 24 months from close | D15: 36 months from close | E15: 24 months from close | F15: 18 months from close
A16: Amortization (after conversion) | B16: 30 | D16: 30 | E16: 25 | F16: 30
A17: Term | B17: =OFFSET(C17,,$B$2) -> 5 | D17: 10 | E17: 5 | F17: 7
A18: Extension Options | B18: =OFFSET(C18,,$B$2) -> 1 x 1-year (subject to DSCR test) | D18: None | E18: 1 x 1-year (subject to DSCR test) | F18: 2 x 1-year
A19: Recourse | B19: =OFFSET(C19,,$B$2) -> Non-recourse with standard carve-outs | D19: Non-recourse | E19: Non-recourse with standard carve-outs | F19: 25% recourse during construction; non-recourse at conversion
A20: Origination Fee | B20: =OFFSET(C20,,$B$2) -> 1.00% | D20: 0.50% | E20: 1.00% | F20: 0.75%
A21: Prepayment | B21: =OFFSET(C21,,$B$2) -> Open after Year 2 | D21: Yield maintenance Years 1-7; 1% Years 8-9; open Year 10 | E21: Open after Year 2 | F21: 1% in Year 1, open after
A22: Interest Reserve | B22: =OFFSET(C22,,$B$2) -> PIK During Construction | D22: PIK During Construction | E22: PIK During Construction | F22: PIK During Construction
A25: Imputed Figures
A26: Max Dev Loan | B26: =B10*'Property Cash Flow'!$B$36 -> 46146437 | D26: =D10*'Property Cash Flow'!$B$36 -> 49222866 | E26: =E10*'Property Cash Flow'!$B$36 -> 46146437 | F26: =F10*'Property Cash Flow'!$B$36 -> 43070008
A27: Max Permanent Loan (LTV stabilized) | B27: =+B11*'Exit Analysis'!$B$16 -> 57936597 | D27: =+D11*'Exit Analysis'!$B$16 -> 62074926 | E27: =+E11*'Exit Analysis'!$B$16 -> 57936597 | F27: =+F11*'Exit Analysis'!$B$16 -> 53798269
A28: Max Permanent Loan (DSCR at Conversion) | B28: =SUMIFS('Property Cash Flow'!$L$19:$CF$19,'Property Cash Flow'!$L$4:$CF$4,">="&'Leverage Options'!B13,'Property Cash Flow'!$L$4:$CF$4,"<"&('Leverage Options'!B13+12))/B12/B9 -> 66929781 | D28: =SUMIFS('Property Cash Flow'!$L$19:$CF$19,'Property Cash Flow'!$L$4:$CF$4,">="&'Leverage Options'!D13,'Property Cash Flow'!$L$4:$CF$4,"<"&('Leverage Options'!D13+12))/D12/D9 -> 81342254 | E28: =SUMIFS('Property Cash Flow'!$L$19:$CF$19,'Property Cash Flow'!$L$4:$CF$4,">="&'Leverage Options'!E13,'Property Cash Flow'!$L$4:$CF$4,"<"&('Leverage Options'!E13+12))/E12/E9 -> 66929781 | F28: =SUMIFS('Property Cash Flow'!$L$19:$CF$19,'Property Cash Flow'!$L$4:$CF$4,">="&'Leverage Options'!F13,'Property Cash Flow'!$L$4:$CF$4,"<"&('Leverage Options'!F13+12))/F12/F9 -> 72262994
A32: Lender Scenario Analysis (sensitivity)
B33: Active | D33: =D4 -> Atlantic Life Insurance | E33: =E4 -> First Southeast Bank | F33: =F4 -> Piedmont Capital | H33: Max
D34: =D2 -> 1 | E34: =E2 -> 2 | F34: =F2 -> 3
A35: Levered IRR | B35: =IF(OFFSET($C$3,,$B$2)="STALE QUOTE","ERROR",'Property Cash Flow'!B72) -> 0.21210951 | C35: =B35 -> 0.21210951 | D35: ERROR | E35: 0.21210951 | F35: 0.19834606 | H35: {=INDEX(D$33:F$33,,MATCH(MAX(D35:F35),D35:F35,0))} -> First Southeast Bank
A36: Levered MoIC | B36: =IF(OFFSET($C$3,,$B$2)="STALE QUOTE","ERROR",'Property Cash Flow'!B75) -> 2.1110725 | C36: =B36 -> 2.1110725 | D36: ERROR | E36: 2.1110725 | F36: 2.0659995 | H36: {=INDEX(D$33:F$33,,MATCH(MAX(D36:F36),D36:F36,0))} -> First Southeast Bank

Sheet Exit Analysis
A1: SouthPark Centre — Exit Analysis
A3: EXIT VALUATION
A4: Exit Month | B4: =HoldMonths -> 60 | C4: = Hold Period
A5: Forward 12-Month NOI | B5: =SUM(OFFSET('Property Cash Flow'!M19,0,'Exit Analysis'!B4,1,12)) -> 6545315.3 | C5: NOI, months 61-72 | E5: =B5/SUM(B13:B14) -> -0.10637845
A6: Exit Cap Rate | B6: =ExitCap -> 0.0775
A7: Gross Exit Value | B7: =B5/B6 -> 84455681
A8: Exit Value $/SF | B8: =B7/BldgSF -> 301.62743
A9: Less: Disposition Costs | B9: =-B7*DispCost -> -1689113.6
A10: Net Sale Proceeds | B10: =B7+B9 -> 82766568
A12: UNLEVERED RETURN SUMMARY
A13: Purchase Price (net) | B13: =-PurchasePrice*(1+Assumptions!B7) -> -51500000
A14: Additional Capital Required | B14: =-'Property Cash Flow'!B36-'Exit Analysis'!B13 -> -10028582
A15: Operating Profit during Hold | B15: =SUM('Property Cash Flow'!E27:J27) -> 7651534 | C15: Months 1–60, before sale
A16: Net Sale Proceeds (exit) | B16: =B10 -> 82766568
A17: Total Profit | B17: =SUM(B13:B16) -> 28889519
A18: Equity Multiple (unlevered) | B18: =(B15+B16)/PurchasePrice -> 1.808362
A21: SENSE CHECKS
A22: Rent Roll SF = Building SF | B22: ='Rent Roll'!F36 -> 0 | C22: =IF(B22=0,"OK","CHECK") -> OK
A23: Year-5 NOI positive | B23: ='Property Cash Flow'!I19 -> 6312430.3 | C23: =IF(B23>0,"OK","CHECK") -> OK
A24: Exit value > purchase price | B24: =B7-PurchasePrice -> 34455681 | C24: =IF(B24>0,"OK","CHECK") -> OK

Sheet Sales Comp Analysis
A1: # | B1: Address | C1: Submarket | D1: Class | E1: SF | F1: Sale Date | G1: Price ($) | H1: $/SF | I1: Cap Rate | J1: Occ at Sale | K1: Buyer Type | L1: Notes | M1: Comp Type (see legend)
A2: 1 | B2: 5200 Park Road | C2: SouthPark | D2: B+ | E2: 185000 | F2: 03/15/2026 | G2: 45120000 | H2: =IFERROR(G2/E2,"N/A") -> 243.89189 | I2: 0.078 | J2: 0.82 | K2: Private Equity | L2: Value-add buyer. Similar size and class to subject. | M2: 1
A3: 2 | B3: 6800 Morrison Boulevard | C3: SouthPark | D3: A | E3: 142000 | F3: 11/08/2025 | G3: 52480000 | H3: =IFERROR(G3/E3,"N/A") -> 369.57746 | I3: 0.062 | J3: 0.94 | K3: REIT | L3: Class A. Sets ceiling for renovated value. | M3: 1
A4: 3 | B4: 4400 Sharon Road | C4: SouthPark | D4: B | E4: 98000 | F4: 08/22/2025 | G4: 20000000 | H4: =IFERROR(G4/E4,"N/A") -> 204.08163 | I4: 0.085 | J4: 0.71 | K4: Private | L4: Lower quality B. Floor for unrenovated product. | M4: 1
A5: 4 | B5: 7000 Fairview Road | C5: SouthPark | D5: B+ | E5: 220000 | F5: 05/03/2025 | G5: 56320000 | H5: =IFERROR(G5/E5,"N/A") -> 256 | I5: 0.072 | J5: 0.88 | K5: Institutional | L5: Recently renovated lobby. Good post-reno comparable. | M5: 1
A6: 5 | B6: 1200 Barclay Downs Drive | C6: SouthPark | D6: B | E6: 65000 | F6: 02/14/2025 | G6: 12480000 | H6: =IFERROR(G6/E6,"N/A") -> 192 | I6: 0.091 | J6: 0.75 | K6: Private | L6: Small building. High cap reflects size and risk. | M6: 1
A7: 6 | B7: 3100 Randolph Road | C7: Midtown | D7: B+ | E7: 155000 | F7: 12/05/2025 | G7: 37200000 | H7: =IFERROR(G7/E7,"N/A") -> 240 | I7: 0.075 | J7: 0.85 | K7: Private Equity | L7: Different submarket but similar profile. | M7: 1
A8: 7 | B8: 8500 University Executive Park | C8: University City | D8: A- | E8: 175000 | F8: 06/20/2025 | G8: 49000000 | H8: =IFERROR(G8/E8,"N/A") -> 280 | I8: 0.068 | J8: 0.91 | K8: Institutional | L8: University City. Quality reference point. | M8: 1
A9: 8 | B9: 2200 Rexford Road | C9: SouthPark | D9: B+ | E9: 110000 | F9: 09/12/2025 | G9: 28864000 | H9: =IFERROR(G9/E9,"N/A") -> 262.4 | I9: 0.073 | J9: 0.84 | K9: Private | L9: Very close in $/SF to subject asking price. | M9: 1
A10: 9 | B10: 4100 Barclay Downs Drive | C10: SouthPark | D10: B+ | E10: 95000 | F10: 01/20/2026 | G10: 24320000 | H10: =IFERROR(G10/E10,"N/A") -> 256 | I10: 0.076 | J10: 0.8 | K10: Private Equity | L10: Recent trade. Good current benchmark. | M10: 1
A11: 10 | B11: 5600 Fairview Road | C11: SouthPark | D11: B | E11: 130000 | F11: 07/18/2025 | G11: 28080000 | H11: =IFERROR(G11/E11,"N/A") -> 216 | I11: 0.082 | J11: 0.77 | K11: Private | L11: Larger B building. Below subject pricing. | M11: 1
A12: 11 | B12: 3400 Coltsgate Road | C12: SouthPark | D12: B+ | E12: 88000 | F12: 04/10/2025 | G12: 21120000 | H12: =IFERROR(G12/E12,"N/A") -> 240 | I12: 0.074 | J12: 0.86 | K12: Institutional | L12: Smaller but comparable class. | M12: 1
A13: 12 | B13: 6100 Piedmont Row Drive | C13: SouthPark | D13: A- | E13: 160000 | F13: 10/25/2025 | G13: 49920000 | H13: =IFERROR(G13/E13,"N/A") -> 312 | I13: 0.065 | J13: 0.92 | K13: REIT | L13: Class A-. Upper end of range. | M13: 1
A14: 13 | B14: 4500 Cameron Valley Parkway | C14: SouthPark | D14: B+ | E14: 125000 | F14: 03/10/2009 | G14: 13600000 | H14: =IFERROR(G14/E14,"N/A") -> 108.8 | I14: N/A | J14: 0.52 | K14: Distressed Buyer | L14: GFC distressed sale. Bank-directed. | M14: 2
A15: 14 | B15: 6200 Fairview Road | C15: SouthPark | D15: B | E15: 150000 | F15: 11/20/2009 | G15: 22800000 | H15: =IFERROR(G15/E15,"N/A") -> 152 | I15: N/A | J15: 0.6 | K15: Opportunity Fund | L15: GFC REO sale. | M15: 2
A16: 15 | B16: 3300 Park Road | C16: SouthPark | D16: B+ | E16: 163000 | F16: 07/15/2020 | G16: 35200000 | H16: =IFERROR(G16/E16,"N/A") -> 215.95092 | I16: 0.089 | J16: 0.7 | K16: Private | L16: COVID pricing. 12% below pre-COVID basis. | M16: 2
A17: 16 | B17: 5100 Sharon Road | C17: SouthPark | D17: B | E17: 100000 | F17: 12/03/2020 | G17: 18880000 | H17: =IFERROR(G17/E17,"N/A") -> 188.8 | I17: 0.095 | J17: 0.65 | K17: Private Equity | L17: Deep COVID discount. | M17: 2
A18: 17 | B18: 7800 Colony Road | C18: SouthPark | D18: B+ | E18: 140000 | F18: 09/22/2020 | G18: 29120000 | H18: =IFERROR(G18/E18,"N/A") -> 208 | I18: 0.087 | J18: 0.72 | K18: Private | L18: COVID-era trade. | M18: 2
A19: 18 | B19: 7200 Pineville-Matthews Road | C19: South Charlotte | D19: B+ | E19: 160000 | F19: 01/28/2026 | G19: 31200000 | H19: =IFERROR(G19/E19,"N/A") -> 195 | I19: N/A | J19: N/A | K19: Unknown | L19: Cap rate and occupancy not disclosed. | M19: 3
A20: 19 | B20: 9800 Northlake Centre Parkway | C20: Northlake | D20: B | E20: 130000 | F20: 04/10/2025 | G20: N/A | H20: =IFERROR(G20/E20,"N/A") -> N/A | I20: N/A | J20: 0.78 | K20: Unknown | L20: Price not disclosed. Only occ available. | M20: 3
A21: 20 | B21: 2800 Selwyn Avenue | C21: Myers Park | D21: A | E21: 72000 | F21: 06/15/2025 | G21: 26496000 | H21: =IFERROR(G21/E21,"N/A") -> 368 | I21: N/A | J21: 0.96 | K21: Private | L21: Cap rate not available. | M21: 3
A22: 21 | B22: 4300 Park Road | C22: SouthPark | D22: B+ | E22: 115000 | F22: 03/05/2026 | G22: 29440000 | H22: =IFERROR(G22/E22,"N/A") -> 256 | I22: N/A | J22: N/A | K22: Private Equity | L22: Cap rate and occ missing. | M22: 3
A23: 22 | B23: 401 South Tryon Street | C23: Uptown CBD | D23: A | E23: 350000 | F23: 08/18/2025 | G23: 156800000 | H23: =IFERROR(G23/E23,"N/A") -> 448 | I23: 0.055 | J23: 0.9 | K23: Institutional | L23: Uptown CBD tower. Wrong submarket, wrong size class. | M23: 4
A24: 23 | B24: 1100 South Mint Street | C24: South End | D24: A | E24: 210000 | F24: 11/10/2025 | G24: 84000000 | H24: =IFERROR(G24/E24,"N/A") -> 400 | I24: 0.06 | J24: 0.93 | K24: REIT | L24: South End. Different market dynamics entirely. | M24: 4
A25: 24 | B25: 8200 Arrowridge Boulevard | C25: Airport/I-77 | D25: Flex | E25: 85000 | F25: 05/08/2025 | G25: 10880000 | H25: =IFERROR(G25/E25,"N/A") -> 128 | I25: 0.092 | J25: 0.88 | K25: Private | L25: Flex/industrial product. Wrong property type. | M25: 4
A26: 25 | B26: 3800 Arco Corporate Drive | C26: Ballantyne | D26: B+ | E26: 45000 | F26: 02/22/2025 | G26: 8640000 | H26: =IFERROR(G26/E26,"N/A") -> 192 | I26: 0.084 | J26: 0.8 | K26: Private | L26: Too small (45K SF vs 280K subject). | M26: 4
A27: Average of Current Market Comps | E27: =AVERAGEIFS(E$2:E$26,$M$2:$M$26,$M27) -> 135250 | G27: =AVERAGEIFS(G$2:G$26,$M$2:$M$26,$M27) -> 35408667 | H27: =AVERAGEIFS(H$2:H$26,$M$2:$M$26,$M27) -> 255.99592 | I27: =AVERAGEIFS(I$2:I$26,$M$2:$M$26,$M27) -> 0.075083333 | J27: =AVERAGEIFS(J$2:J$26,$M$2:$M$26,$M27) -> 0.8375 | M27: 1
A28: Average of Crisis Era Comps | E28: =AVERAGEIFS(E$2:E$26,$M$2:$M$26,$M28) -> 135600 | G28: =AVERAGEIFS(G$2:G$26,$M$2:$M$26,$M28) -> 23920000 | H28: =AVERAGEIFS(H$2:H$26,$M$2:$M$26,$M28) -> 174.71018 | I28: =AVERAGEIFS(I$2:I$26,$M$2:$M$26,$M28) -> 0.090333333 | J28: =AVERAGEIFS(J$2:J$26,$M$2:$M$26,$M28) -> 0.638 | M28: 2
A29: Target Property (Going-in) | E29: =BldgSF -> 280000 | G29: =-('Property Cash Flow'!D29+'Property Cash Flow'!D30) -> 51500000 | H29: =G29/E29 -> 183.92857 | I29: ='Property Cash Flow'!E19/'Sales Comp Analysis'!G29 -> 0.05743247 | J29: ='Property Cash Flow'!E6 -> 0.68791667
A30: Target Property (Underwritten) | E30: =E29 -> 280000 | G30: ='Exit Analysis'!B16 -> 82766568 | H30: =G30/E30 -> 295.59488 | I30: =ExitCap -> 0.0775 | J30: =SUMIFS('Property Cash Flow'!D6:J6,'Property Cash Flow'!D4:J4,HoldMonths) -> 0.97738095
B33: Legend:
B34: (1) White = current market comps (primary benchmarks)
B35: (2) Yellow = crisis-era trades (stress-test / floor) | D35: #FFF2CC
B36: (3) Gray = incomplete data (exclude from statistics) | D36: #F2F2F2
B37: (4) Pink = non-comparable (wrong submarket/type/size) | D37: #FCE4EC

Sheet Rental Comp Analysis
A1: # | B1: Address | C1: Submarket | D1: Tenant | E1: SF | F1: Lease Date | G1: Term (yr) | H1: Rent $/SF (NNN) | I1: Escalation | J1: TI $/SF | K1: Free Rent (mo) | L1: Notes | M1: Comp Type (see legend)
A2: 1 | B2: Ballantyne Corporate Center | C2: Ballantyne | D2: Meridian Financial Group | E2: 80000 | F2: 01/15/2026 | G2: 15 | H2: 28.5 | I2: 0.03 | J2: 55 | K2: 6 | L2: Build-to-suit. ONLY transaction >30,000 SF in this dataset. | M2: 1
A3: 2 | B3: 5400 Park South Drive | C3: SouthPark | D3: Southeast Analytics LLC | E3: 11960 | F3: 03/01/2026 | G3: 7 | H3: 25.5 | I3: 0.025 | J3: 38 | K3: 2 | L3: Renovated B+ building. | M3: 2
A4: 3 | B4: 6200 Fairview Road | C4: SouthPark | D4: Apex Advisory Group | E4: 8740 | F4: 12/10/2025 | G4: 5 | H4: 24.5 | I4: 0.025 | J4: 33 | K4: 1 | L4: Unrenovated B+. | M4: 2
A5: 4 | B5: 4200 Sharon Road | C5: SouthPark | D5: Trident Capital Partners | E5: 10350 | F5: 10/22/2025 | G5: 7 | H5: 26 | I5: 0.03 | J5: 40 | K5: 2 | L5: Recently renovated space. | M5: 2
A6: 5 | B6: 7100 Fairview Road | C6: SouthPark | D6: Palmer & Associates CPA | E6: 14030 | F6: 08/05/2025 | G6: 5 | H6: 24 | I6: 0.025 | J6: 30 | K6: 1 | L6: Unrenovated. Reflects current-condition market. | M6: 2
A7: 6 | B7: 5800 Morrison Boulevard | C7: SouthPark | D7: Waverly Tech Inc | E7: 18860 | F7: 06/18/2025 | G7: 10 | H7: 27 | I7: 0.03 | J7: 45 | K7: 3 | L7: Largest recent small-block lease. Class A- building. | M7: 2
A8: 7 | B8: 4600 Park Road | C8: SouthPark | D8: Bridgewater Legal Group | E8: 7360 | F8: 05/02/2025 | G8: 5 | H8: 23.5 | I8: 0.025 | J8: 28 | K8: 1 | L8: Small suite in unrenovated building. | M8: 2
A9: 8 | B9: 6400 Carmel Road | C9: SouthPark | D9: Carolina Med Group | E9: 11040 | F9: 04/15/2025 | G9: 7 | H9: 24.5 | I9: 0.025 | J9: 36 | K9: 2 | L9: Standard office TI package. | M9: 2
A10: 9 | B10: 5200 Park South Drive | C10: SouthPark | D10: Nexus Financial Corp | E10: 17250 | F10: 02/28/2025 | G10: 7 | H10: 25.5 | I10: 0.025 | J10: 38 | K10: 2 | L10: Mid-size professional services. | M10: 2
A11: 10 | B11: 6800 Morrison Boulevard | C11: SouthPark | D11: DataStream Corp | E11: 13340 | F11: 01/12/2025 | G11: 5 | H11: 26.5 | I11: 0.03 | J11: 35 | K11: 1 | L11: Class A building. Premium location. | M11: 2
A12: 11 | B12: 4400 Sharon Road | C12: SouthPark | D12: Vanguard Consulting LLC | E12: 8280 | F12: 11/05/2024 | G12: 3 | H12: 23 | I12: 0.02 | J12: 25 | K12: 0 | L12: Short term. Tenant-funded buildout. | M12: 2
A13: 12 | B13: 7000 Fairview Road | C13: SouthPark | D13: Summit Group LLC | E13: 9660 | F13: 09/20/2024 | G13: 5 | H13: 24.5 | I13: 0.025 | J13: 32 | K13: 1 | L13: Recently renovated building. | M13: 2
... A43: 42 | B43: 7800 Distribution Drive | C43: Airport/I-77 | D43: Flex Logistics Inc | E43: 27600 | F43: 05/10/2025 | G43: 5 | H43: 14.5 | I43: 0.02 | J43: 15 | K43: 0 | L43: Flex/warehouse. Wrong property type. | M43: 5
A44: 43 | B44: 1200 Old Pineville Road | C44: South Charlotte | D44: Budget Office Co | E44: 14950 | F44: 11/15/2025 | G44: 3 | H44: 16 | J44: 10 | K44: 0 | L44: Class C office. Not comparable. | M44: 5
A45: 44 | B45: 9400 Warehouse Boulevard | C45: Airport/I-77 | D45: QuickShip Dist LLC | E45: 22540 | F45: 03/08/2025 | G45: 7 | H45: 12.5 | I45: 0.02 | J45: 8 | K45: 0 | L45: Industrial distribution. Wrong type. | M45: 5
A46: 45 | B46: 4500 Medical Center Dr | C46: SouthPark | D46: Med Imaging LLC | E46: 17020 | F46: 07/18/2025 | G46: 10 | H46: 35 | I46: 0.03 | J46: 70 | K46: 0 | L46: Medical imaging suite. Specialized build. | M46: 5
A47: 46 | B47: 5500 Park Road | C47: SouthPark | D47: Delta Advisory LLC | E47: 11040 | F47: 02/10/2026 | G47: N/A | H47: N/A | J47: N/A | K47: N/A | L47: Missing rent, term, and TI data. | M47: 6
A48: 47 | B48: 4200 Sharon Road | C48: SouthPark | D48: Sigma Partners Inc | E48: 14260 | F48: 10/05/2025 | G48: 5 | H48: 24.5 | J48: 35 | K48: 2 | L48: Missing escalation data. | M48: 6
A49: 48 | B49: 6100 Fairview Road | C49: SouthPark | D49: Omega Group LLC | E49: 8050 | F49: 06/20/2025 | G49: 7 | H49: N/A | I49: 0.025 | J49: N/A | K49: N/A | L49: Missing rent, TI, and free rent. | M49: 6
A50: 49 | B50: 3800 Morrison Boulevard | C50: SouthPark | D50: Lambda Corp | E50: 11730 | F50: 12/08/2025 | G50: N/A | H50: 25 | J50: N/A | K50: 1 | L50: Missing term and TI. | M50: 6
A51: 50 | B51: 5900 Carmel Road | C51: SouthPark | D51: Theta Financial Inc | E51: 10120 | F51: 08/25/2025 | G51: 5 | H51: N/A | I51: 0.025 | J51: 32 | K51: N/A | L51: Missing rent and free rent. | M51: 6
A52: Average of Current Market Comps | E52: =AVERAGEIFS(E$2:E$51,$M$2:$M$51,$M52) -> 12015.2 | G52: =AVERAGEIFS(G$2:G$51,$M$2:$M$51,$M52) -> 5.92 | H52: =AVERAGEIFS(H$2:H$51,$M$2:$M$51,$M52) -> 24.98 | I52: =AVERAGEIFS(I$2:I$51,$M$2:$M$51,$M52) -> 0.0258 | J52: =AVERAGEIFS(J$2:J$51,$M$2:$M$51,$M52) -> 34.6 | K52: =AVERAGEIFS(K$2:K$51,$M$2:$M$51,$M52) -> 1.44 | M52: 2
A53: Target Property Underwriting (Vacancy) | E53: =AVERAGE('Rent Roll'!F41:F46) -> 12666.667 | H53: =AVERAGE(Assumptions!C56:C59) -> 24.875 | I53: =+RentGrowth -> 0.027 | J53: =AVERAGE(Assumptions!F56:F59) -> 34 | K53: =AVERAGE(Assumptions!I56:J59) -> 1.5
B55: (1) Yellow highlight = Meridian BTS (only large-block transaction) | D55: #FFF2CC
B56: (2) White = current comps, SouthPark area (usable benchmarks)
B57: (3) Gray = older transactions (2023 or earlier) | D57: #F2F2F2
B58: (4) Purple = wrong submarket | D58: #E8EAF6
B59: (5) Pink = wrong property type/class | D59: #FCE4EC
B60: (6) Light yellow = incomplete data | D60: #FFF9C4

Sheet Pure Reference--->

Sheet T-12 Operating Statement
A1: Line Item | B1: Jun 2025 | C1: Jul 2025 | D1: Aug 2025 | E1: Sep 2025 | F1: Oct 2025 | G1: Nov 2025 | H1: Dec 2025 | I1: Jan 2026 | J1: Feb 2026 | K1: Mar 2026 | L1: Apr 2026 | M1: May 2026 | N1: TOTAL
A2: REVENUE
A3: Base Rental Revenue | B3: 371400 | C3: 371400 | D3: 371400 | E3: 371400 | F3: 371400 | G3: 371400 | H3: 371400 | I3: 371400 | J3: 371400 | K3: 371400 | L3: 368700 | M3: 368700 | N3: =SUM(B3:M3) -> 4451400
A4: Expense Reimbursements | B4: 190554 | C4: 190554 | D4: 190554 | E4: 190554 | F4: 190554 | G4: 190554 | H4: 190554 | I4: 190554 | J4: 190554 | K4: 190554 | L4: 188984 | M4: 188984 | N4: =SUM(B4:M4) -> 2283508
A5: Parking Income | B5: 19167 | C5: 19167 | D5: 19167 | E5: 19167 | F5: 19167 | G5: 19167 | H5: 19167 | I5: 19167 | J5: 19167 | K5: 19167 | L5: 19167 | M5: 19167 | N5: =SUM(B5:M5) -> 230004
A6: Antenna / Telecom Income | B6: 5167 | C6: 5167 | D6: 5167 | E6: 5167 | F6: 5167 | G6: 5167 | H6: 5167 | I6: 5167 | J6: 2667 | K6: 2667 | L6: 2667 | M6: 2667 | N6: =SUM(B6:M6) -> 52004
A7: Storage Income | B7: 1667 | C7: 1667 | D7: 1667 | E7: 1667 | F7: 1667 | G7: 1667 | H7: 1667 | I7: 1667 | J7: 1667 | K7: 1667 | L7: 1667 | M7: 1667 | N7: =SUM(B7:M7) -> 20004
A8: Other Income - Lease Termination Fee | B8: 0 | C8: 0 | D8: 0 | E8: 0 | F8: 0 | G8: 42000 | H8: 0 | I8: 0 | J8: 0 | K8: 0 | L8: 0 | M8: 0 | N8: =SUM(B8:M8) -> 42000
A10: TOTAL REVENUE | B10: =SUM(B3:B8) -> 587955 | C10: =SUM(C3:C8) -> 587955 | D10: =SUM(D3:D8) -> 587955 | E10: =SUM(E3:E8) -> 587955 | F10: =SUM(F3:F8) -> 587955 | G10: =SUM(G3:G8) -> 629955 | H10: =SUM(H3:H8) -> 587955 | I10: =SUM(I3:I8) -> 587955 | ... M10: =SUM(M3:M8) -> 581185 | N10: =SUM(B10:M10) -> 7078920
A12: OPERATING EXPENSES
A13: Real Estate Taxes | B13: 61833 | C13: 61833 | D13: 61833 | E13: 61833 | F13: 61833 | G13: 61833 | H13: 61833 | I13: 61833 | J13: 61833 | K13: 61833 | L13: 61833 | M13: 61833 | N13: =SUM(B13:M13) -> 741996
A14: Insurance | B14: 17500 | C14: 17500 | D14: 17500 | E14: 17500 | F14: 17500 | G14: 17500 | H14: 17500 | I14: 17500 | J14: 17500 | K14: 17500 | L14: 17500 | M14: 17500 | N14: =SUM(B14:M14) -> 210000
A15: Utilities | B15: 58333 | C15: 58333 | D15: 58333 | E15: 58333 | F15: 58333 | G15: 58333 | H15: 58333 | I15: 58333 | J15: 58333 | K15: 58333 | L15: 58333 | M15: 58333 | N15: =SUM(B15:M15) -> 699996
A16: Repairs & Maintenance | B16: 40833 | C16: 40833 | D16: 40833 | E16: 40833 | F16: 40833 | G16: 40833 | H16: 40833 | I16: 40833 | J16: 40833 | K16: 40833 | L16: 40833 | M16: 40833 | N16: =SUM(B16:M16) -> 489996
A17: Janitorial / Cleaning | B17: 31500 | C17: 31500 | D17: 31500 | E17: 31500 | F17: 31500 | G17: 31500 | H17: 31500 | I17: 31500 | J17: 31500 | K17: 31500 | L17: 31500 | M17: 31500 | N17: =SUM(B17:M17) -> 378000
A18: Landscaping & Grounds | B18: 7000 | C18: 7000 | D18: 7000 | E18: 7000 | F18: 7000 | G18: 7000 | H18: 7000 | I18: 7000 | J18: 7000 | K18: 7000 | L18: 7000 | M18: 7000 | N18: =SUM(B18:M18) -> 84000
